Workbook

Sheet Updates
A1: Battle Dome 4 updates (Beta)
A3: Current Patch: | B3: Beta 4.2
B5: Upcoming Patch: | D5: NONE
B6: Release Date: | D6: -
A8: Patch number | B8: Release date | C8: Summary
A9: 4.0.02 | B9: 16/8/16 | C9: Basic skill nerfs to polearm and skirmisher.
A10: 4.0.03 | B10: 24/8/16 | C10: Many ability changes for just about every class/branch.
A11: 4.0.04 | B11: 42630 | C11: Nerfs to skills and adjustments to level requirements.
A12: 4.0.05 | B12: 42637 | C12: Nerfs / Buffs to skills, adjustment to transferring weapons/classes, clarifying moves, and a new game mode.
A13: 4.0.06 | B13: 42643 | C13: Rapier buff, adjustment to skills.
A14: 4.0.07 | B14: 8/10/16 | C14: Small buffs, MR changes and Claws nerf.
A15: 4.0.08 | B15: 15/10/16 | C15: Shortbow + Katana buff, new cycle bonus.
A16: 4.0.09 | B16: 22/10/16 | C16: Axe Rework, MR changes and some adjustments.
A17: 4.0.10 | B17: 29/10/16 | C17: Skill Adjustment and Mechanic Changes.
A18: 4.0.11 | B18: 05/11/16 | C18: Move adjustments + Stat changes
A19: 4.0.12 | B19: 12/11/16 | C19: Skill adjustments and important overhaul of patch notes
A20: =HYPERLINK("https://docs.google.com/document/d/1OmgOHDN7s3SCsoJlMlG9kzIdx8Z65RSWNFO3LQwyQ-4/edit","See the changelog for changes past 4.0.12!") -> See the changelog for changes past 4.0.12!

Sheet 4.0 Mechanic Reversions
A1: The following is a list of mechanic changes between 4.1 and 4.0. This will explain things from 4.0's perspective: - Critical Hits only double the dice, not the modifier (so a 2d8+15 attack becomes 4d8+15) - The Defense stat has been removed - AoO will only apply to ranged attacks (this includes ranged attacks used in melee) - The EoT restriction will function differently: the only restriction is that you may not use an EoT move on the turn after you have used another EoT move (eg, you can go Twice -> EoT -> Once, but not EoT -> Twice/EoT) - Stats are a combination of class and weapon stats, rather than just clas stats, allowing for greater diversity - Moves have changed, so they will have different rolls, effects, MRs, etc. than in 4.1.

Sheet 4.0.12
A1: 4.0.12
A2: Release Date: | B2: 42715
A4: General
B5: Statuses
C6: Burn now reduces accuracy by 2 as an added side effect. Bleed reduces the targets damage by 5 as an added side effect.
C7: NEW STATUS: Poison: May deal passive damage to the foe, reduces foes evasion by 2
B8: EXP
C9: Teams get +1 XP
A10: Class
B11: Pyrokinetic
C12: Inferno
D13: Requires 1 Fire Stack minimum to use and no longer adds MAG.
B14: Rifter
C15: Levels
D16: Time Dilation and Wormhole have swapped levels
A17: Weapon
B18: Hammer
C19: Crush
D20: 2d8+5 | E20: 1d8+10 extra damage if the opponent is pushed either into another player or a wall
C21: Gale Force
D22: 2d8+5 | E22: 1d8+10 extra damage if target used the same move as last turn
B23: Bo Staff
C24: Tornado
D25: Confuses for 2 turns on 16+
B26: Rapier
C27: New level 1 move - Precision
D28: Similarly to Berserk, Rapiers may choose to gain -5 damage and +2 accuracy or -10 damage and +4 accuracy on their attacks.
B29: Polearm
C30: Levels
D31: Power Swing and Leg Sweep swapped
B32: Orb
C33: Spirit Shackle
D34: Can only target a maximum of 3 players now.
B35: Katana
C36: Nihonto
D37: MR4 now + Once
C38: Slice
D39: 2d8+8
C40: Fallen Blade
B41: Tonfa | D41: -1 acc now
C42: Leash
D43: MR4
B44: Stave
C45: Storm Smash
D46: Every Turn->EoT

Sheet 4.0.11
A1: 4.0.10
A2: Release Date: | B2: 12/11/16
A4: General
B5: Statuses | D5: V IMPLEMENTED ON THURSDAY V
C6: Burn now reduces accuracy by 2 as an added side effect. Bleed reduces the targets damage by 5 as an added side effect.
C7: NEW STATUS: Poison: May deal passive damage to the foe, reduces foes evasion by 2
B8: EXP
C9: Teams get +1 XP
A10: Class
A14: Weapon
B15: Hammer
C16: Crush
D17: 2d8+5 | E17: 1d8+10 extra damage if the opponent is pushed either into another player or a wall
C18: Gale Force
D19: 2d8+5 | E19: 1d8+10 extra damage if target used the same move as last turn
B20: Bo Staff
C21: Tornado
D22: Confuses for 2 turns on 16+
B23: Rapier
C24: New level 1 move - Precision
D25: Similarly to Berserk, Rapiers may choose to gain -5 damage and +2 accuracy or -10 damage and +4 accuracy on their attacks.
B26: Polearm
C27: Levels
D28: Power Swing and Leg Sweep swapped
B29: Orb
C30: Spirit Shackle
D31: Can only target a maximum of 3 players now.
B32: Katana
C33: Nihonto
D34: MR4 now + Once
B35: Tonfa
C36: Leash
D37: MR4

Sheet 4.0.10
A1: 4.0.10
A2: Release Date: | B2: 42672
A3: Concerns? PM either Taistelu, MMM, Micro, Henka or Hirl, if they're not on, PM some other staff. No staff on? Use %mail. No Kyubs? Cry in isolation. No PS!? Fear for your life that the hacker has returned OR USE THE ABILITY SUGGESTION FORM IN THE ROOMINTRO SERIOUSLY WHY DOES NO ONE USE THAT?
A4: General
B5: PvE
D6: If there are multiple monsters in a battle, the party automatically moves first.
B7: Terrain
C8: Lava
D9: 20 HP damage for entering, ending your turn is 30 HP damage.
B10: Mechanics
C11: The Twice move EoT descision was reversed (lol it was a really weird one).
C13: Moves that can be used on allies can now be used on consenting players similar to Ally Switch.
A15: Weapon
B16: Polearm
C17: Stats
D18: -5 HP and -2 ATK
B20: Wand
C21: Stats
D22: +5 HP and +1 MAG
C23: Chroma
D24: Now 2d8+9
B26: Tonfa
C27: Stats
D28: +5 HP
B29: Spellbook
C30: Seal
D31: d8+6, Seal 10+ on accuracy roll
C32: Bounty of Death
D33: d10+8
C34: Magic Shot (S)
B35: Longbow | D35: Now Line 4
C36: Snipe
D37: No longer crits on 18+ or makes next attack an automatic hit upon critting
C38: Focused Fire
D39: Reworked To: 1d10+7 | Push 3 effect | Range 2 | MR3 | EoT
B40: Crossbow
C41: Rupture/Pierce
D42: Levels are now swapped
B43: Shortbow
C44: Windmill
D45: MR is now 3.
C46: Double Shot
D47: Now 2d8+3
B48: Axe
C49: Skull Bash
D50: Now MR5
B51: Claws
C52: Fury Cutter
D53: MR 3 -> MR 2, Magical -> Physical, 1d8+5 -> 1d8+1

Sheet 4.0.08
A1: 4.0.08
A2: Release Date: | B2: 42658 | C2: Micro is STILL a nerd.
A3: Concerns? PM either Taistelu, MMM, Micro or Henka, if they're not on, PM Moq or Pancake, if they're not on, PM some other staff. No staff on? Use %mail. No Kyubs? Cry in isolation. No PS!? Fear for your life that the hacker returned.
A4: General
B5: New EXP Cycle Bonus
D6: +1 XP/Kill
A8: Class
B9: Pyrokinetic
C10: Maximum of one stack gained per turn.
A12: Weapon
B13: Crossbow
C14: Pierce
D15: Ignores accuracy reduction as well now.
B16: Shortbow
C17: Kip Up
D18: 2d8+12, Range 2
C19: String Shot
D20: If targetting ally, no damage is dealt, 3d8+14
C21: Eagle Eye
D22: Crit +17, -1 evasion.
B23: Katana
C24: Slice
D25: Roll: 2d10+4 -> 2d10+6
C26: Ni Dageki
D27: Roll: 2d8+4 -> 2d8+6
C28: Siedo
D29: Roll: 2d8+6 -> 2d8+12
C30: Nihonto
D31: Roll: 3d8+8 -> 3d8+12
C32: Stats
D33: +1 ATK @ Level 2 | +1 MAG @ Level 2
D34: +1 MAG @ Level 5

Sheet 4.0.07
A1: 4.0.07
A2: Release Date: | B2: Now | C2: Micro is STILL a nerd.
A3: Concerns? PM either Taistelu, MMM or Micro...if they're not on, PM Moq or Pancake, if they're not on, PM some other stuff. No staff on? Use %mail. No Kyubs? Cry in isolation.
A4: Class
B5: Bard
C6: Motivation
D7: The user now always gets the Motivation boost.
C8: Crescendo
D9: Frequency: Extended -> Full
B10: Guardian
C11: Protector
D12: Now Once/Swift
B13: Skirmisher
C14: Outmaneuver
D15: Effect: Add the users highest evasion stat to your next accuracy -> Add +2 accuracy to your next attack(all accuracy for multi-hitting moves)
A16: Weapon
B17: Gladius
C18: Bone Sword
D19: Roll: 3d10+2 -> 2d10+8
B20: Tonfa
C21: Leash
D22: Roll: 3d6+10 -> 3d8+10
C23: Figure 8
D24: Level 2 -> 3
C25: Dazing Shot
D26: Level 3 -> 2
B27: Rapier
C28: Riposte
D29: MR: 4 -> 2
D30: Frequency: EoT -> Every Turn
B31: Claws
C32: Gouge
D33: MR: 3 -> 4
C34: Puncture
D35: Frequency: Twice -> Once
D36: Roll: 2d8+10 -> 2d8+3
D37: Effect: Additional 15 damage if bleeding -> Additional 10 damage if bleeding
C38: Bagh Naka
D39: Roll: 2d8+10 -> 3d8
B40: Hammer
C41: Crush
D42: Wording: Pushed into allies -> Pushed into any player
B43: Polearm
C44: Snap
D45: MR: 6 -> 5
C46: Impulse Skewer
D47: MR: 7 -> 6
D48: Frequency: Twice -> Once
C49: Leg Sweep
D50: MR: 5 -> 4
B51: Bo Staff
C52: Charged Blow
D53: Now does an additional 10 damage if used as a setup move.
B54: Stave
C55: Phantasmal Strike
D56: Roll: 2d8+10 -> 2d8+12

Sheet 4.0.06
A1: 4.0.06
A2: Release Date: | B2: Released
A3: If you want to suggest a change, or disagree with a change on here, PM either Taistelu, MMM or Micro. If they are not around, PM Moq or Pancake. If they are not around, PM another staff. If no staff are on, mail someone, if Ice Kyubs is down, cry in isolation.
A4: General
C5: Game Modes
D6: 2v2v2 and 2v2v2v2 are now playable. Base reward for 2v2v2 is 7 EXP. Base reward for 2v2v2v2 is 9 EXP.
C7: Glossary
D8: This was released before .06 but w/e.
C9: Cone
D10: Reworked, check Cone Examples tab on tracker/glossary!
A12: Classes
B13: Bard
C14: Bard has 1 less MP.
C15: Crescendo
D16: Clarify that it lasts one turn.
C17: Rising Hope
D18: Now only affects the Bard and teammates in melee range of the Bard.
B19: Skirmisher
C20: Skirm has one extra MP.
C21: Quick Thinking
D22: Now only lets the Skirmisher move with half its normal MP rounded down.
A24: Weapon
B25: Shortbow
C26: Stats
D27: Now gains 1 extra ATK at level 4 and level 5
C28: Kip Up
D29: 1d6+10 -> 2d8+10
C30: String Shot
D31: 2d6+8 -> 3d8+12 | F31: Frequency: Twice -> Once
B32: Longbow
C33: Snipe
D34: Frequency: Twice -> Once | G34: Roll: 5d10+5 -> 6d8+10
C35: Marksman
D36: +1d10 at 7 to 8 range -> +1d10 at 8 range
C37: Crippling Shot
D38: Roll: 2d10+6 -> 1d10+6
B39: Gladius
C40: Berserk
D41: Frequency: Passive -> Free/Trigger
B42: Spellbook
C43: Incinerate
D44: No longer inflicts burn damage.
B46: Katana
C47: Ki Blade
D48: Roll: 2d6+6 -> 2d8+6
C49: Seido
D50: Roll: 2d6+6 -> 2d8+6
C51: Ni Dageki
D52: Roll: 2d6+4 -> 2d8+4
C53: Nihonto
D54: MR: 2 -> 3 | E54: Roll: 3d6+8 -> 3d8+8
B55: Claws
C56: Puncture
D57: +2 acc effect when target is bleeding has been removed
B58: Tonfa
C59: Defensive Stance
D60: Now only gives +3 in both evasions
B61: Rapier BUFF
C62: Stats
D63: At level 5, 2 extra ATK, 1 extra MAG, 5 extra HP.
C64: Shadow Spear
D65: Roll: 2d6+4 -> 2d8+4
C66: Riposte
D67: Roll: 1d10+0 -> 2d6+8 | F67: Riposte no longer gains ATK bonus.
C68: Impale -> Thrust
D69: Roll: 2d6+5 -> 2d8+6 | F69: Range 3 -> 5 | G69: Level: 4 -> 2
C70: Phantom Force
D71: Old effect removed completely. New effect: +1 PEvade/MEvade if the attack hits for one turn.
D72: Roll: 2d6+4 -> 3d8+13
D73: Frequency: EoT -> Once
C74: Lunge
D75: Level: 2 -> 4
B76: Crossbow
C77: Rupture
D78: Frequency: Every Turn -> EoT

Sheet 4.0.05
A1: 4.0.05
A2: Release Date: | B2: 24/09/16 (Sat) (Released) | C2: Realm of the minor changes.
A3: Weapon reworks are being worked on even if they're not in this patch! | H3: micro is a nerd
A4: If you would like to comment on the Patch Notes, PM either Taistelu, MMM, microwavable, Pancake or Moq (people who work on balancing specifically) or use the Ability Suggestion Form (idk who has access to that though).
A5: General
C6: Turn Order
D7: d20+MP -> d8+MP
C8: Switching class/branch
D9: Players can switch class/weapon without having to reach level 3.
C10: Backstep
D11: Clarify that Backstep cannot be diagonal.
A14: Class
B15: CyroKinesis
C16: MP: 2 -> 3
C17: Frozen Heart
D18: Now also makes the user immune to roots.
C19: Invoke:Ice
D20: If the opponent's accuracy roll is 16+, they lose one dice on their attack.
B21: Pyrokinetic
C22: Comet
D23: Clarify that Comet isn't affected by Invoke:Fire.
B24: Guardian
C25: Heart Shield
D26: For all cases in which Heart Shield activates, Heart Shield now gives +1 evasion instead of +2.
A27: Weapon
B28: Gladius
C29: Swipe
D30: Level 2 -> Level 3 | F30: 10 HP recoil -> 15 HP recoil
C31: Blunt Force
D32: Level 3 -> Level 2
C33: Bone Sword
D34: Critical hit range is 18+ 14+
B36: Longbow
C37: Longbow
D38: Renamed to Marksman | Additional effect: +1d10 damage dice if at 7-8 range
C39: Snipe
D40: Roll: 3d10+5 -> 5d10+5
B42: Wand
C43: Magic Shot (W)
D44: Miss Rate 1 -> 3
C45: Chroma | D45: (completely reworked to:)
D46: Line 2 | One target | 2d8+5 | MR 3 | If the attack lands target has -2 acc on their next move
C47: Energize
B48: Stave | D48: -20 HP -> -15 HP
C49: Phantasmal Strike
D50: Level 1 -> 3
C51: Earth Bind
D52: Level 3 -> 1 | E52: Frequency: EoT -> Every Turn
B53: Crossbow
C54: Explosive Shot
D55: 2d8+10 -> 2d8+5
C56: Rupture
D57: 2d8+6 -> 3d8+10 | F57: MR: 3 -> 4 | G57: Removed Bleed Effect.
C58: Pierce
D59: MR: 3 -> 6 | E59: Ignores target's evasion and any outside factors to damage originating from the enemy
B61: Claws
C62: Fury Cutter
D63: MR: 5 -> 3
C64: Puncture
D65: Bonus damage from bleed: 10 -> 15

Sheet 4.0.04
A1: 4.0.04
A2: Release Date: | B2: 9/17/16
A4: General
C5: Turn Order
D6: Turn order will now be based by rolling 1d20 and then adding your movement to the roll.
C7: Host Guide
D8: For those who wish to take up hosting in BD4, there is now a hosting guide in the Home Page.
A10: Weapon
B11: Gladius
C12: Etruia
D13: 2d10+10 -> 2d10+2 | F13: Level 4 -> Level 5
C14: Bone Sword
D15: Level 5 -> Level 4
B16: Polearm
C17: Impulse Skewer
D18: 3d10+5 -> 3d10+2
D19: Now only the first hit gets your Attack bonus.
B20: Longbow
C21: Longbow
D22: Removed: Longbows can't Backstep.
B23: Spellbook
C24: Wall of Air
D25: Old effect removed. New effect: You can choose to make this wall a straight 5x1 wall or a ringed wall with 3 diameter around yourself. Ranged attacks that pass through the wall get -2 accuracy and deal 50% damage rounded down. The wall itself is a slow terrain (requiring two movement to move onto). This wall lasts 5 turns, ending at the spellbooks turn or until the spellbook who cast this dies. You can only have one Wall of Air on the field at a time.
B26: Wand
C27: Magic Shot (W)
D28: Removed: This attack always hits. | G28: Miss rate: 1
C29: Energize
D30: Level 2 -> Level 3 | F30: Now requires 20 HP to be sacrificed instead of 10
C31: Life Drain
D32: Level 3 -> Level 2
C33: Blizzard
D34: Level 4 -> Level 5
C35: Chroma
D36: Level 5 -> Level 4

Sheet 4.0.03
A1: 4.0.03
A2: Release Date: | B2: 42606
A4: Basic Skills
B5: Dash
C6: Fixed a typo that makes it sound like dash gives you an additional 150%
B7: Attacks of Opportunity
C8: Added AoO's as a Basic Skill
A9: Class Skills
B10: CryoKinesis
C11: General
D12: Changed the spelling of the class
C13: Invoke: Ice
D14: Moved down to level 2
B15: PyroKinetic
C16: Potential Energy
D17: PE no longer loses all of the stacks if you use a different attack or don't attack
C18: Comet
D19: Moved down to level 2
D20: New: Comet's damage can't be affected by any outside modifier and does not gain bonus magic damage
C21: Ignition
D22: Clarified that Ignite doesn't stack with itself
D23: Range Burst 2 -> Burst 1
B24: Skirmisher
C25: Runner Up
D26: Removed
C27: Quick Thinking
D28: Level 1 Skirmisher ability. Allows skirmishers to use their move action after their standard action. This is a passive ability.
C29: Evade
D30: Moved down to level 2
D31: Evasions: 1,1,2,2,2 -> 0,0,0,1,1
B32: Guardian
C33: Radiance
D34: Moved down to level 2
C35: Iron Defense
D36: Removed
C37: Protector
D38: Moved down to level 4
C39: Oath of Mercy
D40: Level 5 Guardian ability. As a Swift action the Guardian gains +10 Damage Resistance until the end of their next turn. This ability has a frequency of Once.
B41: Bard
C42: Rising Hope
D43: Moved down to level 2
A44: Weapon Skills
B45: Katana
C46: Ki Blade
D47: Ki Blade no longer prevents the target from using AoO's
C48: Go Daegeki
D49: Renamed Ni Daegeki | F49: 5-hit -> 2-hit
D50: Miss rate: 4/5/6/7/8 -> 4 | F50: Damage: 1d6+8 -> 2d6+4
C51: Seido
D52: Frequency: Twice -> EoT | F52: Damage 2d6+4 -> 2d6+6
D53: Effect: Until the end of the targets next turn they can't use attack of opportunities
C54: Nihonto
D55: Frequency once -> twice
D56: Effect: Upon 14+ foes are sealed. Upon 18+ foes are sealed and slowed (2).
B57: Gladius
C58: Berserk
D59: New Passive. The Gladius can choose to gain +5 damage for -2 accuracy up to two times (for a max of +10 and -4)
B60: Hammer
C61: Impact
D62: Impact no longer deals splash damage
D63: Damage: 3d8+10 -> 3d8+5
B64: Axe
C65: Forward Thurst
D66: New! this attack gains +2 accuracy if used after backswing
B67: Polearm
C68: Power Swing
D69: Damage: 2d10+10 -> 3d10+8
C70: Impulse Skewer
D71: Damage: 2d10+2 -> 3d10+5
D72: Miss Rate: 6 -> 7
B73: Longbow
C74: Crimson Collage
D75: Critical hit: 15+ -> 17+
C76: Focused Fire
D77: MR: 6 -> 3
C78: Snipe
D79: Snipe has an 18+ crit range and if it crits the longbow's next attack can't miss.
B80: Short Bow
C81: Double Shot
D82: The attack bonus applies only to the first hit
C83: Eagle Eye
D84: Free action -> Swift action
D85: New: Lasts until the Shortbow has taken damage
B86: Spellbook
C87: Incinerate
D88: (Initial hit) 1d10 -> 1d10+5
C89: Disable
D90: Now takes a standard action and 25% of their maximum health to remove Disable (removing disable triggers AoO's as well)
C91: Fog
D92: Targes lose half their range (rounded down) on all ranged attacks
C93: Ally Switch
D94: Full action -> move action
B95: Wand
C96: Chroma
D97: Damage: 3d8+20 -> 3d8+10
B98: Stave
C99: Earthbind
D100: Old effect removed. New effect: prevents the target from backstepping
B101: Tonfa
...

Sheet 4.0.02
A1: 4.0.02
A2: Release Date: | B2: 42598
A4: Weapon Skills
B5: Heavy - Polearm
C6: Power Swing
D7: 3d10+15 -> 2d10+10
C8: Leg Sweep
D9: 3d10+10 -> 2d10+6
D10: Miss rate 5 -> 4
D11: Polearm is a brusier. Sporting some of the highest damaging stats and attacks, however no one needs a 3d10+15 at level 1.
A12: Class Skills
B13: Skirmisher
C14: Glide
D15: No longer makes backstep a free action
D16: While extra movement for free might be awesome, it gives the skirmisher almost too much fun avoiding attacks of opportunity, additionally glide only giving 2x Movement makes it more in line with other skills

Sheet Home Page
A1: a | B1: Past Version: 4.3 Home Page!
B3: Ability Resources
B4: 4.3 Monsters
B6: =HYPERLINK("https://docs.google.com/spreadsheets/d/1xUe-NUahqo_JugC5LH5svDv46GNFziCUu9ebYzCdD-o/edit","Items List") -> Items List
B8: Class Abilities
B9: Weapon Branches
B10: Archer | C10: Celestial | D10: Clairvoyant | E10: Dark | F10: Dueler | G10: Fighter | H10: Heavy | I10: Regal | J10: Sorcerer
B11: Other Resources
B12: =HYPERLINK("https://docs.google.com/document/d/1uQf6GU1UkaTNPJjXjIe0jaj30t0HbgGVgMoMT2CR6T4/edit?usp=sharing","How to Play") -> How to Play
B14: Host Guide
B16: =HYPERLINK("https://docs.google.com/document/d/136sFrYkoo8cmcQljwF72LC30ywWgwXecfEhQcigRMH0/edit","Changelog") -> Changelog
B18: Glossary
A19: This is a previous version of Battle Dome. Version 4.4 can be found here: https://docs.google.com/spreadsheets/d/1KP-a4mvTbhhul9mONBqrsuCRzc2UoqodNQMpdT_3Zzk

Sheet BETA
B2: BETA CHANGELOG
B3: To use beta content, users must ask for special permission to host (betaperms). Beta games are looted as normal. Changes found here are for feedback and playtesting purposes and are in no way final. To discuss feedback, feel free to use the #suggestion_discussion channel or its Beta thread on the Discord or use the main chatroom.
B4: Date of Addition | C4: Change | D4: Created By | E4: Approved By | F4: Last Edited
B5: 44818 | C5: Game Mod - Pokemon in the Dome | D5: Salient | E5: Salient | F5: 28/06/2023
B6: 44973 | C6: Trickster Branch (Coins, Cards, Dice)+New Tarot Cards+New Status: Ruin | D6: OHKOff | E6: Krytocon | F6: 44975
B7: 45076 | C7: PvE Rework | D7: Salient / Krytocon | E7: Krytocon | F7: 45076
B8: 45187 | C8: BD Game Mods | D8: mistlo | E8: Elissem | F8: 45187
B9: 45259 | C9: 1vE Beta | D9: Taistelu | E9: Taistelu | F9: no one uses this column
B10: 45421 | C10: Cryo Rework | D10: God evening | E10: God evening | F10: hi
B11: 45446 | C11: Solar Rod Rework (Salient) | D11: Salient | E11: Taistelu | F11: Baked
B12: 45446 | C12: Solar Rod Rework (4mat) | D12: 4mat | E12: God evening | F12: Beans
B13: 45457 | C13: Star Rod Rework (Saya amanogawa) | D13: Saya | E13: God evening | F13: Are
B14: 45525 | C14: Cycle Beta | D14: God evening, Taistelu, Tapler, Oases | E14: Baked Beans | F14: Epic
B15: 45537 | C15: Version 4.4 | D15: BD Staff | E15: BD Staff | F15: 45537
C17: Changes are cool, but curious as to what old Battle Dome looked like? Check out the previous version of Battle Dome - 4.2 - here! | F17: "If you know the enemy, and know yourself, you need not fear the result of a hundred battles. If you know yourself but not the enemy, for every victory gained you will suffer a defeat. If you know neither enemy nor yourself, you will succumb in every battle." -Sun Tzu, Art of War | G17: semeoz is a noob lol

Sheet Classes
A1: Name | B1: Lvl | C1: Frequency | D1: MR | E1: Damage | H1: Target | K1: Effect
E2: Roll | F2: Type | G2: Action Type | H2: Amount | I2: Group | J2: Range and Modifiers
A3: Basic Abilities
A4: Basic Attack (P) / Basic Attack (M) | B4: B | C4: Every Turn | D4: 2 | E4: 1d10+2 | F4: Physical or Magical | G4: Standard | H4: 1 | I4: Foe | J4: Melee | K4: A basic attack. The user may choose either BATK (P) or BATK (M). Add the corresponding stat depending on their choice (BATK (P) = Physical Attack. BATK (M) = Magical Attack).This attack can be used even when sealed and its use cannot be prevented by any means, outside of Stun.
A5: Dash | B5: B | C5: Every Turn | D5: - | E5: - | F5: - | G5: Full | H5: - | I5: Self | J5: - | K5: The user moves up to 1.5x their MP (rounded down) instead of 1x. (Dash is a Full action, which takes up both the Movement and Standard actions.)
A6: Backstep | B6: B | C6: Every Turn | D6: - | E6: - | F6: - | G6: Movement | H6: - | I6: Self | J6: - | K6: This can only be used while a foe is in the user's Melee. The user moves one tile in a cardinal direction without triggering Attack of Opportunity.
A7: Attack of Opportunity | B7: B | C7: Every Turn | D7: 2 | E7: 1d10+2 | F7: Physical or Magical | G7: Reaction | H7: 1 | I7: Foe | J7: Melee | K7: This may be used when a foe in the user's Melee either: leaves that Melee with their Movement action, or uses a ranged attack that doesn't target the user (after damage is rolled). This Reaction still adds ATK or MAG.
A8: Class Abilities
A10: Bard
A11: 80 HP | 6 ATK | 6 MAG | 22 PD | 22 MD | 3 MP | G11: "Support yourself and others with damage and accuracy bonuses."
A12: Rising Hope | B12: 1 | C12: Passive | D12: - | E12: - | F12: - | G12: Passive | H12: AoE | I12: Self and Allies | J12: Burst 1 | K12: The user and allies in Melee range have +1 Accuracy and +1 Crit Range. Allies that have received Harmony or a buff from the user since the start of their previous turn gain a bonus +1 ACC. The user also gains +1 ACC while this bonus is active. Rising Hope does not stack with more than one Bard.
A13: Harmony | B13: 3 | C13: Twice/E2T | D13: - | E13: - | F13: - | G13: Swift | H13: 1 | I13: Self or Ally | J13: Range 3 | K13: For one round, the target cannot be affected by any status or debuff and has any such effect removed. If the target is affected by unremovable Poison, Burn or Bleed upon the usage or during the duration of this move, they gain +2 EVAs, +2 ACC, or +5 DMG respectively for the duration of the status. This move does not interact with self-inflicted statuses or debuffs in any way.
A14: Encore | B14: 5 | C14: Every Turn | D14: - | E14: - | F14: - | G14: Standard or Reaction | H14: - | I14: Self | J14: - | K14: Roll 1d20 and store the result (max one stored roll). As a Reaction, before the user or an ally in Range 3 rolls an accuracy check of an attack, the stored roll is used instead.
A15: Primadonna | B15: 7 | C15: Once | D15: - | E15: - | F15: - | G15: Free | H15: 1 or 2 | I15: Self or Self and Ally | J15: Global | K15: Targets gain +5 ATK/MAG and -5 DR permanently. If either effect is cleansed, the other is removed. After one round, targets may choose to lose the buff as a Free action. This does not stack.
A16: Crescendo | B16: 10 | C16: Once | D16: - | E16: - | F16: - | G16: Swift | H16: AoE | I16: Self and Allies | J16: Star 5 | K16: All targets gain +7 DR and +1 EVA until the start of the user's next turn. If the user's Primadonna is active, they instead gain +1 ACC, +5 DMG, and +2 Crit Range. This ability may be used as a Standard action instead to have Global range, provide a 50% boost (rounded up) to the buff values, and increase their duration to one round.
A17: Cryokinetic
A18: 75 HP | 7 ATK | 7 MAG | 21 PD | 21 MD | 3 MP | G18: "Geared toward defense, with strong utility."
A19: Invoke: Ice | B19: 1 | C19: Passive | D19: - | E19: - | F19: - | G19: Passive | H19: - | I19: - | J19: - | K19: When targeted with a non- Free, Swift, or Global attack from a foe, the user gains an Ice Stack (max three) after the move is resolved. Only two Ice Stacks can be gained per round. If the accuracy roll of an attack targeting the user rolls X+, that attack loses one die, where X = 15 - # of Ice Stacks.
A20: Mist | B20: 3 | C20: Twice | D20: - | E20: - | F20: - | G20: Free | H20: - | I20: Self | J20: - | K20: For one round, all attacks made by enemies from inside the user's Burst 2 deal -5 damage. The user may spend up to two Ice Stacks to extend this effect's duration by one for each stack used, or spend three stacks for a duration of two rounds and a range of Burst 3. This move cannot be used again while its effect is active.
A21: Frost Barrier | B21: 5 | C21: Twice | D21: - | E21: 2d8+X | F21: - | G21: Swift | H21: - | I21: Self | J21: - | K21: The user gains a Shield/1 equal to 2d8+X, where X is thrice the amount of Ice Stacks the user chooses to spend, minimum one stack.
A22: Ice Wall | B22: 7 | C22: Once | D22: - | E22: - | F22: - | G22: Movement or Free | H22: - | I22: - | J22: Range 5 | K22: The user creates a 3-tile wall of Ice in a cardinal direction, or a diagonal one with halved length (rounded up). This Ice has 15 HP. Foes who end their turn with at least one of these Ice tiles in their melee take 10 damage. The user may spend Ice Stacks to increase the wall's base length by one for each stack spent. The wall expires after 3 rounds. The user may shatter the wall as a Trigger action after one turn, destroying it and inflicting 3 Bleed/2 on foes within melee of it. This move ignores Range Rule.
A23: Flash Freeze | B23: 10 | C23: Once | D23: - | E23: - | F23: - | G23: Reaction | H23: - | I23: - | J23: Global | K23: This player may use this when targeted by an attack after damage has been rolled, and must spend one Ice Stack to do so. The interrupted attack loses all of its additive dice (excluding Critical Hit). The user may spend an additional Ice Stack to also remove the attack's additive positive damage modifiers, or two additional Ice Stacks to remove all positive damage factors. This ability cannot remove advantage damage dice.
A24: Guardian
A25: 85 HP | 5 ATK | 5 MAG | 30 PD | 30 MD | 3 MP | G25: "Protect yourself and allies."
A26: Strike Guard | B26: 1 | C26: Passive | D26: - | E26: - | F26: - | G26: Passive | H26: - | I26: - | J26: - | K26: If the opponent rolls 14+ on their accuracy on an attack that is targetting the user or an ally in their Melee, the attack deals -5 damage.
A27: Vanguard | B27: 3 | C27: Twice/EoT | D27: - | E27: - | F27: - | G27: Reaction | H27: 1 | I27: Ally | J27: Homing 4 | K27: This move may be used when an ally in range is targeted by an attack, after damage is rolled. The user moves to a tile in the ally's melee, and the ally takes 5 less damage from the attack. If the user is also a target of the attack, both the user and the Ally take 10 less damage instead. This effect does not stack with multiple Guardians.
A28: Fortify | B28: 5 | C28: Once | D28: - | E28: - | F28: - | G28: Swift | H28: 1 | I28: Self or Ally | J28: Homing 4 | K28: The target gains X Shield/1, where X is 35% of the amount of damage the user has taken directly from attacks since the beginning of their last turn (max 30 Shield).
A29: Tenacity | B29: 7 | C29: Thrice | D29: - | E29: - | F29: - | G29: Trigger | H29: 1 | I29: Self or Ally | J29: Homing 4 | K29: If the target was alive and was not attacked last round, they heal 15% of their missing HP. This can only be used once per turn.
A30: Radiance | B30: 10 | C30: Once | D30: - | E30: - | F30: - | G30: Swift | H30: - | I30: Self | J30: - | K30: The user takes 80% damage from attacks for two rounds. Additionally, for one round, whenever an ally is targeted by an attack from within the user’s Burst 2, the user may use a Reaction to redirect 30% of the damage the ally would take to themselves. (Redirected damage cannot be reduced by any means, nor can it stack with multiple users.)
A31: Pyrokinetic
A32: 65 HP | 11 ATK | 11 MAG | 16 PD | 16 MD | 3 MP | G32: "Geared towards offense at a slower pace."
A33: Invoke: Fire | B33: 1 | C33: Passive | D33: - | E33: - | F33: - | G33: Passive | H33: - | I33: - | J33: - | K33: When targetting a foe with a non- Free, Swift, or Global attack, the user gains a Fire Stack (max three) after the move is resolved. After gaining a Fire Stack, the user cannot gain another one until the start of their next turn. If the accuracy roll of an attack by the user rolls X+, that attack gains one die, where X = 15 - # of Fire Stacks the user has.
A34: Ignition | B34: 3 | C34: EoT | D34: - | E34: - | F34: - | G34: Free | H34: - | I34: Self | J34: - | K34: The user spends 1 to 3 Fire Stacks to use this move. Their next attack gains 3X Burn/1, where X is the number of Stacks spent.
A35: Comet | B35: 5 | C35: Twice | D35: 2 | E35: 1d4+2 | F35: Magical | G35: Movement | H35: 2 | I35: Foes | J35: Melee | K35: The user does the following things in any order: deals damage equal to the rolled amount to up to two foes in melee range, moves up to their full MP range. This move is immune to outside damage factors. Do not add MAG.
A36: Afterburn | B36: 7 | C36: Once | D36: - | E36: - | F36: - | G36: Free | H36: - | I36: Self | J36: - | K36: The user gains +accuracy equal to X+1 for one turn, where X is the amount of Fire Stacks the user chooses to spend, minimum one stack.
A37: Kinetic Energy | B37: 10 | C37: Once | D37: - | E37: - | F37: - | G37: Free | H37: - | I37: Self | J37: - | K37: The user spends two Fire Stacks to gain +10 damage on their next attack, or three Fire Stacks to gain +2 dice and +15 damage to their next attack.
A38: Rifter
A39: 60 HP | 9 ATK | 9 MAG | 19 PD | 19 MD | 3 MP | G39: "Deal lots of damage in short bursts."
A40: Time Matrix | B40: 1 | C40: Passive | D40: - | E40: - | F40: - | G40: Passive | H40: AoE | I40: Self and Allies | J40: Burst 1 | K40: If the user or an ally in Burst 1 rolls 14+ for their accuracy on an attack, the attack deals +5 damage.
A41: Rewind | B41: 3 | C41: EoT | D41: - | E41: - | F41: - | G41: Reaction | H41: 1 | I41: Self or Ally | J41: Range 4 | K41: This move can be used after the target rolls damage for an attack. The target may reroll up to 3 damage dice, but the user takes 3% of the attack's damage per die rerolled as recoil. Rerolled dice cannot trigger bombs or inverse bombs.
A42: Interval | B42: 5 | C42: Twice | D42: - | E42: - | F42: - | G42: Swift | H42: 1 | I42: Self or Ally | J42: Range 4 | K42: The target's EoT abilities that are on cooldown are reset, if the target's next ability is EoT it does not go on cooldown. (Affected Triggers are limited to one use per turn, unless specified otherwise.)
A43: Paradox | B43: 7 | C43: Once | D43: - | E43: - | F43: - | G43: Swift | H43: - | I43: Self | J43: - | K43: This turn, the user may use a Once/Twice/Thrice move without expending a use, even if the move is out of uses. The user cannot use Paradox on Reaction or Trigger actions. The user takes 20% of the damage from the Paradox move as recoil.
A44: Time Dilation | B44: 10 | C44: Once | D44: - | E44: - | F44: - | G44: Reaction | H44: 1 | I44: Foe | J44: Global | K44: This may be used when the user is attacked, after damage is rolled. After the user takes damage, their next attack deals +Damage equal to one third of the damage the user took from the attack.
A45: Skirmisher
A46: 65 HP | 8 ATK | 8 MAG | 20 PD | 20 MD | 4 MP | G46: "Strong movement capabilities."
A47: Glide | B47: 1 | C47: Passive | D47: - | E47: - | F47: - | G47: Passive | H47: - | I47: - | J47: - | K47: When dashing, the player may move up to 2x their MP instead of 1.5. If they do, the dash caps at 12 MP. Additionally, the player's dash ignores the effects of Slow.
A48: Quick Thinking | B48: 1 | C48: EoT | D48: - | E48: - | F48: - | G48: Trigger | H48: - | I48: - | J48: - | K48: This turn, the user loses half of their MP (rounded up), but may use their Movement action after Standard actions. This Movement is unaffected by AoO and Slow.
A49: Stealth | B49: 3 | C49: EoT | D49: - | E49: - | F49: - | G49: Free | H49: - | I49: Self | J49: - | K49: This turn, the user’s Backstep becomes a Free action. While under this effect, the user has -2 MP.
A50: Outmaneuver | B50: 5 | C50: Twice | D50: - | E50: - | F50: - | G50: Free | H50: - | I50: Self | J50: - | K50: The user may sacrifice up to 4 unused MP to gain +1 accuracy for every 2 MP sacrificed for one turn.
A51: Tunneling | B51: 7 | C51: Twice | D51: - | E51: - | F51: - | G51: Free | H51: - | I51: Self | J51: - | K51: This turn, the user may move through all tiles and Enemy Players/Monsters as if they were regular terrain, but they may not perform/end any action on tiles that they normally can't move through (Stop, Ice, Broken, or Bone).
A52: Time's Edge | B52: 10 | C52: Once | D52: - | E52: - | F52: - | G52: Free | H52: - | I52: Self | J52: - | K52: This turn, the user uses an additional Standard action. The next two Standard/Full actions this turn only add 25% ATK/MAG. If the first Standard/Full deals damage, the second Standard ignores outside damage factors and does not add ATK/MAG. The user can only use Reactions and Triggers between these actions, unless specified otherwise.

Sheet Archer
A1: Name | B1: Lvl | C1: Frequency | D1: MR | E1: Damage | H1: Target | K1: Effect
E2: Roll | F2: Type | G2: Action Type | H2: Amount | I2: Group | J2: Range and Modifiers
A3: Basic Abilities
A4: =Classes!A4 -> Basic Attack (P) / Basic Attack (M) | B4: =Classes!B4 -> B | C4: =Classes!C4 -> Every Turn | D4: =Classes!D4 -> 2 | E4: =Classes!E4 -> 1d10+2 | F4: =Classes!F4 -> Physical or Magical | G4: =Classes!G4 -> Standard | H4: =Classes!H4 -> 1 | ... K4: =Classes!K4 -> A basic attack. The user may choose either BATK (P) or BATK (M). Add the corresponding stat depending on their choice (BATK (P) = Physical Attack. BATK (M) = Magical Attack).This attack can be used even when sealed and its use cannot be prevented by any means, outside of Stun.
A5: =Classes!A5 -> Dash | B5: =Classes!B5 -> B | C5: =Classes!C5 -> Every Turn | D5: =Classes!D5 -> - | E5: =Classes!E5 -> - | F5: =Classes!F5 -> - | G5: =Classes!G5 -> Full | H5: =Classes!H5 -> - | ... K5: =Classes!K5 -> The user moves up to 1.5x their MP (rounded down) instead of 1x. (Dash is a Full action, which takes up both the Movement and Standard actions.)
A6: =Classes!A6 -> Backstep | B6: =Classes!B6 -> B | C6: =Classes!C6 -> Every Turn | D6: =Classes!D6 -> - | E6: =Classes!E6 -> - | F6: =Classes!F6 -> - | G6: =Classes!G6 -> Movement | H6: =Classes!H6 -> - | ... K6: =Classes!K6 -> This can only be used while a foe is in the user's Melee. The user moves one tile in a cardinal direction without triggering Attack of Opportunity.
A7: =Classes!A7 -> Attack of Opportunity | B7: =Classes!B7 -> B | C7: =Classes!C7 -> Every Turn | D7: =Classes!D7 -> 2 | E7: =Classes!E7 -> 1d10+2 | F7: =Classes!F7 -> Physical or Magical | G7: =Classes!G7 -> Reaction | H7: =Classes!H7 -> 1 | ... K7: =Classes!K7 -> This may be used when a foe in the user's Melee either: leaves that Melee with their Movement action, or uses a ranged attack that doesn't target the user (after damage is rolled). This Reaction still adds ATK or MAG.
A8: Archer Abilities
A10: Crossbow
A11: 65 HP | 11 ATK | 7 MAG | 13 PD | 14 MD | 1 MP | G11: "A weapon that has increased damage and effects the more you target an opponent."
A12: Hunter's Mark | B12: 1 | C12: Passive | D12: - | E12: - | F12: - | G12: Passive | H12: - | I12: - | J12: - | K12: When the user's Crossbow attack resolves, targets of the attack gain 1 Mark each. The user's attacks deal +5% damage per Mark on one target (does not stack with multiple targets). Marks only apply to their user's attacks.
A13: Arrow Flurry | B13: 1 | C13: Every Turn | D13: 3 | E13: 2d8+7 | F13: Physical | G13: Standard | H13: 1 | I13: Foe | J13: Range 6 | K13: If the original target has a Mark, this move gains Splash 1. If the target has 2+ Marks, this move instead gains Splash 2.
A14: Arrow Net | B14: 2 | C14: E2T | D14: 4 | E14: 3d8+4 | F14: Physical | G14: Standard | H14: 1 | I14: Foe | J14: Range 6 | K14: If the target has a Mark, they are inflicted with Slow/1. If the target has 2+ Marks, the user may inflict the target with 6 Cripple/1 instead.
A15: Shadow Quiver | B15: 3 | C15: Once | D15: - | E15: - | F15: - | G15: Swift | H15: - | I15: Self | J15: - | K15: The user's next attack becomes Magical and ignores all obstructions in its path (including Air tiles and Personal Bubble).
A16: Scoping Shot | B16: 4 | C16: EoT | D16: 3 | E16: 2d10+6 | F16: Physical | G16: Standard | H16: 1 | I16: Foe | J16: Line 4 | K16: For one round, all attacks on the target gain +1 ACC for every mark the target has.
A17: Quick Scope | B17: 5 | C17: Twice/EoT | D17: 3 | E17: 1d8+2 | F17: Physical | G17: Swift | H17: 1 | I17: Foe | J17: Range 6 | K17: This attack is immune to outside damage factors. Do not add ATK/MAG.
A18: Explosive Shot | B18: 6 | C18: Once | D18: 4 | E18: 2d8+6 | F18: Physical | G18: Standard | H18: 1 | I18: Foe | J18: Range 6 | K18: The target gains a "bomb". The user may choose to detonate this bomb as a trigger action on their turn, dealing 1d8+2X Bomb damage to all foes within Burst 2 of the target, where X is the amount of Marks the target has. The bomb automatically detonates when the user or target dies, or after two rounds.
A19: Tornado Bolt | B19: 7 | C19: Twice/EoT | D19: 4 | E19: 2d8+5 | F19: Physical | G19: Standard | H19: 1 | I19: Foe | J19: Line 6 (Push X) | K19: This move has Push X, where X is the amount of Marks the target has. If the target is unable to be pushed the full distance, the target gains another Mark.
A20: Pierce | B20: 8 | C20: EoT | D20: 5 | E20: 2d10+8 | F20: Physical | G20: Standard | H20: AoE | I20: Foes | J20: Pierce 6 | K20: If a target has 1+ Marks, this move ignores evasions. If a target has 2+ marks, this move also ignores negative accuracy modifiers.
A21: Serrated Arrows | B21: 9 | C21: Twice/E2T | D21: 4 | E21: 4d8+1 | F21: Physical | G21: Standard | H21: 1 | I21: Foe | J21: Range 6 | K21: This move inflicts 5 Bleed/X, where X is the amount of Marks the target has.
A22: Ballista | B22: 10 | C22: Once | D22: 5 | E22: 3d8+5X | F22: Physical | G22: Standard | H22: 1 | I22: Foe | J22: Line 6 | K22: This may only be used on a target with 2+ Marks. The X in this attack is the amount of Marks the target has.
A23: Longbow
A24: 65 HP | 12 ATK | 2 MAG | 6 PD | 6 MD | 1 MP | G24: "A high range weapon that excels in beating defence and other 'bullshit'."
A25: Skill Shot | B25: 1 | C25: Every Turn | D25: 2 | E25: 2d8+5 | F25: Physical | G25: Standard | H25: 1 | I25: Foe | J25: Range 8 | K25: This move can be used regardless of the user’s statuses (except stun) or foes’ move effects, and it cannot be prevented from doing damage.
A26: Chase Arrow | B26: 2 | C26: EoT | D26: 3 | E26: 3d8+4 | F26: Physical | G26: Standard | H26: 1 | I26: Foe | J26: Homing 6 | K26: This attack is immune to outside damage factors.
A27: Rupture | B27: 3 | C27: EoT | D27: 5 | E27: 2d8+9 | F27: Physical | G27: Standard | H27: 1 | I27: Foe | J27: Range 8 | K27: This attack ignores Evasions and outside accuracy factors. If the target's Evasions are increased or this attack is affected by accuracy factors by an effect from a foe, the target is inflicted with Bleed 5/1.
A28: Long Shot | B28: 4 | C28: E2T | D28: 3 | E28: 3d6+7 | F28: Physical | G28: Standard | H28: 1 | I28: Foe | J28: Range 8 | K28: This attack's range cannot be reduced. If the target has targeted the user from outside Range 6 before, they are inflicted with Seal/1.
A29: Bow Slam | B29: 5 | C29: E2T | D29: 3 | E29: 4d8+2 | F29: Physical | G29: Standard | H29: AoE | I29: Foes | J29: Cone 1 (Push 3) | K29: Targets are pushed in the direction of the Cone. For two rounds, the user cannot be moved by foes and is immune to effects dependent on Push/Pull.
A30: Ricochet | B30: 6 | C30: Twice/E2T | D30: 4 | E30: 2d10+6 | F30: Physical | G30: Standard | H30: 1 | I30: Foe | J30: Range 6 | K30: If the target dealt a total of 55+ damage to the user since the beginning of the user's last turn, this attack gains +2 dice.
A31: Tranquil Technique | B31: 7 | C31: Twice/EoT | D31: 4 | E31: 1d8+14 | F31: Physical | G31: Standard | H31: 1 | I31: Foe | J31: Range 8 | K31: If the target used a Reaction move since the beginning of the user's last turn, the user gains +2 accuracy on this and their next attack.
A32: Squall Volley | B32: 8 | C32: Twice/EoT | D32: 5 | E32: 1d10+6 | F32: Physical | G32: Standard | H32: 1 | I32: Foe | J32: Range 6 (Double Hit) | K32: If the user is debuffed from effects originating from foes, this attack ignores those debuffs that the user has and hits thrice instead.
A33: Arrow Rain | B33: 9 | C33: Once | D33: 4 | E33: 3d10+5 | F33: Physical | G33: Standard | H33: 1 | I33: Foes | J33: Range 6 (Splash 1) | K33: Foes hit are inflicted with any status effects the user has. The user may choose to target an empty space instead of a player for -3 accuracy on this attack.
A34: Shatter Shot | B34: 10 | C34: Once | D34: 4 | E34: 3d10+8 | F34: Physical | G34: Standard | H34: 1 | I34: Foe | J34: Range 6 | K34: This attack inverts numerical negative outside factors to damage and dice that do not originate from the user.
A35: Shortbow
A36: 60 HP | 10 ATK | 5 MAG | 9 PD | 9 MD | 3 MP | G36: "A precise weapon with high accuracy and critical chance, but lower non-critical damage."
A37: Hawkeye | B37: 1 | C37: Every Turn | D37: - | E37: - | F37: - | G37: Trigger | H37: - | I37: Self | J37: - | K37: Up to twice per turn, the user may choose to sacrifice 5 damage for +2 accuracy and +2 crit range this turn. This debuff is unremovable.
A38: Blitz | B38: 1 | C38: Every Turn | D38: 3 | E38: 2d6+0 | F38: Physical | G38: Standard | H38: 1 | I38: Foe | J38: Range 4 (Double Hit) | K38: This attack critical hits on 18+. For each successful hit, the user gains +4 damage on their next attack.
A39: Windmill | B39: 2 | C39: EoT | D39: 3 | E39: 3d6+6 | F39: Physical | G39: Standard | H39: AoE | I39: Foes | J39: Burst 1 | K39: This attack has +2 ACC and +2 CR for every target.
A40: Venom Shot | B40: 3 | C40: Twice/EoT | D40: 3 | E40: 2d8+5 | F40: Physical | G40: Standard | H40: 1 | I40: Foe | J40: Range 4 | K40: This attacks inflicts X Poison/1 on the target, where X is 2* accuracy bonus the user has. (If the user has no accuracy bonus, do not inflict Poison.)
A41: Homing Shot | B41: 4 | C41: EoT | D41: - | E41: 1d8+9 | F41: Magical | G41: Standard | H41: 1 | I41: Foe | J41: Homing 4 | K41: This move automatically hits the target. (This move still rolls accuracy.)
A42: Salvo | B42: 5 | C42: Passive | D42: - | E42: - | F42: - | G42: Passive | H42: - | I42: - | J42: - | K42: When using a multihit attack, the user may choose different targets for each individual hit. When targeting different foes, instead of adding ATK/MAG only to the first hit, add the user's ATK/MAG and +/- damage effects divided by the amount of unique targets to the damage dealt to each foe.
A43: Dampening Shot | B43: 6 | C43: Twice/E2T | D43: 3 | E43: 4d6+5 | F43: Physical | G43: Standard | H43: 1 | I43: Foe | J43: Range 4 | K43: If this move deals less than 30 damage, inflict Seal/1 on the target.
A44: Hook Shot | B44: 7 | C44: EoT | D44: 3 | E44: 2d10+8 | F44: Physical | G44: Standard | H44: 1 | I44: Foe | J44: Range 4 (Pull 3) | K44: The user chooses between pulling the target towards the user or pulling the user toward the target. If the user's accuracy is raised by at least two this turn, this move is immune to negative outside factors to damage. This move can be used as a non-damaging Movement on any obstruction to pull the user to the target or the target to the user, if possible.
A45: Trick Arrow | B45: 8 | C45: Twice/EoT | D45: 4 | E45: 3d8+5 | F45: Physical | G45: Standard | H45: 1 | I45: Foe | J45: Range 4 (Splash 1) | K45: On hit, this attack may target one additional foe within X-1 tiles from the original target. X = this attack's +CR bonus.
A46: Sagittarian Pride | B46: 9 | C46: Twice/E2T | D46: 4 | E46: 2d6+3 | F46: Physical | G46: Standard | H46: 1 | I46: Foe | J46: Range 4 (Triple Hit) | K46: For each successful hit of this attack, subsequent hits gain +1 accuracy and +1 crit range.
A47: Arrow Storm | B47: 10 | C47: Once | D47: 4 | E47: 1d8+2 | F47: Physical | G47: Standard | H47: 1 | I47: Foe | J47: Range 4 (Quadruple Hit) | K47: This attack critical hits on 18+. Critical hits on this attack have triple base dice instead of double.

Sheet Celestial
A1: Name | B1: Lvl | C1: Frequency | D1: MR | E1: Damage | H1: Target | K1: Effect
E2: Roll | F2: Type | G2: Action Type | H2: Amount | I2: Group | J2: Range and Modifiers
A3: Basic Abilities
A4: =Classes!A4 -> Basic Attack (P) / Basic Attack (M) | B4: =Classes!B4 -> B | C4: =Classes!C4 -> Every Turn | D4: =Classes!D4 -> 2 | E4: =Classes!E4 -> 1d10+2 | F4: =Classes!F4 -> Physical or Magical | G4: =Classes!G4 -> Standard | H4: =Classes!H4 -> 1 | ... K4: =Classes!K4 -> A basic attack. The user may choose either BATK (P) or BATK (M). Add the corresponding stat depending on their choice (BATK (P) = Physical Attack. BATK (M) = Magical Attack).This attack can be used even when sealed and its use cannot be prevented by any means, outside of Stun.
A5: =Classes!A5 -> Dash | B5: =Classes!B5 -> B | C5: =Classes!C5 -> Every Turn | D5: =Classes!D5 -> - | E5: =Classes!E5 -> - | F5: =Classes!F5 -> - | G5: =Classes!G5 -> Full | H5: =Classes!H5 -> - | ... K5: =Classes!K5 -> The user moves up to 1.5x their MP (rounded down) instead of 1x. (Dash is a Full action, which takes up both the Movement and Standard actions.)
A6: =Classes!A6 -> Backstep | B6: =Classes!B6 -> B | C6: =Classes!C6 -> Every Turn | D6: =Classes!D6 -> - | E6: =Classes!E6 -> - | F6: =Classes!F6 -> - | G6: =Classes!G6 -> Movement | H6: =Classes!H6 -> - | ... K6: =Classes!K6 -> This can only be used while a foe is in the user's Melee. The user moves one tile in a cardinal direction without triggering Attack of Opportunity.
A7: =Classes!A7 -> Attack of Opportunity | B7: =Classes!B7 -> B | C7: =Classes!C7 -> Every Turn | D7: =Classes!D7 -> 2 | E7: =Classes!E7 -> 1d10+2 | F7: =Classes!F7 -> Physical or Magical | G7: =Classes!G7 -> Reaction | H7: =Classes!H7 -> 1 | ... K7: =Classes!K7 -> This may be used when a foe in the user's Melee either: leaves that Melee with their Movement action, or uses a ranged attack that doesn't target the user (after damage is rolled). This Reaction still adds ATK or MAG.
A8: Celestial Abilities
A10: Lunar Rod
A11: 70 HP | 1 ATK | 13 MAG | 6 PD | 10 MD | 2 MP | G11: "Shift phases every round for a variety of effects."
A12: Lunar Phase | B12: 1 | C12: Passive | D12: - | E12: - | F12: - | G12: Passive | H12: 1 | I12: Self | J12: - | K12: At the start of a game, the user picks a Phase. At the start of each turn, the user shifts between Phases in the following order: New Moon (+1 PE/ME) -> Waxing (+1 Range) -> Full Moon (Foes get -1 dice on attacks targeting the user) -> Waning (+1 Dice) -> New, etc. This passive cannot be disabled.
A13: Moonblast | B13: 1 | C13: Every Turn | D13: 3 | E13: 2d8+5 | F13: Magical | G13: Standard | H13: 1 | I13: Foe | J13: Range 3 | K13: The user's next phase effect is doubled.
A14: Lunar Shift | B14: 2 | C14: Twice/E2T | D14: - | E14: - | F14: - | G14: Free | H14: 1 | I14: Self | J14: - | K14: The user immediately moves to their next Lunar Phase. If Moonblast's effect is active it's transferred to the new phase.
A15: Holy Light | B15: 3 | C15: EoT | D15: 3 | E15: 1d8+10 | F15: Magical | G15: Standard | H15: 1 | I15: Foe | J15: Range 7 | K15: If the user is in Waxing, they gain +1 MP until the end of their next turn.
A16: Dark Reflection | B16: 4 | C16: EoT | D16: 4 | E16: 2d8+9 | F16: Magical | G16: Standard | H16: 1 | I16: Foe | J16: Range 4 | K16: Applies the inverse of the user's current phase effect to the target for one round.
A17: Harvest Moon | B17: 5 | C17: Every Turn | D17: 3 | E17: 2d10+6 | F17: Magical | G17: Standard | H17: 1 | I17: Foe | J17: Range 4 | K17: When used while in New Moon or Full Moon Phase, heal the user by 10% of the damage done.
A18: Tidal Wave | B18: 6 | C18: Twice | D18: 4 | E18: 3d8+7 | F18: Magical | G18: Standard | H18: AoE | I18: Foes | J18: Burst 1 | K18: Targets hit are moved one tile towards the user. This move is affected by the +Range from Waxing Phase.
A19: Tidal Locking | B19: 7 | C19: Twice | D19: 4 | E19: 2d10+7 | F19: Magical | G19: Standard | H19: 1 | I19: Foe | J19: Melee | K19: The user doesn't change phases at the start of their next turn. This move may be used as a non-damaging standard.
A20: Blood Moon | B20: 8 | C20: EoT | D20: 4 | E20: 2d8+6 | F20: Magical | G20: Standard | H20: 2 | I20: Foes | J20: Range 3 | K20: If the user is in Waxing or Waning, this move inflicts 5/1 Poison, otherwise it inflicts 5/1 Bleed.
A21: Celestial Blessing | B21: 9 | C21: Once | D21: - | E21: - | F21: - | G21: Free | H21: AoE | I21: Self and Allies | J21: Burst 1 | K21: All targets in range gain the effect of the user's next phase until the start of the user's next turn. Next turn, the user's phase has no effect, and phase-specific move effects cannot trigger. This is not affected by Moonblast.
A22: Gravity Crash | B22: 10 | C22: Once | D22: 4 | E22: 2d10+9 | F22: Magical | G22: Standard | H22: 1 | I22: Foe | J22: Melee | K22: This move has a different effect based on the phase it's used in: New Moon: The target is Sealed/1 Waxing (Push 2): If the target can't be pushed fully, they take 15 extra damage. Full Moon: All the target's AoE moves are single target for one round. Waning: This attack has bomb dice.
A23: Solar Rod
A24: 60 HP | 2 ATK | 14 MAG | 9 PD | 9 MD | 1 MP | G24: "Burn the opponent and benefit from their suffering."
A25: Sun Rays | B25: 1 | C25: Every Turn | D25: 2 | E25: 2d8+4 | F25: Magical | G25: Standard | H25: 1 | I25: Foe | J25: Homing 5 | K25: The target is inflicted with unremovable Burn 3/1.
A26: Searing Shot | B26: 2 | C26: EoT | D26: 3 | E26: 2d10+4 | F26: Magical | G26: Standard | H26: 1 | I26: Foe | J26: Range 3 | K26: The user's next attack gains +5 damage.
A27: Brilliant Flash | B27: 3 | C27: Twice/EoT | D27: 3 | E27: 2d10+7 | F27: Magical | G27: Standard | H27: AoE | I27: Foes | J27: Beam 2 | K27: Targets who are burned have their Burn extended by one round.
A28: Firestorm | B28: 4 | C28: E2T | D28: 4 | E28: 2d10+3 | F28: Magical | G28: Standard | H28: 2 | I28: Foes | J28: Homing 4 | K28: If one of the targets missed the user with an attack on their last turn, the user's next attack gains +X damage, where X = 3 * the MR of the attack that missed.
A29: Meteor Shower | B29: 5 | C29: Twice/EoT | D29: 4 | E29: 3d8+5 | F29: Magical | G29: Standard | H29: 1 | I29: Foe | J29: Homing 5 (Splash 1) | K29: For every target in range that is Burned, this attack gains a die.
A30: Radiant Dawn | B30: 6 | C30: E2T | D30: - | E30: - | F30: - | G30: Swift | H30: 1 | I30: Self or Foe | J30: Range 4 | K30: If used on a foe, the next time they are Burned, the burn damage is increased by 3. If used on self, the next time the user inflicts Burn, they heal the damage dealt by the burn whenever the foe takes it.
A31: Pyroclasm | B31: 7 | C31: Once | D31: 4 | E31: 1d6+2 | F31: Magical | G31: Standard | H31: 3 | I31: Foes | J31: Global | K31: All targets hit are inflicted with unremovable 3 Burn/1. This move and its burn are immune to outside factors. Do not add MAG to the roll.
A32: Supernova | B32: 8 | C32: Twice / EoT | D32: 4 | E32: 3d8+2 | F32: Magical | G32: Standard | H32: AoE | I32: Foes | J32: Star 2 | K32: Targets in Burst 1 are inflicted with unremovable 5 Burn/2. Other targets are inflicted with unremovable 5 Burn/1.
A33: Conflagration | B33: 9 | C33: Twice/EoT | D33: 4 | E33: 3d8+5 | F33: Magical | G33: Standard | H33: 1 | I33: Foe | J33: Melee | K33: If this attack has a damage buff from a Solar Rod move applied to it, double the additional damage dealt from it.
A34: Solar Flare | B34: 10 | C34: Once | D34: 5 | E34: 4d8+3 | F34: Magical | G34: Standard | H34: AoE | I34: Foes | J34: Pierce 4 | K34: This attack gains Bomb Dice if a target is burned.
A35: Star Rod
A36: 65 HP | 0 ATK | 11 MAG | 12 PD | 12 MD | 2 MP | G36: "A defensive weapon that controls and manipulates enemy movement."
A37: Geodesic | B37: 1 | C37: Passive | D37: - | E37: - | F37: - | G37: Passive | H37: - | I37: Self | J37: - | K37: The user takes 80% damage from attacks originating from their Range 3, and 10% more for every tile closer or farther away.
A38: Star Storm | B38: 1 | C38: Every Turn | D38: 3 | E38: 2d8+5 | F38: Magical | G38: Standard | H38: 1 | I38: Foe | J38: Range 5 (Splash 1) | K38: If the target(s), on their next turn, moves towards the user, this deals an additional 1d8 damage.
A39: Orbit | B39: 2 | C39: Twice/EoT | D39: 3 | E39: 1d8+0 | F39: Magical | G39: Standard | H39: AoE | I39: Foes | J39: Star 3 | K39: On their next turn, targets that perform attacks that do not target the user (if they are able to target the user) take 2d8+8 damage. Additionally, targets who end their next turn in the user's Range 3 take 2d8+8 damage.
A40: Cosmic Power | B40: 3 | C40: Twice/EoT | D40: 4 | E40: 3d6+7 | F40: Magical | G40: Standard | H40: 1 | I40: Foe | J40: Range 4 | K40: If the opponent is able to move to a different tile type before the end of their next turn, but doesn't, this deals an additional 1d8+10 damage and inflicts 6 Cripple/1.
A41: Focal Point | B41: 4 | C41: Every Turn | D41: - | E41: - | F41: - | G41: Trigger | H41: - | I41: Self | J41: - | K41: Gain either Exotic Star or Sequence Star until the start of the user's next turn. This move cannot be used while the user has a star active. Exotic Star: Whenever the user deals damage to a foe outside their melee, deal an additional 1d8 damage. If Exotic Star was also selected last turn, instead deal 1d4 additional damage. Sequence Star: Geodesic instead calculates based on Range 1. If Sequence Star was also selected last turn, Geodesic's base is 90%.
A42: White Hole | B42: 5 | C42: EoT | D42: 3 | E42: 2d8+10 | F42: Magical | G42: Standard | H42: 1 | I42: Foe | J42: Range 6 | K42: If the user is in Exotic Star, the target is pushed to a space within the user's Range 4-6. The push must be in the direction of the attack. After using this move, the user's movement action is disabled for the rest of their turn.
A43: Black Hole | B43: 5 | C43: EoT | D43: 3 | E43: 2d8+7 | F43: Magical | G43: Standard | H43: 1 | I43: Foe | J43: Range 6 | K43: If the user is in Sequence Star, the target is pulled to a space within the user's Range 2. The pull must be in the direction of the attack.
A44: Gravitation | B44: 6 | C44: E2T | D44: - | E44: - | F44: - | G44: Swift | H44: 1 | I44: Foe | J44: Range 3 | K44: The user chooses another player (can be the user, but not the target's allies) in Range 3. If the target does not attack that player on their next turn, they take 2d8+5 damage.
A45: Singularity | B45: 7 | C45: Thrice/E2T | D45: - | E45: - | F45: - | G45: Movement | H45: 1 | I45: Tile | J45: Burst 3 | K45: Select a tile in the user's Burst 3 (can be the user's tile). Up to three foes and/or allies are pulled two spaces toward the selected tile in any order.
A46: Negative Mass | B46: 8 | C46: Twice/EoT | D46: 3 | E46: 1d8+12 | F46: Magical | G46: Standard | H46: AoE | I46: Foes | J46: Burst 2 | K46: Targets cannot damage the user from melee range for one round. The user must be in Exotic Star to use this ability.
A47: Planetary Nebula | B47: 8 | C47: Twice/EoT | D47: 4 | E47: 2d8+5 | F47: Magical | G47: Standard | H47: AoE | I47: Foes | J47: Star 3 | K47: Foes that can enter the user’s melee can only damage them from melee for one round. The user must be in Sequence Star to use this ability.
A48: Asteroid Belt | B48: 9 | C48: Twice/EoT | D48: - | E48: - | F48: - | G48: Swift or Standard | H48: - | I48: Self | J48: - | K48: If the user is in Exotic Star, ranged attacks on the user lose Xd4 damage for one round, where X is the range the attack was used at (max of 3d4). If in Sequence Star, foes who willingly enter the user's melee range before the user's next turn take 2d8+5 damage. This ability may be used as a Standard to extend the effect's duration by an additional round.
A49: Accretion Disc | B49: 10 | C49: Once | D49: 4 | E49: 4d8+5 | F49: Magical | G49: Standard | H49: AoE | I49: Foes | J49: Star 4 | K49: For one round, foes cannot enter or leave the user's Star 2. Targets are inflicted with 6 Cripple/1.

Sheet Clairvoyant
B1: Lvl | C1: Frequency | D1: MR | E1: Damage | H1: Target | K1: Effect
E2: Roll | F2: Type | G2: Action Type | H2: Amount | I2: Group | J2: Range and Modifiers
A3: Basic Abilities
A4: =Classes!A4 -> Basic Attack (P) / Basic Attack (M) | B4: =Classes!B4 -> B | C4: =Classes!C4 -> Every Turn | D4: =Classes!D4 -> 2 | E4: =Classes!E4 -> 1d10+2 | F4: =Classes!F4 -> Physical or Magical | G4: =Classes!G4 -> Standard | H4: =Classes!H4 -> 1 | ... K4: =Classes!K4 -> A basic attack. The user may choose either BATK (P) or BATK (M). Add the corresponding stat depending on their choice (BATK (P) = Physical Attack. BATK (M) = Magical Attack).This attack can be used even when sealed and its use cannot be prevented by any means, outside of Stun.
A5: =Classes!A5 -> Dash | B5: =Classes!B5 -> B | C5: =Classes!C5 -> Every Turn | D5: =Classes!D5 -> - | E5: =Classes!E5 -> - | F5: =Classes!F5 -> - | G5: =Classes!G5 -> Full | H5: =Classes!H5 -> - | ... K5: =Classes!K5 -> The user moves up to 1.5x their MP (rounded down) instead of 1x. (Dash is a Full action, which takes up both the Movement and Standard actions.)
A6: =Classes!A6 -> Backstep | B6: =Classes!B6 -> B | C6: =Classes!C6 -> Every Turn | D6: =Classes!D6 -> - | E6: =Classes!E6 -> - | F6: =Classes!F6 -> - | G6: =Classes!G6 -> Movement | H6: =Classes!H6 -> - | ... K6: =Classes!K6 -> This can only be used while a foe is in the user's Melee. The user moves one tile in a cardinal direction without triggering Attack of Opportunity.
A7: =Classes!A7 -> Attack of Opportunity | B7: =Classes!B7 -> B | C7: =Classes!C7 -> Every Turn | D7: =Classes!D7 -> 2 | E7: =Classes!E7 -> 1d10+2 | F7: =Classes!F7 -> Physical or Magical | G7: =Classes!G7 -> Reaction | H7: =Classes!H7 -> 1 | ... K7: =Classes!K7 -> This may be used when a foe in the user's Melee either: leaves that Melee with their Movement action, or uses a ranged attack that doesn't target the user (after damage is rolled). This Reaction still adds ATK or MAG.
A8: Clairvoyant Abilities
A10: Orb
A11: 60 HP | 7 ATK | 13 MAG | 5 PD | 16 MD | 1 MP | G11: "Delay your attacks to the future for enhanced effects."
A12: Future Sight | B12: 1 | C12: Passive | D12: - | E12: - | F12: - | G12: Passive | H12: - | I12: - | J12: - | K12: The user's Delay attacks always land if they hit, even if the user is dead. Delay: Delay moves have their damage and effects delayed for a specified number of rounds, landing at the start of the user's turn. Damage is rolled when the move is used, with damage altering effects applied on use
A13: Augur | B13: 1 | C13: Every Turn | D13: 3 | E13: 3d8+1 | F13: Magical | G13: Standard | H13: 1 | I13: Foe | J13: Homing 5 | K13: Before accuracy, the user may choose to give this move Delay-1 for an additional 5 damage or +3 Critical Range on this move, or Delay-2 for both.
A14: Echo Burst | B14: 2 | C14: Every Turn | D14: 3 | E14: 2d8+7 | F14: Magical | G14: Standard | H14: 1 | I14: Foe | J14: Homing 5 (Splash 1) | K14: Before accuracy, the user may choose to give this move Delay-1. If they do, it loses Splash, but the user gains +5 DR until the move deals damage.
A15: Scry | B15: 3 | C15: EoT | D15: 3 | E15: 2d8+4 | F15: Magical | G15: Standard | H15: AoE | I15: Foes | J15: Cone 2 | K15: The user gains +5 damage on their next attack. Before accuracy, the user may give this move Delay-1 to extend this attack's Cone by 1.
A16: Spirit Shackle | B16: 4 | C16: Twice/EoT | D16: 4 | E16: 1d8+3 | F16: Magical | G16: Standard | H16: 3 | I16: Foes | J16: Global | K16: This move has Delay-X, where X is the number of Foes hit. This move is immune to outside factors. This does not add MAG.
A17: Dawn Break | B17: 5 | C17: EoT | D17: 3 | E17: 1d8+9 | F17: Magical | G17: Standard | H17: 1 | I17: Foe | J17: Range 7 | K17: This ability has Delay-2. Until this ability lands, all of the user's attacks on the target have -1 MR. The user may increase the Delay by 1 for an additional -1 MR on the target.
A18: Prismatic Burst | B18: 6 | C18: E2T | D18: 4 | E18: 3d6+6 | F18: Magical | G18: Standard | H18: AoE | I18: Foes | J18: Burst 1 | K18: The user may choose to add Delay-X to this ability to give it +X dice, where X is the amount of targets hit.
A19: Omen | B19: 7 | C19: Once | D19: - | E19: - | F19: - | G19: Swift | H19: 1 | I19: Self | J19: - | K19: The user's next attack has an extra turn of delay with a doubled delay bonus.
A20: Foresight | B20: 7 | C20: Once | D20: - | E20: - | F20: - | G20: Reaction | H20: 1 | I20: Foe | J20: - | K20: This may be used when the user is attacked, after damage is rolled. 10% of the attack's damage is removed and added to all of the user's currently delayed attacks.
A21: Prophecy | B21: 8 | C21: Twice/EoT | D21: 4 | E21: 1d8+12 | F21: Magical | G21: Standard | H21: 1 | I21: Foe | J21: Homing 6 | K21: All the user's currently delayed moves land at the same time as this attack.
A22: Corruption | B22: 9 | C22: Twice/EoT | D22: 4 | E22: 3d8+6 | F22: Magical | G22: Standard | H22: 1 | I22: Foe | J22: Range 5 | K22: This attack inflicts 5 Poison/1 on hit. Before accuracy, the user may choose to give this move Delay-1 for extending the Poison duration by 1 round, or Delay-2 for +5 poison damage.
A23: Requite | B23: 10 | C23: Once | D23: 5 | E23: 3d8+11 | F23: Magical | G23: Standard | H23: 1 | I23: Foe | J23: Range 5 | K23: This move has Delay-1 and a Delay bonus of +10 damage if the user dies before this attack lands.
A24: Pendulum
A25: 65 HP | 5 ATK | 9 MAG | 12 PD | 9 MD | 1 MP | G25: "A control weapon that requires its opponents to use their abilities carefully."
A26: Oscillations | B26: 1 | C26: Passive | D26: - | E26: - | F26: - | G26: Passive | H26: - | I26: - | J26: - | K26: The user starts the game with one Momentum (max three). The user gains +1 MP per Momentum. Momentum can be spent even if the MP was used previously on their turn. Conditional out-of-turn damage effects of this weapon can trigger only once, excluding damage from statuses.
A27: Entrance | B27: 1 | C27: Every Turn | D27: 2 | E27: 2d10+3 | F27: Magical | G27: Standard | H27: 1 | I27: Foe | J27: Range 6 | K27: For one round, if the target uses a move on the user, the user gains one Momentum. This move can be used while Sealed.
A28: Torment | B28: 2 | C28: Every Turn | D28: 4 | E28: 5d4+3 | F28: Magical | G28: Standard | H28: 1 | I28: Foe | J28: Range 4 | K28: After accuracy, the user may spend 1 Momentum to either: extend the effect of their next Pendulum Standard/Full by one round (including status effects), or gain 2d8+1 advantage damage on their next Standard/Full attack.
A29: Action and Reaction | B29: 3 | C29: Twice/EoT | D29: - | E29: - | F29: - | G29: Trigger | H29: 1 | I29: Self | J29: - | K29: This can only be used at the start of the user's turn. The user permanently sacrifices 1 MP to increase their Momentum cap by 1 (preserving their Momentum stacks). Additionally, the user activates the ability to passively generate 1 Momentum after using a Standard/Full which targets a player (including self, except Dash), once per turn. Dowse is disabled for one round.
A30: Dowse | B30: 3 | C30: Every Turn | D30: - | E30: - | F30: - | G30: Trigger | H30: 1 | I30: Self | J30: - | K30: Once per turn, the user's next Standard/Full attack this turn unremovably gains advantage damage rolls & -2 DMG. Action and Reaction's passive Momentum generation is deactivated. (Dowse cannot trigger Amplifier).
A31: Hallucinations | B31: 4 | C31: E2T | D31: 3 | E31: Varies | F31: Magical | G31: Standard | H31: 1 | I31: Foe | J31: Range 4 | K31: Choose Dream or Nightmare. Dream: 5d6+1 damage roll. The user gains two Momentum, while the target gains +3 DR/1 or +3 DMG/1 (chosen by the user). Nightmare: 3d10+2 damage roll. For one round, if the target uses a Once/Twice/Thrice move, they take 3d8+5 damage. The user may spend 2 Momentum to inflict -25% damage on such attacks of the target for one round.
A32: Clacker Volley | B32: 5 | C32: EoT | D32: 3 | E32: 3d8+6 | F32: Magical | G32: Standard | H32: 2 | I32: Foes | J32: Line 3 (Push 1) | K32: Targets are inflicted with Confusion/1. If at least two targets have hit the user with Standard/Full attacks last round, one of the targets hit (chosen by the user) is also Sealed/1. The Seal's duration cannot be extended by Torment.
A33: Angular Momentum | B33: 6 | C33: Twice/EoT | D33: - | E33: - | F33: - | G33: Free | H33: 1 | I33: Self | J33: - | K33: The user spends Momentum to gain +2 EVA/1 for every two Momentum spent. One additional Momentum may be spent to extend this buff's duration to two rounds.
A34: Mass Hysteria | B34: 7 | C34: Twice/EoT | D34: 5 | E34: 6d6+2 | F34: Magical | G34: Full | H34: AoE | I34: Foes | J34: Cone 2 | K34: The user can spend 1 Momentum per effect to give this ability any combination of the following effects: - Make this attack Burst 2, - Use this move as a Standard (1 Momentum is refunded if it misses 2+ targets), - Reduce 2d4+3 DMG from the next Standard/Full attack of each target hit, - Inflict Confusion/2.
A35: Hypnotic Daze | B35: 8 | C35: Twice/E2T | D35: 4 | E35: 1d12+10 | F35: Magical | G35: Standard | H35: 1 | I35: Foe | J35: Range 4 | K35: If the target uses a non-Weapon/non-Basic move in the next two rounds, they take 3d6+3 bomb damage. At the cost of one Momentum, the target's Frees and Triggers become Swifts for one round. If Dowse was used this turn, this move has +1 ACC.
A36: Nihil | B36: 9 | C36: Once | D36: 4 | E36: 3d10+6 | F36: Magical | G36: Standard | H36: 1 | I36: Foe | J36: Homing 3 | K36: For one round, if the target fails to buff the user on their turn, they take 7d4+4 damage. While under this effect, the target may target foes in their Range 3 with moves that can normally buff Self and/or Allies.
A37: Shatter Psyche | B37: 10 | C37: Once | D37: 4 | E37: 4d8+6 | F37: Magical | G37: Standard | H37: 1 | I37: Foe | J37: Melee | K37: For one round, if the target deals 45+ damage on their turn, they take 4d8+6 damage. The user may spend X Momentum to decrease the required damage threshold by 6X.
A38: Tarot Cards
A39: 65 HP | 5 ATK | 11 MAG | 9 PD | 10 MD | 2 MP | G39: "A luck weapon - gamble on your attacks to give you a massive advantage... or disadvantage!"
A40: Discard | B40: 1 | C40: Every Turn | D40: 2 | E40: 2d8+5 | F40: Magical | G40: Standard | H40: 1 | I40: Foe | J40: Range 4 | K40: On an accuracy roll of 15+, the user gains 1 Discard stack. As a Reaction to an attack of a Foe within Range 4 after its accuracy roll, the user may spend one stack to give that attack -2 ACC.
A41: Maverick | B41: 2 | C41: EoT | D41: 3 | E41: 2d8+4 | F41: Magical | G41: Standard | H41: AoE | I41: Foes | J41: Pierce 3 | K41: By default, roll a d4 after rolling damage. This determines damage multiplication: 1 = 0.5x, 2 = 1x, 3 = 1.5x, 4 = 2x. The user may choose to not roll the d4 before damage.
A42: Roulette | B42: 3 | C42: EoT | D42: 3 | E42: 3d8+3 | F42: Magical | G42: Standard | H42: 1 | I42: Foe | J42: Range 5 | K42: Roll a 1d8 to inflict a random status on the opponent, then roll a d3. If the d3 roll is 1, status the user instead. Statuses: 1 = 10 Bleed/1, 2 = 10 Poison/1, 3 = 10 Burn/1, 4 = Confusion/2, 5 = Seal/1, 6 = Root/1, 7 = 6 Cripple/1, 8 = Stun/1.
A43: Dealer | B43: 4 | C43: Thrice/EoT | D43: - | E43: - | F43: - | G43: Standard | H43: AoE | I43: All | J43: Global | K43: Roll Xd13 where X is the number of players alive. P1 takes the first dice roll as damage, P2 the second roll, etc. This is immune to all outside factors.
A44: Gamble | B44: 5 | C44: Twice/EoT | D44: 3 | E44: 3d8+0 | F44: Magical | G44: Standard | H44: 1 | I44: Foe | J44: Range 3 | K44: Roll d7. 1 = Subtract the target's ATK and MAG, 2 = Subtract the higher of the target's offensive stats, 3 = Subtract the user's ATK, 4 = Add the user's ATK, 5 = Add the higher of the target's offensive stats, 6 = Add the user's MAG again, 7 = Add the user's ATK and the target's ATK and MAG. This ability is immune to outside factors to damage. (These effects do not count as negative damage factors. This move still adds the user's MAG.)
A45: Blackjack | B45: 6 | C45: Twice | D45: 3 | E45: 3d8+5 | F45: Magical | G45: Standard | H45: 1 | I45: Foe | J45: Range 3 | K45: On a successful hit, roll 2d10, treating 1s as either 1 or 11 (user’s choice). The user may choose to roll additional 1d10s to add to the roll. If the total is 17-20, this attack gains 1 base dice. On a total of 21, this attack instead gains 3 base dice. On a total of 22 or higher, the attack instead loses 2 base dice.
A46: Hi-Lo | B46: 7 | C46: Twice/EoT | D46: 4 | E46: Xd10+0 | F46: Magical | G46: Standard | H46: 1 | I46: Foe | J46: Range 3 | K46: Roll a d10. The user predicts whether the next d10 result will be higher or lower than the previous result, then rolls again. On a correct guess, this attack gains +2 base dice and the user may continue predicting and rolling (max 5 guesses) or choose to stop. On a failed guess, the user stops and the attack loses half of its total base dice. If the roll is the same as the previous, reroll that die.
A47: Full House | B47: 8 | C47: Once | D47: 4 | E47: 7d8+0 | F47: Magical | G47: Standard | H47: 1 | I47: Foe | J47: Range 4 | K47: Roll 3d3. For every 3 rolled, this attack gains +1 die. Only add half MAG.
A48: House Advantage | B48: 9 | C48: Twice/EoT | D48: 4 | E48: 2d12+6 | F48: Magical | G48: Standard | H48: AoE | I48: Foes | J48: Cone 2 | K48: Targets are inflicted with -7 DMG/1. Each target may choose to roll a d10 and a d2 together. If the d2 rolls 1, add the d10 to their debuff, if it rolls 2, subtract it instead.
A49: Stacked Deck | B49: 10 | C49: Once | D49: - | E49: 6d8+0 | F49: Magical | G49: Standard | H49: 1 | I49: Foe | J49: Melee | K49: In place of an accuracy roll, roll a 1d14 for an effect: 1 = Set the user's HP to 1. 2 = Deals no damage, and the user is Stunned on their next turn. 3 = The target is instead healed by the damage roll. 4 = This attack misses. 5 = Deals 0.5x damage. 6 = The user takes recoil equal to half the damage dealt by this attack. 7 = Cleanse all statuses and numerical debuffs from the user & reset their other moves' frequencies. 8 = This attack has Bomb dice. 9 = Inflict 5 Burn/1, 5 Bleed/1, and 5 Poison/1 on the target (stacks with other statuses). 10 = The user gains a Once/Reaction: "reroll the Cards move's secondary effect". 11 = Deals 1.5x damage. 12 = Inflict Seal/1. 13 = Inflict Stun/1. 14 = This attack has unremovable thrice dice.

Sheet Dark
A1: Name | B1: Lvl | C1: Frequency | D1: MR | E1: Damage | H1: Target | K1: Effect
E2: Roll | F2: Type | G2: Action Type | H2: Amount | I2: Group | J2: Range and Modifiers
A3: Basic Abilities
A4: =Classes!A4 -> Basic Attack (P) / Basic Attack (M) | B4: =Classes!B4 -> B | C4: =Classes!C4 -> Every Turn | D4: =Classes!D4 -> 2 | E4: =Classes!E4 -> 1d10+2 | F4: =Classes!F4 -> Physical or Magical | G4: =Classes!G4 -> Standard | H4: =Classes!H4 -> 1 | ... K4: =Classes!K4 -> A basic attack. The user may choose either BATK (P) or BATK (M). Add the corresponding stat depending on their choice (BATK (P) = Physical Attack. BATK (M) = Magical Attack).This attack can be used even when sealed and its use cannot be prevented by any means, outside of Stun.
A5: =Classes!A5 -> Dash | B5: =Classes!B5 -> B | C5: =Classes!C5 -> Every Turn | D5: =Classes!D5 -> - | E5: =Classes!E5 -> - | F5: =Classes!F5 -> - | G5: =Classes!G5 -> Full | H5: =Classes!H5 -> - | ... K5: =Classes!K5 -> The user moves up to 1.5x their MP (rounded down) instead of 1x. (Dash is a Full action, which takes up both the Movement and Standard actions.)
A6: =Classes!A6 -> Backstep | B6: =Classes!B6 -> B | C6: =Classes!C6 -> Every Turn | D6: =Classes!D6 -> - | E6: =Classes!E6 -> - | F6: =Classes!F6 -> - | G6: =Classes!G6 -> Movement | H6: =Classes!H6 -> - | ... K6: =Classes!K6 -> This can only be used while a foe is in the user's Melee. The user moves one tile in a cardinal direction without triggering Attack of Opportunity.
A7: =Classes!A7 -> Attack of Opportunity | B7: =Classes!B7 -> B | C7: =Classes!C7 -> Every Turn | D7: =Classes!D7 -> 2 | E7: =Classes!E7 -> 1d10+2 | F7: =Classes!F7 -> Physical or Magical | G7: =Classes!G7 -> Reaction | H7: =Classes!H7 -> 1 | ... K7: =Classes!K7 -> This may be used when a foe in the user's Melee either: leaves that Melee with their Movement action, or uses a ranged attack that doesn't target the user (after damage is rolled). This Reaction still adds ATK or MAG.
A8: Dark Abilities
A10: Athame
A11: 65 HP | 6 ATK | 7 MAG | 15 PD | 10 MD | 3 MP | G11: "Gradually sacrifice your own HP to permanently boost your damage with no limit."
A12: Crimson Pact | B12: 1 | C12: Passive | D12: - | E12: - | F12: - | G12: Passive | H12: - | I12: - | J12: - | K12: Whenever the user damages a foe, they sacrifice HP equal to 10% of the total damage the foe took, if able. Then, they gain permanent bonus damage equal to the damage they took. (Bonus damage is also gained through effect-derived CP.)
A13: Bloodrush | B13: 1 | C13: Every Turn | D13: 2 | E13: 2d8+5 | F13: Magical | G13: Standard | H13: 1 | I13: Foe | J13: Range 3 | K13: If this move is used in Melee range, before accuracy, the user gains +3 DMG and +1 MP for one round.
A14: Infusion | B14: 2 | C14: E2T | D14: 4 | E14: 1d10+8 | F14: Magical | G14: Standard | H14: AoE | I14: Foes | J14: Pierce 4 | K14: For one round, the user gains +DR equal to the amount of bonus damage gained from this attack with Crimson Pact.
A15: Purloin Youth | B15: 3 | C15: E2T | D15: 3 | E15: 3d8+7 | F15: Magical | G15: Standard | H15: 1 | I15: Foe | J15: Melee | K15: For one round, the target suffers -1 EVA and the user gains +1 EVA. If the target's next Standard/Full attack misses on the user, the user still rolls the attack's damage and sacrifices 10% of the damage (excluding outside factors) to Crimson Pact.
A16: Defile | B16: 4 | C16: EoT | D16: 4 | E16: 1d10+5 | F16: Magical | G16: Standard | H16: AoE | I16: Foes | J16: Burst 1 | K16: Targets are inflicted with 5 Poison/1. For each target hit, the user sacrifices 1 HP to Crimson Pact.
A17: Sanctified Blade | B17: 5 | C17: Once | D17: - | E17: - | F17: - | G17: Swift | H17: 1 | I17: Self | J17: - | K17: Crimson Pact's sacrifice amount on the user's next single-target attack is increased by 10%. If the Foe has targeted the user since the beginning of their last turn, the amount is increased by an additional 5%.
A18: Massacre | B18: 6 | C18: E2T | D18: 3 | E18: 2d10+12 | F18: Magical | G18: Standard | H18: 1 | I18: Foe | J18: Melee | K18: If an opponent is killed using this move, the CP gained from it is doubled. (Round down the amount gained normally before doubling.)
A19: Black Magic | B19: 7 | C19: Passive | D19: - | E19: - | F19: - | G19: Passive | H19: - | I19: - | J19: - | K19: When the user has 8+ CP, they gain +1 MP permanently. With 12+ CP, they gain +3 DR permanently. With 15+ CP, they gain +5 MAG permanently.
A20: Exsanguinate | B20: 8 | C20: Once | D20: 4 | E20: 2d8+6 | F20: Magical | G20: Standard | H20: 1 | I20: Foe | J20: Melee | K20: This move does not benefit from the user's CP damage bonus. The user's current Black Magic buffs are doubled.
A21: Siphon Soul | B21: 9 | C21: Once | D21: 4 | E21: 3d10+5 | F21: Magical | G21: Standard | H21: 1 | I21: Foe | J21: Range 3 | K21: Bonus damage to this move from Crimson Pact also restores the user's HP.
A22: Oblation | B22: 10 | C22: Once | D22: 4 | E22: 2d8+7 | F22: Magical | G22: Standard | H22: 1 | I22: Foe | J22: Range 3 | K22: This move gets double bonus damage from Crimson Pact. For one round, the user's moves do not benefit from CP bonus.
A23: Chalice
A24: 65 HP | 0 ATK | 13 MAG | 15 PD | 15 MD | 1 MP | G24: "Summons a blood tile from which you can poison the opponent and extend your eldritch powers."
A25: Pact of the Elder | B25: 1 | C25: Passive | D25: - | E25: - | F25: - | G25: Passive | H25: - | I25: - | J25: - | K25: While active, the user's Blood tile creates a Blood Storm effect in Burst 1 of the tile. Foes must use an additional MP to exit the Blood Storm. If the user is within Range 3 of their Blood tile, they may choose to have their abilities originate from the Blood tile. By doing so, the attack gains +3 damage. This ability follows range rule.
A26: Blood Storm | B26: 1 | C26: Every Turn | D26: - | E26: - | F26: - | G26: Free | H26: - | I26: - | J26: Homing 4 | K26: The user either: sacrifices 10 HP to place a Blood tile in range, or removes their Blood tile. The user can only have one Blood at once, and Blood tiles cannot be replaced.
A27: Tainted Faith | B27: 1 | C27: Every Turn | D27: 2 | E27: 2d8+3 | F27: Magical | G27: Standard | H27: 1 | I27: Foe | J27: Homing 5 | K27: The target is inflicted with unremovable 5 Poison/1. If this ability originates from the user's Blood tile, it has -1 range but the target is inflicted with unremovable 7 Poison/1 instead.
A28: Defiled Tentacles | B28: 2 | C28: EoT | D28: 3 | E28: 2d10+4 | F28: Magical | G28: Standard | H28: 2 | I28: Foes | J28: Homing 4 (Pull 2) | K28: If this ability originates from the user's Blood tile, it becomes 1/Foe/Range 5 and has Pull 4 instead.
A29: Accursed Brew | B29: 3 | C29: EoT | D29: 4 | E29: 2d6+6 | F29: Magical | G29: Standard | H29: AoE | I29: Foes | J29: Cone 1 | K29: This ability gains +1 dice for every Poisoned target in range. If this ability originates from the user's Blood tile, it deals damage to all foes in the user's Blood Storm instead.
A30: Crimson Rain | B30: 4 | C30: Twice/EoT | D30: 4 | E30: 1d6+4 | F30: Magical | G30: Standard | H30: 1 | I30: Foe | J30: Global | K30: The next time the user uses Blood Storm or Bloodlet, subtract the damage dealt by this attack from the HP sacrificed (this effect does not stack with itself). This ability is immune to outside factors to damage. Do not add MAG.
A31: Toxic Blood | B31: 5 | C31: Twice/E2T | D31: - | E31: - | F31: - | G31: Free | H31: - | I31: - | J31: - | K31: For 1 round, Foes who enter the user's Blood Storm are inflicted with unremovable 3 Poison/1. If already inflicted with unremovable Poison, increase its damage by 3 and its duration by 1.
A32: Hemokinesis | B32: 6 | C32: Twice/EoT | D32: 4 | E32: 4d8+0 | F32: Magical | G32: Standard | H32: 1 | I32: Foe | J32: Homing 4 (Splash 1) | K32: The user's Blood tile is moved to the tile the target is currently on. This ability may be used as a non-damaging standard to move the Blood tile to a tile in range. The user then loses 5 HP.
A33: Bloodlet | B33: 7 | C33: Twice | D33: - | E33: - | F33: - | G33: Free | H33: - | I33: - | J33: - | K33: The user sacrifices 7 HP to permanently increase the Burst of their Blood Storm by 1. Until the start of the user's next turn, the user and allies in the user's Blood Storm gain +3 DMG and +1 ACC. A Blood Storm may not increase in size more than once.
A34: Blood Ties | B34: 8 | C34: Twice/EoT | D34: 4 | E34: 3d8+4 | F34: Magical | G34: Standard | H34: 3 | I34: Foes | J34: Homing 2 | K34: This ability must originate from the user's Blood tile. For 1 round, targets in the user's Blood Storm cannot exit the Blood Storm willingly.
A35: Price of Power | B35: 9 | C35: Once | D35: 4 | E35: 3d10+2 | F35: Magical | G35: Standard | H35: 1 | I35: Foe | J35: Melee | K35: Before accuracy, the user and allies within the Blood Storm may each sacrifice 5 HP to give this attack +1 dice for every 5 HP sacrificed (max of +3 dice).
A36: Eldritch Horror | B36: 10 | C36: Once | D36: 5 | E36: 2d10+4 | F36: Magical | G36: Standard | H36: AoE | I36: Foes | J36: Varies | K36: This ability must originate from the user's Blood tile and deals damage to all Foes in the Blood Storm. Poisoned targets take an additional 1d10+4 damage and have their Poison extended by 1 round. Non-poisoned targets are inflicted with unremovable 3X Poison/1, -2X DR/1 and -2X DMG/1, where X is the amount of targets in the Blood Storm.
A37: Scythe
A38: 65 HP | 8 ATK | 13 MAG | 9 PD | 9 MD | 2 MP | G38: "Steals the opponent's HP with every attack."
A39: Reaper's Touch | B39: 1 | C39: Passive | D39: - | E39: - | F39: - | G39: Passive | H39: - | I39: - | J39: - | K39: Whenever the user damages a foe, the user heals 1/8 of the damage dealt.
A40: Reap | B40: 1 | C40: Every Turn | D40: 3 | E40: 2d8+6 | F40: Magical | G40: Standard | H40: 1 | I40: Foe | J40: Melee | K40: Reaper's Touch heals 1/5 of the damage dealt by this attack instead of 1/8.
A41: Haunted Swing | B41: 2 | C41: EoT | D41: 4 | E41: 3d6+6 | F41: Magical | G41: Standard | H41: AoE | I41: Foes | J41: Beam 2 | K41: Targets at full HP take an additional 5 damage. The user heals 5 HP for each target this triggers on.
A42: Pestilent Strike | B42: 3 | C42: EoT | D42: 3 | E42: 2d10+9 | F42: Magical | G42: Standard | H42: 1 | I42: Foe | J42: Range 3 | K42: If the user heals 4+ HP from this move, it inflicts -3 Evasions/1.
A43: Coup de Grâce | B43: 4 | C43: E2T | D43: 3 | E43: 2d8+5 | F43: Magical | G43: Standard | H43: 1 | I43: Foe | J43: Homing 5 | K43: If this kills a target, the user heals 10 HP and gains +5 damage to their next attack.
A44: Wither Soul | B44: 5 | C44: EoT | D44: 3 | E44: 2d8+6 | F44: Magical | G44: Standard | H44: AoE | I44: Foes | J44: Burst 1 | K44: For each target hit that is currently under a debuff, this deals an additional 3 damage and the user heals 3 HP.
A45: Hades's Toll | B45: 6 | C45: Twice/EoT | D45: 4 | E45: 3d8+3 | F45: Magical | G45: Standard | H45: 1 | I45: Foe | J45: Homing 4 | K45: For two rounds, the user's Reaper's Touch heal is doubled for attacks against the target.
A46: Phantasmal Shield | B46: 7 | C46: Once | D46: - | E46: - | F46: - | G46: Swift | H46: 1 | I46: Self | J46: - | K46: For one round, the user heals 10% of the damage taken from all attacks.
A47: Memento Mori | B47: 8 | C47: Twice/EoT | D47: 4 | E47: 4d8+7 | F47: Magical | G47: Standard | H47: 1 | I47: Foe | J47: Range 4 | K47: Before accuracy, choose X between 1 and 3. This move has Delay-X, and Reaper's Touch heals the user X/8 of the damage dealt by this attack instead of 1/8.
A48: Spirit Break | B48: 9 | C48: Twice | D48: 4 | E48: 5d6+5 | F48: Magical | G48: Standard | H48: 1 | I48: Foe | J48: Range 3 | K48: The target is inflicted with -3 DR/1, and the user gains +3 DMG/1.
A49: Phantom Blade | B49: 10 | C49: Once | D49: 5 | E49: 6d6+6 | F49: Magical | G49: Standard | H49: 1 | I49: Foe | J49: Melee | K49: This move gains +damage equal to amount of HP the user has healed from Scythe abilities since the start of their last turn.

Sheet Dueler
A1: Name | B1: Lvl | C1: Frequency | D1: MR | E1: Damage | H1: Target | K1: Effect
E2: Roll | F2: Type | G2: Action Type | H2: Amount | I2: Group | J2: Range and Modifiers
A3: Basic Abilities
A4: =Classes!A4 -> Basic Attack (P) / Basic Attack (M) | B4: =Classes!B4 -> B | C4: =Classes!C4 -> Every Turn | D4: =Classes!D4 -> 2 | E4: =Classes!E4 -> 1d10+2 | F4: =Classes!F4 -> Physical or Magical | G4: =Classes!G4 -> Standard | H4: =Classes!H4 -> 1 | ... K4: =Classes!K4 -> A basic attack. The user may choose either BATK (P) or BATK (M). Add the corresponding stat depending on their choice (BATK (P) = Physical Attack. BATK (M) = Magical Attack).This attack can be used even when sealed and its use cannot be prevented by any means, outside of Stun.
A5: =Classes!A5 -> Dash | B5: =Classes!B5 -> B | C5: =Classes!C5 -> Every Turn | D5: =Classes!D5 -> - | E5: =Classes!E5 -> - | F5: =Classes!F5 -> - | G5: =Classes!G5 -> Full | H5: =Classes!H5 -> - | ... K5: =Classes!K5 -> The user moves up to 1.5x their MP (rounded down) instead of 1x. (Dash is a Full action, which takes up both the Movement and Standard actions.)
A6: =Classes!A6 -> Backstep | B6: =Classes!B6 -> B | C6: =Classes!C6 -> Every Turn | D6: =Classes!D6 -> - | E6: =Classes!E6 -> - | F6: =Classes!F6 -> - | G6: =Classes!G6 -> Movement | H6: =Classes!H6 -> - | ... K6: =Classes!K6 -> This can only be used while a foe is in the user's Melee. The user moves one tile in a cardinal direction without triggering Attack of Opportunity.
A7: =Classes!A7 -> Attack of Opportunity | B7: =Classes!B7 -> B | C7: =Classes!C7 -> Every Turn | D7: =Classes!D7 -> 2 | E7: =Classes!E7 -> 1d10+2 | F7: =Classes!F7 -> Physical or Magical | G7: =Classes!G7 -> Reaction | H7: =Classes!H7 -> 1 | ... K7: =Classes!K7 -> This may be used when a foe in the user's Melee either: leaves that Melee with their Movement action, or uses a ranged attack that doesn't target the user (after damage is rolled). This Reaction still adds ATK or MAG.
A8: Dueler Abilities
A10: Gladius
A11: 65 HP | 14 ATK | 0 MAG | 15 PD | 10 MD | 2 MP | G11: "A three-in-one versatile weapon."
A12: Weapon Swap | B12: 1 | C12: EoT | D12: - | E12: - | F12: - | G12: Free | H12: - | I12: Self | J12: - | K12: The user switches to Gladius, Scutum or Pilum. (The user starts the game in Gladius.)
A13: Exercitus | B13: 1 | C13: Every Turn | D13: 3 | E13: 2d8+6 | F13: Physical | G13: Standard | H13: 1 | I13: Foe | J13: Range 2 | K13: If the user is Gladius, this deals +3 damage. If Scutum, the user gains +3 DR/1. If Pilum, this move has -1 MR.
A14: Opening Strike | B14: 2 | C14: EoT | D14: 4 | E14: 2d8+10 | F14: Physical | G14: Standard | H14: 1 | I14: Foe | J14: Range 4 | K14: If the user is in Scutum, the target is inflicted with 5 Bleed/1. If the user is in Pilum, the target is inflicted with Confusion/1. The user automatically switches to Gladius.
A15: Forward Jab | B15: 3 | C15: EoT | D15: 3 | E15: 2d10+5 | F15: Physical | G15: Standard | H15: 1 | I15: Foe | J15: Melee | K15: This move has a different effect depending on the user's weapon. Gladius: +5 damage. Scutum: The target's next standard/full attack loses 5 damage. Pilum: This move may be made AoE/Foes/Pierce 4 instead.
A16: Shield Wall | B16: 4 | C16: Thrice/EoT | D16: 4 | E16: 2d10+7 | F16: Physical | G16: Standard | H16: AoE | I16: Foes | J16: Cone 1 | K16: The user must be in Gladius or Pilum to use this move, and may be used as a non-damaging standard on the user. The user automatically switches to Scutum and only takes 75% damage from foes' attacks for one round.
A17: Invigorate | B17: 5 | C17: Thrice/EoT | D17: - | E17: - | F17: - | G17: Swift | H17: AoE | I17: Self and Allies | J17: Burst 2 | K17: Targets gain a buff, depending on the user's Weapon. Gladius: +DMG on their next attacks, equal to 10% of the damage dealt by the user's previous attack. Scutum: +DR for one round, equal to 15% of the collective damage dealt by all target's previous attacks. Pilum: +ACC on their next attacks, equal to 8% of the damage deal by the user's previous attack.
A18: Disengage | B18: 6 | C18: Twice/EoT | D18: 4 | E18: 2d10+5 | F18: Physical | G18: Standard | H18: 1 | I18: Foe | J18: Melee | K18: The user is pushed back one space. If the user is in Gladius, foes who enter the user's melee before the user's next turn take 5 damage. If the user is in Scutum, the user does not take damage from AoE attacks for one round. The user automatically switches to Pilum.
A19: Weapon Crash | B19: 7 | C19: Twice/EoT | D19: 4 | E19: 3d10+5 | F19: Physical | G19: Standard | H19: Varies | I19: Foe(s) | J19: Varies | K19: This move has a different range and effect depending on the user's Weapon. If Dual Wield is active, the user chooses one range and effect each from either of the two Weapons. Gladius: One/Foe/Melee, and inflicts 10 Bleed/1. Scutum: AoE/Foes/Cone 2, and Push 3. Pilum: AoE/Foes/Pierce 3, and inflicts 6 Cripple/1.
A20: Dual Wield | B20: 8 | C20: Twice/EoT | D20: - | E20: - | F20: - | G20: Swift | H20: - | I20: Self | J20: - | K20: The user benefits from the effects of any two weapons (Gladius/Scutum/Pilum) this turn. At the end of their turn, if they did not switch weapons again, they revert to their original weapon.
A21: Imperial Might | B21: 9 | C21: Twice/EoT | D21: 4 | E21: 2d10+12 | F21: Physical | G21: Standard | H21: 1 | I21: Foe | J21: Melee | K21: If the user is in Gladius, the user gains 15% of this attack's damage as +damage for one round. If the user is in Scutum, the user gains immunity to statuses and debuffs for one round and is cured from them (before accuracy). If the user is in Pilum, the target's evasions are reduced to 0 for one round.
A22: Iberian Steel | B22: 10 | C22: Once | D22: 5 | E22: 3d10+10 | F22: Physical | G22: Standard | H22: 1 | I22: Foe | J22: Melee | K22: This attack gains +2X dice where X is the amount of times the user has used a Gladius ability (other than Weapon Swap and Dual Wield) with their least used weapon.
A23: Katana
A24: 65 HP | 10 ATK | 0 MAG | 12 PD | 12 MD | 3 MP | G24: "The lower your HP, the more powerful you become."
A25: Fallen Blade | B25: 1 | C25: Passive | D25: - | E25: - | F25: - | G25: Passive | H25: - | I25: - | J25: - | K25: When the user is below 75%, 50%, or 25% of their Max HP (rounded down), they gain 1 Enrage counter. Each counter can only be acquired once, even if the user heals above a threshold. The user's attacks have +1 dice per counter.
A26: Cursed Slice | B26: 1 | C26: Every Turn | D26: 2 | E26: 3d7+3 | F26: Physical | G26: Standard | H26: 1 | I26: Foe | J26: Melee | K26: If the user has 1 Enrage counter, this move may be used when Sealed. If the user has 2+ counters, this may be used regardless of any statuses or move effects (except Stun).
A27: Lunge | B27: 2 | C27: Every Turn | D27: 3 | E27: 2d6+4 | F27: Physical | G27: Standard | H27: 1 | I27: Foe | J27: Range 4 | K27: For every enrage counter the user has, this move gains +1 ACC. The user moves as close to the target as possible.
A28: Provoke | B28: 3 | C28: EoT | D28: 3 | E28: 2d8+3 | F28: Physical | G28: Standard | H28: 1 | I28: Foe | J28: Melee | K28: If the target doesn't perform an attack which would deal over 35 damage before outside damage factors on their next turn, then the user gains one Enrage counter.
A29: Revenge | B29: 4 | C29: Twice | D29: - | E29: - | F29: - | G29: Trigger | H29: - | I29: Self | J29: - | K29: Once per turn, the user's next Standard/Full attack gains +damage equal to X% of the damage they took from one of the targets since the start of the user's last turn. X = 10 times the amount of Enrage counters the user has.
A30: Sharpen | B30: 5 | C30: Once | D30: 3 | E30: 2d6+4 | F30: Physical | G30: Standard | H30: 1 | I30: Foe | J30: Melee | K30: If this attack kills the target, the user gains one Enrage counter and another use on this move.
A31: Costly Swing | B31: 6 | C31: Twice | D31: 4 | E31: 6d4+8 | F31: Physical | G31: Standard | H31: 1 | I31: Foe | J31: Melee | K31: Until the start of their next turn, the user has -10 DR. This debuff is decreased by 2 for each Enrage counter the user has (minimum 0).
A32: Bushido | B32: 7 | C32: Twice/EoT | D32: 4 | E32: 2d8+4 | F32: Physical | G32: Standard | H32: 1 | I32: Foe | J32: Melee | K32: If the user has at least one Enrage counter, this move can be used while sealed and they are cleansed from any statuses and debuffs (before accuracy). If they have two counters, the user can choose for this move to be AoE/Foes/Burst 1. If they have 3, this move can be Burst 2.
A33: Rising Sun | B33: 8 | C33: Once | D33: 4 | E33: 3d8+1 | F33: Physical | G33: Standard | H33: AoE | I33: Foes | J33: Cone 1 | K33: The user gains a Shield equal to X% of this attack's damage, where X is 10 times the amount of Enrage counters the user has.
A34: Delirium Slash | B34: 9 | C34: Twice/EoT | D34: 4 | E34: 2d8+2 | F34: Physical | G34: Standard | H34: 1 | I34: Foe | J34: Melee | K34: This attack has doubled bonus dice from Fallen Blade, but the user takes recoil equal to the extra bonus dice rolled. If the recoil would kill the user, they are left at 1 HP instead.
A35: Giant Slayer | B35: 10 | C35: Once | D35: 5 | E35: 2d10+3 | F35: Physical | G35: Standard | H35: 1 | I35: Foe | J35: Melee | K35: If the target has at least 40 more HP than the user, Fallen Blade dice on this move are converted into bonus damage equal to ten times the number of Enrage counters the user has.
A36: Rapier
A37: 60 HP | 10 ATK | 9 MAG | 13 PD | 11 MD | 2 MP | G37: "A weapon centred on reacting to opponent's attacks, keeping both of you on your toes."
A38: Point-in-Line | B38: 1 | C38: Every Turn | D38: 2 | E38: 2d8+5 | F38: Physical | G38: Standard | H38: AoE | I38: Foes | J38: Pierce 3 | K38: This attack can be used even when sealed.
A39: Counter | B39: 2 | C39: EoT | D39: 2 | E39: 1d6+5 | F39: Physical | G39: Reaction | H39: 1 | I39: Foe | J39: Melee | K39: This may be used on a foe hitting the user in Melee range, after accuracy is rolled. The foe's attack loses 3 damage (5 damage if the user used Feint on their last turn). This move is immune to non-Rapier outside damage factors. Do not add ATK/MAG.
A40: Thrust | B40: 3 | C40: Every Turn | D40: 3 | E40: 2d8+7 | F40: Physical | G40: Standard | H40: 1 | I40: Foe | J40: Range 5 | K40: The user moves to a cardinally adjacent space to the target. If the user cannot enter the target's Melee, they move as close to the target as possible. If the target was at full HP, they are inflicted with 5 Bleed/1.
A41: Deflect | B41: 4 | C41: EoT | D41: 2 | E41: 2d6+5 | F41: Physical | G41: Reaction | H41: 1 | I41: Foe | J41: Global | K41: This may be used on a foe attacking the user from range, after accuracy is rolled. The user gains +2 DR (+4 DR if the user is under the effects of En Garde) for the duration of the attack this is used on. This move is immune to non-Rapier outside damage factors. Do not add ATK/MAG.
A42: Feint | B42: 5 | C42: Twice/EoT | D42: 4 | E42: 4d6+3 | F42: Physical | G42: Standard | H42: 1 | I42: Foe | J42: Melee | K42: The user's next Reaction deals an additional 1d6+5 damage.
A43: En Garde | B43: 6 | C43: Thrice/EoT | D43: - | E43: - | F43: - | G43: Swift | H43: - | I43: Self | J43: - | K43: For one round, the user gains +5 DR and their Reaction moves become MR0.
A44: Moulinet | B44: 7 | C44: EoT | D44: 3 | E44: 3d8+4 | F44: Physical | G44: Standard | H44: 1 | I44: Foe | J44: Melee | K44: The user's Reaction abilities ignore evasions for one round.
A45: Riposte | B45: 8 | C45: Every Turn | D45: 2 | E45: 2d6+3 | F45: Physical | G45: Reaction | H45: 1 | I45: Foe | J45: Melee | K45: This may be used on a foe in Melee range that missed an attack on the user. This move is immune to non-Rapier outside damage factors. Do not add ATK/MAG.
A46: Patinando | B46: 9 | C46: Twice/EoT | D46: 4 | E46: 2d8+8 | F46: Physical | G46: Standard | H46: 1 | I46: Foe | J46: Melee | K46: The user picks Fast or Slow. Fast: The user gains +2 EVA for one round. Slow: The user's next Reaction gives them +10 DR for the duration of the attack it is used on.
A47: Parry | B47: 10 | C47: Once | D47: 5 | E47: 5d6+7 | F47: Physical | G47: Reaction | H47: 1 | I47: Foe | J47: Global | K47: This may be used when a foe targeting the user would deal 40+ damage (before damage reducing effects) on an attack that hits the user. This move is immune to non-Rapier outside damage factors. Do not add ATK/MAG.

Sheet Fighter
A1: Name | B1: Lvl | C1: Frequency | D1: MR | E1: Damage | H1: Target | K1: Effect
E2: Roll | F2: Type | G2: Action Type | H2: Amount | I2: Group | J2: Range and Modifiers
A3: Basic Abilities
A4: =Classes!A4 -> Basic Attack (P) / Basic Attack (M) | B4: =Classes!B4 -> B | C4: =Classes!C4 -> Every Turn | D4: =Classes!D4 -> 2 | E4: =Classes!E4 -> 1d10+2 | F4: =Classes!F4 -> Physical or Magical | G4: =Classes!G4 -> Standard | H4: =Classes!H4 -> 1 | ... K4: =Classes!K4 -> A basic attack. The user may choose either BATK (P) or BATK (M). Add the corresponding stat depending on their choice (BATK (P) = Physical Attack. BATK (M) = Magical Attack).This attack can be used even when sealed and its use cannot be prevented by any means, outside of Stun.
A5: =Classes!A5 -> Dash | B5: =Classes!B5 -> B | C5: =Classes!C5 -> Every Turn | D5: =Classes!D5 -> - | E5: =Classes!E5 -> - | F5: =Classes!F5 -> - | G5: =Classes!G5 -> Full | H5: =Classes!H5 -> - | ... K5: =Classes!K5 -> The user moves up to 1.5x their MP (rounded down) instead of 1x. (Dash is a Full action, which takes up both the Movement and Standard actions.)
A6: =Classes!A6 -> Backstep | B6: =Classes!B6 -> B | C6: =Classes!C6 -> Every Turn | D6: =Classes!D6 -> - | E6: =Classes!E6 -> - | F6: =Classes!F6 -> - | G6: =Classes!G6 -> Movement | H6: =Classes!H6 -> - | ... K6: =Classes!K6 -> This can only be used while a foe is in the user's Melee. The user moves one tile in a cardinal direction without triggering Attack of Opportunity.
A7: =Classes!A7 -> Attack of Opportunity | B7: =Classes!B7 -> B | C7: =Classes!C7 -> Every Turn | D7: =Classes!D7 -> 2 | E7: =Classes!E7 -> 1d10+2 | F7: =Classes!F7 -> Physical or Magical | G7: =Classes!G7 -> Reaction | H7: =Classes!H7 -> 1 | ... K7: =Classes!K7 -> This may be used when a foe in the user's Melee either: leaves that Melee with their Movement action, or uses a ranged attack that doesn't target the user (after damage is rolled). This Reaction still adds ATK or MAG.
A8: Fighter Abilities
A10: Bo Staff
A11: 65 HP | 12 ATK | 5 MAG | 14 PD | 14 MD | 2 MP | G11: "A weapon with two modes, allowing you to play both offense and defense."
A12: Stance Change | B12: 1 | C12: Every Turn | D12: - | E12: - | F12: - | G12: Trigger | H12: - | I12: Self | J12: - | K12: At the start of their turn, the user may choose to become "Attack Stance", which grants +3 damage on attacks, "Defense Stance", which grants +3 DR, or "Neutral Stance". The user starts the game in "Neutral Stance", which confers no bonuses.
A13: Flowing Strike | B13: 1 | C13: Every Turn | D13: 3 | E13: 2d8+6 | F13: Physical | G13: Standard | H13: 1 | I13: Foe | J13: Melee | K13: If the user is in Attack Stance, this move is Range 4, and targets 1 Foe. If the user is in Defense Stance, this move is Burst 1 and AoE. If the user is in both Attack and Defense Stance, this attack is Range 4 and has Splash 1.
A14: Sweep | B14: 2 | C14: EoT | D14: 3 | E14: 2d10+4 | F14: Physical | G14: Standard | H14: 1 | I14: Foe | J14: Melee | K14: If the user is in Attack Stance, this attack inflicts -2 Evasions/1. If the user is in Defense Stance, the user gains +2 Evasions/1.
A15: Whirlwind | B15: 3 | C15: EoT | D15: 3 | E15: 2d8+8 | F15: Physical | G15: Standard | H15: 1 | I15: Foe | J15: Melee | K15: If the user is in Attack Stance, the foe is pushed back 3 spaces. If the user is in Defense Stance, the user is pushed back 3 spaces. If the user is in Neutral Stance, the user and target are pushed back 1 space each.
A16: Steady Strike | B16: 4 | C16: Twice/EoT | D16: 2 | E16: 1d8+9 | F16: Physical | G16: Standard | H16: 1 | I16: Foe | J16: Melee | K16: Before accuracy, if the user is in Attack Stance, both the user's and the target's debuffs are removed, if the user is in Defense Stance, both the user's and the target's buffs (including stance effects) are removed, and if the user is in Neutral Stance, the user's debuffs and the target's buffs are removed.
A17: Impeding Grip | B17: 5 | C17: Once | D17: - | E17: - | F17: - | G17: Free | H17: - | I17: Self | J17: - | K17: If the user is in Attack Stance, the user's attacks have +2 range this turn, and if the user is in Defense Stance, attacks that would target the user have -2 range for one round.
A18: Reprisal | B18: 6 | C18: Twice | D18: 3 | E18: 1d8+3 | F18: Physical | G18: Standard | H18: 1 | I18: Foe | J18: Melee | K18: If the user is in Attack Stance, their next attack against the target deals an additional 1d8+9 damage. If the user is in Defense Stance, the user gains a 1d8+9 shield.
A19: Defiance | B19: 7 | C19: Once | D19: - | E19: - | F19: - | G19: Swift | H19: - | I19: Self | J19: - | K19: If the user is in Attack Stance, their accuracy rolls gain Advantage; if the user is in Defense Stance, accuracy rolls against them gain Disadvantage. Both effects last until the start of the user's next turn. If in both stances, the user may choose which effect to gain. The user may not have both effects at once.
A20: Volatile Swing | B20: 8 | C20: Twice/EoT | D20: 4 | E20: 3d8+5 | F20: Physical | G20: Standard | H20: 1 | I20: Foe | J20: Melee | K20: If the user is in Attack Stance, this move has bomb dice. If the user is in Defense Stance, the opponent has inverse bomb dice (the attack affected rolls bomb, but the extra rolls of bomb are instead deducted from the total damage of the attack) for two rounds.
A21: Reverse Strike | B21: 9 | C21: Twice/EoT | D21: 4 | E21: 3d8+12 | F21: Physical | G21: Standard | H21: 1 | I21: Foe | J21: Melee | K21: The user is locked into their current stance, and their stance's bonus is inverted, for one round. This move cannot be used in Neutral Stance.
A22: Martial Art | B22: 10 | C22: Once | D22: 4 | E22: 3d10+5 | F22: Physical | G22: Standard | H22: 1 | I22: Foe | J22: Melee | K22: Starting after the accuracy roll, the user is in both Attack and Defense Stance for one round. When using a move with different effects depending on the user's stance, both effects apply, unless specified.
A23: Claws
A24: 65 HP | 11 ATK | 4 MAG | 9 PD | 9 MD | 3 MP | G24: "A bleed-focused weapon that has the weakest abilities, but can attack twice every turn!"
A25: Gouge | B25: 1 | C25: Every Turn | D25: 3 | E25: 2d6+1 | F25: Physical | G25: Standard | H25: 1 | I25: Foe | J25: Melee | K25: The target is inflicted with 3 Bleed/1. This bleed is unremovable.
A26: Animal Instinct | B26: 2 | C26: Passive | D26: - | E26: - | F26: - | G26: Passive | H26: - | I26: - | J26: - | K26: When the user's Claws Standard resolves, they may immediately use a second Claws Standard (this second Standard does not trigger itself). These Standards only add 50% ATK (rounded up on the first). The second Standard is immune to outside (non-multiplier) damage factors.
A27: Pounce | B27: 2 | C27: Every Turn | D27: 3 | E27: 2d4+3 | F27: Physical | G27: Standard | H27: 1 | I27: Foe | J27: Range 4 | K27: The user moves as close to the target as possible. The user may choose to lose their next standard this turn to add their full ATK instead and increase range to 7.
A28: Crippling Slash | B28: 3 | C28: EoT | D28: 2 | E28: 3d4+0 | F28: Physical | G28: Standard | H28: 1 | I28: Foe | J28: Melee | K28: The user's attacks against the target have +2 ACC for one round.
A29: Fury Swipes | B29: 4 | C29: EoT | D29: 3 | E29: 1d4+2 | F29: Physical | G29: Standard | H29: 1 | I29: Foe | J29: Melee (Triple Hit) | K29: This move ignores outside negative damage factors.
A30: Close Combat | B30: 5 | C30: Twice/EoT | D30: 3 | E30: 3d4+2 | F30: Physical | G30: Standard | H30: 1 | I30: Foe | J30: Melee | K30: If used on the same turn as Fury Swipes, any bleed the target has is extended for another turn.
A31: Gyre | B31: 6 | C31: EoT | D31: 2 | E31: 2d4+5 | F31: Physical | G31: Standard | H31: AoE | I31: Foes | J31: Cone 1 | K31: The user may choose to lose their second standard, but add their full ATK stat to this attack instead. If they do, this move's range is Cone 2 instead.
A32: Frenzy | B32: 7 | C32: Twice/EoT | D32: 4 | E32: 4d6+2 | F32: Physical | G32: Standard | H32: 1 | I32: Foe | J32: Melee | K32: If the target is bleeding, this move has bomb dice.
A33: Vengeance | B33: 8 | C33: Twice | D33: 3 | E33: 2d4+0 | F33: Physical | G33: Standard | H33: 1 | I33: Foe | J33: Melee | K33: If the user's previous standard missed, inflict (or, if already bleeding, increase to) unremovable bleed on the target to 10/1 and its effect to -10 damage.
A34: Heartseek | B34: 9 | C34: Once | D34: 4 | E34: Xd8+0 | F34: Physical | G34: Standard | H34: 1 | I34: Foe | J34: Melee | K34: This move has X dice, where X is the number of times the target has been hit by the user. (Maximum 10d8; multi-hit attacks only add 1 die.)
A35: Shred | B35: 10 | C35: Once | D35: 5 | E35: 4d4+5 | F35: Physical | G35: Standard | H35: 1 | I35: Foe | J35: Melee | K35: If the target is bleeding, this move automatically crits if it hits.
A36: Tonfa
A37: 70 HP | 12 ATK | 9 MAG | 15 PD | 15 MD | 2 MP | G37: "A defensive control weapon that manipulates foes into your melee, then punishes them for it."
A38: Disarm | B38: 1 | C38: Every Turn | D38: 3 | E38: 2d8+5 | F38: Physical | G38: Standard | H38: 2 | I38: Foes | J38: Melee | K38: The targets' next Standard/Full attacks have -1 dice, and -1 ACC if this accuracy debuff was not applied on the user's previous Disarm.
A39: Spurn Shot | B39: 2 | C39: EoT | D39: 3 | E39: 2d8+4 | F39: Physical | G39: Standard | H39: 1 | I39: Foe | J39: Range 4 | K39: During their next turn, if the target is able to, but does not attack the user from Melee, the user may AoO them at the end of the turn.
A40: Figure 8 | B40: 3 | C40: Every Turn | D40: 2 | E40: 2d10+5 | F40: Physical | G40: Standard | H40: 1 | I40: Foe | J40: Melee | K40: This may be used whenever the user may use AoO. If used as a Reaction, this move cannot be ignored by abilities (except Backstep).
A41: Evasive Stance | B41: 4 | C41: Once | D41: - | E41: - | F41: - | G41: Free | H41: 1 | I41: Self | J41: - | K41: The user gains +3 EVA for one round. Next turn, the user has -10 DMG on attacks.
A42: Hold Over | B42: 4 | C42: Twice/EoT | D42: - | E42: - | F42: - | G42: Free | H42: - | I42: Self | J42: - | K42: Declare a range type (except Melee). For one round, foes outside of the user's Melee cannot target the user with attacks of that range type. (Range modifiers do not affect Hold Over.)
A43: Yin Yang | B43: 5 | C43: EoT | D43: 4 | E43: 3d8+8 | F43: Varies | G43: Standard | H43: 1 | I43: Foe | J43: Varies | K43: Choose Yin or Yang. Yin: Physical/Melee. If the target does not damage the user with attacks on their next turn, they take 1d8+5 damage. Yang: Magical/Homing 4. For one round, foes take 1d8+5 damage each time they damage the user with attacks.
A44: Standoff | B44: 6 | C44: Twice/EoT | D44: 4 | E44: 2d10+8 | F44: Physical | G44: Standard | H44: 1 | I44: Foe | J44: Melee | K44: If the target ends their next turn in the user's Melee, they take 1d10+ATK/2 damage at the start of the user's next turn.
A45: Tempest Sweep | B45: 7 | C45: Every Turn | D45: 3 | E45: 3d8+3 | F45: Magical | G45: Standard | H45: 1 | I45: Foe | J45: Range 4 | K45: Replace all instances of "next round/turn" or "one round" with "next two rounds/turns" or "two rounds" (respectively) in the user's weapon abilities.
A46: Block | B46: 8 | C46: Once | D46: - | E46: - | F46: - | G46: Reaction | H46: - | I46: Self | J46: - | K46: This may be used when the user is attacked, after damage is rolled. 1/3 of the attack's damage is removed.
A47: Dazing Hook | B47: 9 | C47: E2T | D47: 5 | E47: 2d8+3 | F47: Physical | G47: Full | H47: 1 | I47: Foe | J47: Line 4 (Pull 3) | K47: This move's range cannot be reduced. If the the target attacked the user outside of Melee last round, they are inflicted with Seal/1.
A48: Gale Force | B48: 10 | C48: Once | D48: 4 | E48: 3d10+8 | F48: Magical | G48: Standard or Swift | H48: AoE | I48: All | J48: Burst 2 | K48: This move does not check accuracy or deal damage to allies or the user. The user may teleport any targets to any unoccupied space in range. As a non-damaging Swift, this move is AoE/Self-and-Allies/Star 2.

Sheet Heavy
A1: Name | B1: Lvl | C1: Frequency | D1: MR | E1: Damage | H1: Target | K1: Effect
E2: Roll | F2: Type | G2: Action Type | H2: Amount | I2: Group | J2: Range and Modifiers
A3: Basic Abilities
A4: =Classes!A4 -> Basic Attack (P) / Basic Attack (M) | B4: =Classes!B4 -> B | C4: =Classes!C4 -> Every Turn | D4: =Classes!D4 -> 2 | E4: =Classes!E4 -> 1d10+2 | F4: =Classes!F4 -> Physical or Magical | G4: =Classes!G4 -> Standard | H4: =Classes!H4 -> 1 | ... K4: =Classes!K4 -> A basic attack. The user may choose either BATK (P) or BATK (M). Add the corresponding stat depending on their choice (BATK (P) = Physical Attack. BATK (M) = Magical Attack).This attack can be used even when sealed and its use cannot be prevented by any means, outside of Stun.
A5: =Classes!A5 -> Dash | B5: =Classes!B5 -> B | C5: =Classes!C5 -> Every Turn | D5: =Classes!D5 -> - | E5: =Classes!E5 -> - | F5: =Classes!F5 -> - | G5: =Classes!G5 -> Full | H5: =Classes!H5 -> - | ... K5: =Classes!K5 -> The user moves up to 1.5x their MP (rounded down) instead of 1x. (Dash is a Full action, which takes up both the Movement and Standard actions.)
A6: =Classes!A6 -> Backstep | B6: =Classes!B6 -> B | C6: =Classes!C6 -> Every Turn | D6: =Classes!D6 -> - | E6: =Classes!E6 -> - | F6: =Classes!F6 -> - | G6: =Classes!G6 -> Movement | H6: =Classes!H6 -> - | ... K6: =Classes!K6 -> This can only be used while a foe is in the user's Melee. The user moves one tile in a cardinal direction without triggering Attack of Opportunity.
A7: =Classes!A7 -> Attack of Opportunity | B7: =Classes!B7 -> B | C7: =Classes!C7 -> Every Turn | D7: =Classes!D7 -> 2 | E7: =Classes!E7 -> 1d10+2 | F7: =Classes!F7 -> Physical or Magical | G7: =Classes!G7 -> Reaction | H7: =Classes!H7 -> 1 | ... K7: =Classes!K7 -> This may be used when a foe in the user's Melee either: leaves that Melee with their Movement action, or uses a ranged attack that doesn't target the user (after damage is rolled). This Reaction still adds ATK or MAG.
A8: Heavy Abilities
A10: Axe
A11: 60 HP | 19 ATK | 7 MAG | 11 PD | 11 MD | 1 MP | G11: "A simple weapon, with the highest ATK, but low accuracy and range."
A12: Bloodlust | B12: 1 | C12: Passive | D12: - | E12: - | F12: - | G12: Passive | H12: - | I12: - | J12: - | K12: Whenever the user deals 15+ damage with an attack, or takes 15+ damage from a foe's attack, they gain 1 Rage stack.
A13: Feral Chop | B13: 1 | C13: Every Turn | D13: 3 | E13: 2d10+4 | F13: Physical | G13: Standard | H13: 1 | I13: Foe | J13: Melee | K13: This inflicts +1 damage for each Rage stack the user has.
A14: Chain Axe | B14: 2 | C14: Every Turn | D14: 3 | E14: 1d10+2 | F14: Physical | G14: Standard | H14: 1 | I14: Foe | J14: Line 4 (Pull 3) | K14: The user gains an additional stack of Rage from this attack.
A15: Power Swing | B15: 3 | C15: EoT | D15: 6 | E15: 3d10+6 | F15: Physical | G15: Standard | H15: 1 | I15: Foe | J15: Melee | K15: The user may spend any number of Rage. This move's MR is lowered by 1 for every stack of Rage spent.
A16: Brutal Strike | B16: 4 | C16: EoT | D16: 4 | E16: 3d10+2 | F16: Physical | G16: Standard | H16: 1 | I16: Foe | J16: Melee | K16: The user may consume stacks of Rage. For every stack consumed, this attack gains +2 critical hit range.
A17: Sever | B17: 5 | C17: Twice/EoT | D17: 4 | E17: 1d10+2 | F17: Physical | G17: Standard | H17: 1 | I17: Foe | J17: Melee | K17: The user may spend stacks of Rage. For every stack consumed up to 4, this attack gains +1 hit. For every two stacks consumed beyond that, this attack gains +1 hit.
A18: Vindictive | B18: 6 | C18: Passive | D18: - | E18: - | F18: - | G18: Passive | H18: - | I18: - | J18: - | K18: The user gains two stacks of Rage every time they kill a foe.
A19: Wide Slash | B19: 7 | C19: Twice/EoT | D19: 4 | E19: 2d10+7 | F19: Physical | G19: Standard | H19: AoE | I19: Foes | J19: Cone 1 | K19: The user may spend two Rage stacks to make this attack Cone 2.
A20: Gash | B20: 8 | C20: Once | D20: 5 | E20: 2d10+8 | F20: Physical | G20: Standard | H20: 1 | I20: Foe | J20: Melee | K20: The target is inflicted with Bleed 5/1. The user may consume up to two stacks of Rage when they use this attack, before accuracy. For every stack consumed, the bleed lasts an additional round.
A21: Franciscate | B21: 9 | C21: Once | D21: 4 | E21: 3d10+3 | F21: Physical | G21: Standard | H21: 1 | I21: Foe | J21: Line 6 | K21: The user is inflicted with Seal/1. They may spend 1 stack before accuracy to negate this status.
A22: Amped Strike | B22: 10 | C22: Once | D22: 5 | E22: 3d10+8 | F22: Physical | G22: Standard | H22: 1 | I22: Foe | J22: Melee (Splash 1) | K22: This attack deals an additional X damage, where X = the number of Rage stacks the user has * 4. On a hit, the user then loses all of their Rage stacks.
A23: Hammer
A24: 70 HP | 15 ATK | 7 MAG | 19 PD | 8 MD | 1 MP | G24: "A weapon with many attacks that allow it to hit multiple foes at once."
A25: Cyclone Sweep | B25: 1 | C25: Every Turn | D25: 3 | E25: Xd10+7 | F25: Physical | G25: Standard | H25: AoE | I25: Foes | J25: Cone 1 | K25: X = 1 + the number of targets hit.
A26: Storm Strike | B26: 2 | C26: Every Turn | D26: 4 | E26: 2d10+6 | F26: Physical | G26: Standard | H26: 1 | I26: Foe | J26: Range 5 (Splash 1) | K26: The user moves as close to the original target as possible, and the original target is Slowed/1.
A27: Hammerang | B27: 3 | C27: Twice | D27: 4 | E27: 1d10+5 | F27: Physical | G27: Standard | H27: AoE | I27: Foes | J27: Pierce 3 (Double Hit) | K27: -
A28: Masonry | B28: 4 | C28: Twice/EoT | D28: - | E28: - | F28: - | G28: Free | H28: - | I28: - | J28: Melee | K28: The user creates a Stone tile on any unoccupied space in range. Stone tiles have 1 HP and 2/2 EVA, and may be attacked.
A29: Crush | B29: 5 | C29: EoT | D29: 4 | E29: 2d10+6 | F29: Physical | G29: Standard | H29: 1 | I29: Foe | J29: Melee (Push 2) | K29: This move has Push 2. If the target cannot be pushed the full distance, they take an additional 1d10+4 damage. This damage is also dealt to the obstruction if it is an entity.
A30: Earth Render | B30: 6 | C30: Twice/EoT | D30: 5 | E30: 3d10+5 | F30: Physical | G30: Standard | H30: 1 | I30: Foe | J30: Melee (Splash 1) | K30: Within Splash 2 of the original target, the user replaces up to 3 unoccupied tiles with Broken tiles. These tiles revert after 3 rounds, until the user decides to remove them, or until the user dies.
A31: Lagging Spin | B31: 7 | C31: Once | D31: 5 | E31: 2d10+5 | F31: Physical | G31: Standard | H31: AoE | I31: Foes | J31: Burst 1 | K31: The user may select one target within range. This move gains extra dice equal to the target's MP minus the user's MP, but no less than 0. Max +3 dice.
A32: Fissure | B32: 8 | C32: Twice/E2T | D32: 4 | E32: 3d10+5 | F32: Physical | G32: Standard | H32: 1 | I32: Foe | J32: Melee | K32: The target is Slowed/1. Foes in Pierce 3 behind the target take half the damage rolled and are Slowed/1.
A33: Shockwave Slam | B33: 9 | C33: Once | D33: 4 | E33: 2d10+8 | F33: Physical | G33: Standard | H33: 1 | I33: Foe | J33: Melee (Splash 2) | K33: The user pushes all foes within Burst 2 of the original target one space away from the original target.
A34: Gravity Slam | B34: 10 | C34: Once | D34: 5 | E34: 4d10+8 | F34: Physical | G34: Standard | H34: 1 | I34: Foe | J34: Melee (Splash 1) | K34: Before accuracy, the user may choose an entity within Splash 2 and pull into any tile in Splash 1. This pull ignores the user.
A35: Tomahawk
A36: 65 HP | 13 ATK | 8 MAG | 17 PD | 10 MD | 2 MP | G36: "A weapon reliant on positioning, benefitting from pushing people away."
A37: Heavy Weapon | B37: 1 | C37: Passive | D37: - | E37: - | F37: - | G37: Passive | H37: - | I37: - | J37: - | K37: The user has +1 accuracy on all ranged attacks, but cannot use Backstep.
A38: Tomahawk Toss | B38: 1 | C38: Every Turn | D38: 3 | E38: 2d10+4 | F38: Physical | G38: Standard | H38: 1 | I38: Foe | J38: Range 4 | K38: If used from full range, this attack has +4 damage.
A39: Kip Up | B39: 1 | C39: Every Turn | D39: - | E39: - | F39: - | G39: Swift | H39: 1 | I39: Any | J39: Range 2 | K39: This can only be used if the user targeted a foe/ally in Melee range on their previous turn. The target is pushed up to 3 tiles (if targeting the user, they choose the direction). Then, the user's Movement action is disabled for the rest of the turn.
A40: Piercing Blow | B40: 2 | C40: EoT | D40: 3 | E40: 1d10+7 | F40: Physical | G40: Standard | H40: 1 | I40: Foe | J40: Range 2 | K40: The target is inflicted with 2 Bleed/1. If used in melee, the bleed is increased to 7/1.
A41: Focused Fling | B41: 3 | C41: EoT | D41: X | E41: 2d10+6 | F41: Physical | G41: Standard | H41: 1 | I41: Foe | J41: Range 5 | K41: This move has a MR of X, where X = 5 - The range this move is used at.
A42: Kinetic Throw | B42: 4 | C42: Twice/EoT | D42: 4 | E42: Xd10+3 | F42: Physical | G42: Standard | H42: 1 | I42: Foe | J42: Range 5 | K42: This attack has X - 1 dice, where X is the range this move is used at.
A43: Repulse Slice | B43: 5 | C43: Twice/EoT | D43: 4 | E43: 3d10+5 | F43: Physical | G43: Standard | H43: 1 | I43: Foe | J43: Melee (Push 1) | K43: Foes cannot enter the user's melee for one round.
A44: Continental Crash | B44: 6 | C44: Twice/EoT | D44: 4 | E44: 3d10+4 | F44: Physical | G44: Standard | H44: AoE | I44: Foes | J44: Burst 1 | K44: The user may replace two unoccupied tiles in their Melee with Broken tiles. Foes who end their turn with at least one of these tiles in their Melee take 10 damage. These tiles revert after 3 rounds, or when the user dies.
A45: Two-Handed | B45: 7 | C45: Twice | D45: 4 | E45: 3d10+8 | F45: Physical | G45: Standard | H45: 1 | I45: Foe | J45: Range 4 (Push 1) | K45: This attack has Splash 1 if used outside of Range 3.
A46: Line-Out | B46: 8 | C46: E2T | D46: 4 | E46: 2d10+5 | F46: Physical | G46: Standard | H46: AoE | I46: Foes | J46: Pierce 5 | K46: Targets take +4 damage for every target before them in the Pierce.
A47: Razor Rust | B47: 9 | C47: Once | D47: 5 | E47: 3d10+8 | F47: Physical | G47: Standard | H47: 1 | I47: Foe | J47: Range 4 | K47: The target is inflicted with 6 Cripple/1.
A48: Supreme Strike | B48: 10 | C48: Once | D48: 5 | E48: 5d10+3 | F48: Physical | G48: Standard | H48: 1 | I48: Foe | J48: Range 4 | K48: This attack can only be used from maximum range, and gains +dice equal to the number of times the user has pushed any foe with weapon abilities.

Sheet Regal
A1: Name | B1: Lvl | C1: Frequency | D1: MR | E1: Damage | H1: Target | K1: Effect
E2: Roll | F2: Type | G2: Action Type | H2: Amount | I2: Group | J2: Range and Modifiers
A3: Basic Abilities
A4: =Classes!A4 -> Basic Attack (P) / Basic Attack (M) | B4: =Classes!B4 -> B | C4: =Classes!C4 -> Every Turn | D4: =Classes!D4 -> 2 | E4: =Classes!E4 -> 1d10+2 | F4: =Classes!F4 -> Physical or Magical | G4: =Classes!G4 -> Standard | H4: =Classes!H4 -> 1 | ... K4: =Classes!K4 -> A basic attack. The user may choose either BATK (P) or BATK (M). Add the corresponding stat depending on their choice (BATK (P) = Physical Attack. BATK (M) = Magical Attack).This attack can be used even when sealed and its use cannot be prevented by any means, outside of Stun.
A5: =Classes!A5 -> Dash | B5: =Classes!B5 -> B | C5: =Classes!C5 -> Every Turn | D5: =Classes!D5 -> - | E5: =Classes!E5 -> - | F5: =Classes!F5 -> - | G5: =Classes!G5 -> Full | H5: =Classes!H5 -> - | ... K5: =Classes!K5 -> The user moves up to 1.5x their MP (rounded down) instead of 1x. (Dash is a Full action, which takes up both the Movement and Standard actions.)
A6: =Classes!A6 -> Backstep | B6: =Classes!B6 -> B | C6: =Classes!C6 -> Every Turn | D6: =Classes!D6 -> - | E6: =Classes!E6 -> - | F6: =Classes!F6 -> - | G6: =Classes!G6 -> Movement | H6: =Classes!H6 -> - | ... K6: =Classes!K6 -> This can only be used while a foe is in the user's Melee. The user moves one tile in a cardinal direction without triggering Attack of Opportunity.
A7: =Classes!A7 -> Attack of Opportunity | B7: =Classes!B7 -> B | C7: =Classes!C7 -> Every Turn | D7: =Classes!D7 -> 2 | E7: =Classes!E7 -> 1d10+2 | F7: =Classes!F7 -> Physical or Magical | G7: =Classes!G7 -> Reaction | H7: =Classes!H7 -> 1 | ... K7: =Classes!K7 -> This may be used when a foe in the user's Melee either: leaves that Melee with their Movement action, or uses a ranged attack that doesn't target the user (after damage is rolled). This Reaction still adds ATK or MAG.
A8: Regal Abilities
A10: Crown
A11: 70 HP | 12 ATK | 4 MAG | 14 PD | 14 MD | 2 MP | G11: "A pure defense weapon focusing on shields."
A12: Brave Leader | B12: 1 | C12: Every Turn | D12: - | E12: 1d6+4 | F12: - | G12: Trigger | H12: - | I12: Self | J12: - | K12: The user sacrifices 5 HP to gain the roll as a Shield that lasts until the start of their next turn. This cannot be used if the user already has a Shield from Brave Leader. Effects that depend on the user having a Shield from Brave Leader last only until the Shield expires or is broken.
A13: Engage | B13: 1 | C13: Every Turn | D13: 2 | E13: 2d10+4 | F13: Physical | G13: Standard | H13: 1 | I13: Foe | J13: Melee | K13: If the user has a Shield from Brave Leader, they heal for half of the Shield's value.
A14: Ambush | B14: 2 | C14: EoT | D14: 3 | E14: 1d12+8 | F14: Physical | G14: Standard | H14: 1 | I14: Foe | J14: Melee | K14: If the user has a Shield from Brave Leader, attacks targeting the user lose 1 dice. Otherwise, this attack has +1 dice.
A15: Diversion | B15: 3 | C15: E2T | D15: 3 | E15: 3d6+7 | F15: Physical | G15: Standard | H15: 1 | I15: Foe | J15: Range 5 | K15: If the user has a Shield from Brave Leader, they have +2 EVA.
A16: Bastion | B16: 4 | C16: EoT | D16: - | E16: - | F16: - | G16: Free | H16: - | I16: Self | J16: - | K16: This turn, Brave Leader generates +50% more Shield than usual.
A17: War of Attrition | B17: 5 | C17: E2T | D17: 3 | E17: 2d8+6 | F17: Physical | G17: Standard | H17: AoE | I17: Foes | J17: Cone 2 | K17: If the user has a Shield from Brave Leader, foes who hit the user are immediately (before damage is dealt) inflicted 5 Bleed/1.
A18: Blockade | B18: 6 | C18: Twice/EoT | D18: 4 | E18: 1d4+3 | F18: Physical | G18: Standard | H18: 1 | I18: Foe | J18: Global | K18: If the user has a Shield from Brave Leader, the user has +1 MP and their Shield expires one turn later than it normally would. This move is immune to outside damage factors. Do not add ATK.
A19: Divide et Impera | B19: 7 | C19: Twice/EoT | D19: - | E19: - | F19: - | G19: Swift | H19: - | I19: Self | J19: - | K19: If the user has a Shield from Brave Leader, they lose the Shield to gain an equivalent amount of DR for the rest of the Shield's duration. For the purposes of the user's move effects, having this DR is considered as having a Shield from Brave Leader.
A20: War Cry | B20: 8 | C20: Twice/EoT | D20: 4 | E20: 2d10+5 | F20: Physical | G20: Standard | H20: AoE | I20: Foes | J20: Burst 2 | K20: If the user has a Shield from Brave Leader, allies in range gain a Shield of equal value that lasts for one round. This may be used as a non-damaging Standard.
A21: Shock and Awe | B21: 9 | C21: Once | D21: 4 | E21: 3d8+3 | F21: Physical | G21: Standard | H21: 1 | I21: Foe | J21: Line 4 | K21: If the user has a Shield from Brave Leader, attacks targeting them are immune to positive outside accuracy and damage factors.
A22: Last Stand | B22: 10 | C22: Once | D22: 5 | E22: 1d10+2 | F22: Physical | G22: Standard | H22: 1 | I22: Foe | J22: Melee | K22: The user gains a Shield/1 equal to the amount of Shield they have generated with Brave Leader before the start of this turn.
A23: Runes
A24: 70 HP | 0 ATK | 5 MAG | 10 PD | 15 MD | 2 MP | G24: "Inflict your opponents with persistent damage over time."
A25: Echoes of Time | B25: 1 | C25: Passive | D25: - | E25: - | F25: - | G25: Passive | H25: - | I25: - | J25: - | K25: Damage over Time (DoT) effects deal damage just before the affected Entity's turn and last for the specified duration, even if the user dies. The user can only inflict a Foe with one new DoT effect per turn.
A26: Galdr | B26: 1 | C26: Every Turn | D26: 3 | E26: 2d6+2 | F26: Magical | G26: Standard | H26: 1 | I26: Foe | J26: Range 5 (Splash 1) | K26: This move inflicts 2d6+2 DoT on the original target for 2 rounds.
A27: Astral Projection | B27: 2 | C27: EoT | D27: 2 | E27: 3d4+10 | F27: Magical | G27: Standard | H27: AoE | I27: Foes | J27: Burst 1 | K27: This move deals no damage. On hit, inflict the targets with DoT equal to the roll for one round. This move is immune to outside damage factors. Only add half MAG.
A28: Jera | B28: 3 | C28: E2T | D28: 4 | E28: 1d6+1 | F28: Magical | G28: Standard | H28: 1 | I28: Foe | J28: Range 2 | K28: Before accuracy, the user's active DoT effects on the target are extended by 1 round. On hit, the target takes double damage from the user's DoT for 1 round. Do not add MAG.
A29: Oath of Harmony | B29: 4 | C29: Every Turn | D29: - | E29: - | F29: - | G29: Swift | H29: 1 | I29: Self or Ally | J29: Homing 5 | K29: Whenever the target attacks a foe, they heal 15% of the damage dealt. When hitting multiple foes, only heal for 15% of the highest damage dealt to one. Only one target can be affected at a time. This effect only ends once the target dies, and does not stack.
A30: Oath of Discord | B30: 4 | C30: Every Turn | D30: - | E30: - | F30: - | G30: Swift | H30: 1 | I30: Foe | J30: Homing 5 | K30: The target takes 10% more damage from all attacks. Only one target can be affected at a time. This effect only ends once the target dies, and does not stack.
A31: Sealed Fate | B31: 5 | C31: Twice/E2T | D31: 4 | E31: 1d4+0 | F31: Magical | G31: Standard | H31: 2 | I31: Foes | J31: Range 3 (Double Hit) | K31: This move inflicts 2d4+5 DoT on the targets for 2 rounds. If neither hit misses a target, that target has -1 Evasions until this move's DoT expires.
A32: Hagalaz | B32: 6 | C32: Twice/EoT | D32: 4 | E32: 1d4+1 | F32: Magical | G32: Standard | H32: 1 | I32: Foe | J32: Global | K32: This move deals no damage. On hit, inflict the target with DoT equal to the roll for 2 rounds. This move is immune to outside damage factors. Do not add MAG.
A33: Crippling Ailment | B33: 7 | C33: Twice/E2T | D33: 4 | E33: 4d6+6 | F33: Magical | G33: Standard | H33: 1 | I33: Foe | J33: Varies | K33: Choose Isaz or Kenaz. Isaz: Homing 5. The target is inflicted with -2 EVAs/1 and -3 DR/1. Kenaz: Line 5. The user's active DoT effects on the target are extended by 1 round. Until those DoT effects expire, the target is inflicted with -2 ACC and -3 DMG.
A34: Inveita | B34: 8 | C34: Once | D34: - | E34: 3d4+6 | F34: - | G34: Swift or Standard | H34: 1 | I34: Ally | J34: Range 3 | K34: The target is healed for the amount rolled. As a Standard, add the user's MAG to the roll.
A35: Magic Circle | B35: 9 | C35: Once | D35: - | E35: - | F35: - | G35: Standard | H35: AoE | I35: Self and Allies | J35: Burst 2 | K35: For one round, the user and allies in range have +2 MP, deal an additional 20% attack damage to targets affected by the user's Oath of Discord, and heal an additional 30% of damage dealt with attacks while affected by the user's Oath of Harmony.
A36: Ragnarök | B36: 10 | C36: Once | D36: 4 | E36: 5d6+5 | F36: Magical | G36: Standard | H36: 1 | I36: Foe | J36: Range 5 | K36: This attack gains +damage equal to one quarter of the damage the user has dealt to foes with DoT this game.
A37: Talisman
A38: 65 HP | 7 ATK | 11 MAG | 15 PD | 15 MD | 2 MP | G38: "A weapon focused on buffing itself and/or allies."
A39: Solomon's Wisdom | B39: 1 | C39: Every Turn | D39: - | E39: - | F39: - | G39: Standard | H39: 1 | I39: Self or Ally | J39: Range 4 | K39: The target gains 1d8+5 damage to their next attack. A player cannot gain this buff again if they currently have this buff. Only two players can have this buff from the user at the same time (self and one ally).
A40: Smite | B40: 1 | C40: Every Turn | D40: 3 | E40: 2d8+7 | F40: Magical | G40: Standard | H40: 1 | I40: Foe | J40: Homing 5 | K40: This attack gains +1 dice if the target has used or received a buff at any point during the game.
A41: Blessing of Kings | B41: 2 | C41: EoT | D41: 3 | E41: 2d10+5 | F41: Magical | G41: Standard | H41: AoE | I41: Foes | J41: Cone 2 | K41: The user gains +1 ACC and +3 DR for one round.
A42: Purify | B42: 3 | C42: Thrice/E2T | D42: - | E42: 1d8+3 | F42: - | G42: Free | H42: 1 | I42: Self or Ally | J42: Range 3 | K42: The target heals the amount rolled and all the debuffs on the target are removed.
A43: Divine Merit | B43: 4 | C43: E2T | D43: 3 | E43: 2d8+5 | F43: Magical | G43: Standard | H43: 1 | I43: Foe | J43: Homing 6 | K43: 10% of the damage dealt by this attack is gained as +DMG for 1 round.
A44: Enlighten | B44: 5 | C44: Twice | D44: - | E44: - | F44: - | G44: Reaction | H44: 1 | I44: Ally | J44: Homing 3 | K44: This move can be used when an ally in range attacks or is attacked, before accuracy is rolled. The user's non-permanent buffs are transferred to the target for the rest of their duration. The target is also healed 5 HP.
A45: Indulgence | B45: 6 | C45: Twice/EoT | D45: - | E45: - | F45: - | G45: Swift | H45: 1 | I45: Self or Ally | J45: Range 5 | K45: The target gains two of the following buffs (chosen by the user) for one round: +2 ACC, +5 DR, +3 DMG, +2 Crit Range. The player cannot gain this buff again if they currently have this buff.
A46: Tempting Fate | B46: 7 | C46: Twice/EoT | D46: 4 | E46: 2d6+5 | F46: Magical | G46: Standard | H46: 2 | I46: Foes | J46: Melee (Double Hit) | K46: The user is inflicted with -3 DMG and -1 ACC for one round. If the user rolls 16+ on accuracy on one of the hits, these effects are negated. If the user rolls 16+ on accuracy on both hits, the debuffs are instead inverted.
A47: Absolution | B47: 8 | C47: Twice/EoT | D47: 5 | E47: 4d8+12 | F47: Magical | G47: Standard | H47: 1 | I47: Foe | J47: Range 4 | K47: Before accuracy, the user loses all of their buffs and cannot gain any until the start of their next turn.
A48: Siphon | B48: 9 | C48: Once | D48: 4 | E48: 3d8+6 | F48: Magical | G48: Standard | H48: 1 | I48: Foe | J48: Homing 5 | K48: Before accuracy, the target's non-permanent buffs are transferred to the user.
A49: Echo of Light | B49: 10 | C49: Once | D49: 5 | E49: 2d10+7 | F49: Magical | G49: Standard | H49: AoE | I49: Foes | J49: Pierce 3 | K49: After this move deals damage, the user's non-multiplicative buffs obtained through the user's Talisman abilities are doubled and extended by one round. These buffs may not be further increased in duration until their effects end.

Sheet Sorcerer
A1: Name | B1: Lvl | C1: Frequency | D1: MR | E1: Damage | H1: Target | K1: Effect
E2: Roll | F2: Type | G2: Action Type | H2: Amount | I2: Group | J2: Range and Modifiers
A3: Basic Abilities
A4: =Classes!A4 -> Basic Attack (P) / Basic Attack (M) | B4: =Classes!B4 -> B | C4: =Classes!C4 -> Every Turn | D4: =Classes!D4 -> 2 | E4: =Classes!E4 -> 1d10+2 | F4: =Classes!F4 -> Physical or Magical | G4: =Classes!G4 -> Standard | H4: =Classes!H4 -> 1 | ... K4: =Classes!K4 -> A basic attack. The user may choose either BATK (P) or BATK (M). Add the corresponding stat depending on their choice (BATK (P) = Physical Attack. BATK (M) = Magical Attack).This attack can be used even when sealed and its use cannot be prevented by any means, outside of Stun.
A5: =Classes!A5 -> Dash | B5: =Classes!B5 -> B | C5: =Classes!C5 -> Every Turn | D5: =Classes!D5 -> - | E5: =Classes!E5 -> - | F5: =Classes!F5 -> - | G5: =Classes!G5 -> Full | H5: =Classes!H5 -> - | ... K5: =Classes!K5 -> The user moves up to 1.5x their MP (rounded down) instead of 1x. (Dash is a Full action, which takes up both the Movement and Standard actions.)
A6: =Classes!A6 -> Backstep | B6: =Classes!B6 -> B | C6: =Classes!C6 -> Every Turn | D6: =Classes!D6 -> - | E6: =Classes!E6 -> - | F6: =Classes!F6 -> - | G6: =Classes!G6 -> Movement | H6: =Classes!H6 -> - | ... K6: =Classes!K6 -> This can only be used while a foe is in the user's Melee. The user moves one tile in a cardinal direction without triggering Attack of Opportunity.
A7: =Classes!A7 -> Attack of Opportunity | B7: =Classes!B7 -> B | C7: =Classes!C7 -> Every Turn | D7: =Classes!D7 -> 2 | E7: =Classes!E7 -> 1d10+2 | F7: =Classes!F7 -> Physical or Magical | G7: =Classes!G7 -> Reaction | H7: =Classes!H7 -> 1 | ... K7: =Classes!K7 -> This may be used when a foe in the user's Melee either: leaves that Melee with their Movement action, or uses a ranged attack that doesn't target the user (after damage is rolled). This Reaction still adds ATK or MAG.
A8: Sorcerer Abilities
A10: Shillelagh
A11: 65 HP | 13 ATK | 13 MAG | 10 PD | 10 MD | 1 MP | G11: "Manipulates and paints the map!" (Shi-lay-lee)
A12: Terraform | B12: 1 | C12: EoT | D12: - | E12: - | F12: - | G12: Trigger | H12: - | I12: - | J12: Cone 1 or Line 3 | K12: Select Cone 1 or Line 3 (cannot be diagonal). The user places up to three Forest or Water tiles in range (cannot replace obstructions).
A13: Rototill | B13: 1 | C13: Every Turn | D13: 3 | E13: 2d6+6 | F13: Physical | G13: Standard | H13: 1 | I13: - | J13: Range 4 (Pull 3) | K13: If the target is on a non-Normal tile, this attack loses Pull 3 but gains +1 ACC and +1 dice.
A14: Blackthorn | B14: 2 | C14: EoT | D14: 4 | E14: 4d4+5 | F14: Varies | G14: Standard | H14: 1 | I14: Foe | J14: Range 4 (Splash 1) | K14: Before damage, positive tile effects are inverted on targets for one round. Damage on targets (except the original) ignores negative outside factors to damage. The user chooses whether this attack is Physical or Magical.
A15: Windstorm | B15: 3 | C15: E2T | D15: 3 | E15: 2d8+4 | F15: Magical | G15: Standard | H15: AoE | I15: Foes | J15: Cone 2 (Push 1) | K15: Targets are pushed in the direction of the cone. Within range, the user may place either: 4 Air, 4 Sticky, or 1 Boost tile(s). There can only be one instance of Windstorm-generated tiles on the map from the user and allies at any one time. This may be used as a non-damaging Standard targeting only tiles in range.
A16: Bioturbation | B16: 4 | C16: EoT | D16: 3 | E16: 3d6+5 | F16: Physical | G16: Standard | H16: 1 | I16: Foe | J16: Range 6 | K16: If the user is on a non-Normal tile, they may move to a tile of the same type within their Range 6. This cannot move you further away from the target, and may pass through players. Players passed through gain -5 DR for one round.
A17: Bloom | B17: 5 | C17: E2T | D17: - | E17: - | F17: - | G17: Free | H17: - | I17: - | J17: Star 3 | K17: For one round, Normal tiles in range grant +1 ACC to the user and allies and -3 DMG to foes. (This effect does not stack.)
A18: Gelid Wrath | B18: 6 | C18: Twice/E2T | D18: 4 | E18: 5d4+8 | F18: Magical | G18: Swift or Standard | H18: AoE | I18: Foes | J18: Pierce 5 | K18: All unoccupied Water and Lava tiles in range become Ice for one round. The user cannot move through this Ice, and this can be used as a non-damaging Swift targetting only tiles in range. Foes who end their turn with at least one of these Ice tiles in their melee take 10 damage. This move converts the user's previously generated Ice to Normal, and the user may not generate Ice until the start of their next turn.
A19: Wildfire | B19: 7 | C19: Twice/EoT | D19: 4 | E19: 3d10+0 | F19: Magical | G19: Standard | H19: 1 | I19: Foe | J19: Range 4 | K19: If the target's tile is Forest, that tile gains "Wildfire". Wildfire: This property is unignorable. Inflicts 10 DMG and -1 EVA/1 on the start of an occupying player's turn. If there are Forest tiles cardinally adjacent to Wildfire, they also become Wildfire. This property ends after two rounds.
A20: Flower Crown | B20: 8 | C20: Twice/EoT | D20: - | E20: - | F20: - | G20: Swift | H20: AoE | I20: Self and Allies | J20: Global | K20: Targets on Forest tiles gain +10% DMG/1, while targets on Water tiles heal 4d4 HP.
A21: Nature's Madness | B21: 9 | C21: Twice/EoT | D21: 4 | E21: 3d8+4 | F21: Physical | G21: Standard | H21: 1 | I21: Foe | J21: Range 3 | K21: This move is immune to Air tiles, and is augmented depending on the number of certain tile types (X) in the user's Burst 1: Air/Sticky/Boost: +X Range, Damage and Amount of Targets (max 3). Forest/Water/Lava: Choose one tile type, and inflict X Bleed (Forest), Poison (Water), or Burn (Lava) / 1. If X>3, then extend the status duration by one round. After damage, convert utilised tiles to Normal.
A22: Scorched Earth | B22: 10 | C22: Once | D22: 4 | E22: 1d8+0 | F22: Physical | G22: Standard | H22: 1 | I22: Foe | J22: Range 3 (Push 1) | K22: After accuracy, tiles in the target's Star 1 become Lava tiles until the user dies. Lava from this move cannot be ignored, nor can entities take damage for entering more than once per turn.
A23: Spellbook
A24: 60 HP | 4 ATK | 12 MAG | 7 PD | 27 MD | 1 MP | G24: "A versatile weapon with many useful effects and debuffs."
A25: Fireball | B25: 1 | C25: Every Turn | D25: 2 | E25: 2d10+5 | F25: Magical | G25: Standard | H25: 1 | I25: Foe | J25: Line 4 | K25: On an accuracy roll of 16+, the target is inflicted with 3 Burn/1.
A26: Frost Hex | B26: 2 | C26: EoT | D26: 3 | E26: 2d8+6 | F26: Magical | G26: Standard | H26: 1 | I26: Foe | J26: Range 3 | K26: All attacks on the target have +2 accuracy for one round.
A27: Lightning | B27: 3 | C27: Twice/EoT | D27: 4 | E27: 1d10+3 | F27: Magical | G27: Standard | H27: 1 | I27: Foe | J27: Global | K27: This move is immune to outside factors. Do not add MAG.
A28: Fog | B28: 4 | C28: Twice/EoT | D28: 3 | E28: 1d8+0 | F28: Magical | G28: Standard | H28: 3 | I28: Foes | J28: Homing 8 | K28: Targets' ranged attacks have halved range (rounded up) until the end of their next turn. This ability only adds half MAG.
A29: Faith | B29: 5 | C29: Twice/EoT | D29: - | E29: 2d6+0 | F29: - | G29: Swift | H29: 1 | I29: Self or Ally | J29: Range 4 | K29: The target heals the amount rolled the next two times their turn ends.
A30: Sandstorm | B30: 6 | C30: Once | D30: 4 | E30: 2d8+5 | F30: Magical | G30: Standard | H30: AoE | I30: Foes | J30: Burst 2 | K30: Targets deal -25% damage on their next standard/full attack.
A31: Plague | B31: 7 | C31: E2T | D31: 4 | E31: 3d10+2 | F31: Magical | G31: Standard | H31: 1 | I31: Foe | J31: Homing 6 | K31: The user chooses Bleed, Burn or Poison. The target is inflicted with 5 [Chosen Status]/2.
A32: Tornado | B32: 8 | C32: Twice | D32: - | E32: - | F32: - | G32: Movement | H32: 1 | I32: Foe or Ally | J32: Range 5 | K32: The user teleports and swaps locations with the target, ignoring AoOs. On their next turn, the target has +1 MP.
A33: Focus | B33: 9 | C33: Once | D33: - | E33: - | F33: - | G33: Free | H33: - | I33: Self | J33: - | K33: The user’s next Spellbook attack deals -12 damage, and has its secondary effect doubled. (In the case of statuses, only duration is doubled.)
A34: Maelstrom | B34: 10 | C34: Once | D34: 4 | E34: 2d10+13 | F34: Magical | G34: Standard | H34: 1 | I34: Foe | J34: Range 4 (Splash 1) | K34: At the start of user's next turn, the user may choose to gain +10 damage, +3 accuracy, or +2 MP for that turn.
A35: Totems
A36: 70 HP | 3 ATK | 7 MAG | 5 PD | 5 MD | 1 MP | G36: "Build up Totem stacks for various offensive buffs."
A37: Carve Totem | B37: 1 | C37: Once | D37: - | E37: - | F37: - | G37: Trigger | H37: - | I37: Self | J37: - | K37: This may be used at the start of the user's turn and restores a use, once per turn, after the user's Standard/Full attack resolves. The user gains a Totem with one Animal of their choice and one Colour of their choice. Only the most recently carved Colour will have its effect. Animals: Lion (+2 damage), Hawk (+1 accuracy), Giraffe (+1 range). Colours: Red (+1 Dice), Blue (+2 DR), Green (+1 Evasion) The user may have a maximum of 5 Totems active at one time. Damage bonuses that scale with number of Totems are applied as outside damage factors.
A38: Totem Dance | B38: 1 | C38: Every Turn | D38: 3 | E38: 2d10+0 | F38: Magical | G38: Standard | H38: AoE | I38: Foes | J38: Burst 1 | K38: This attack deals +3 damage for each of the user's active Totems.
A39: Feral Spark | B39: 2 | C39: EoT | D39: 3 | E39: 2d8+5 | F39: Magical | G39: Standard | H39: 1 | I39: Foe | J39: Range 4 | K39: The user may create an additional Totem the next time they use Carve Totem.
A40: Blasphemy | B40: 3 | C40: EoT | D40: - | E40: - | F40: - | G40: Free | H40: AoE | I40: Allies | J40: Star 3 | K40: Each of the user's active Totem's bonuses are granted to the user's allies for one round.
A41: Animal Sacrifice | B41: 4 | C41: E2T | D41: 4 | E41: 1d8+3 | F41: Magical | G41: Standard | H41: 1 | I41: Foe | J41: Range 4 (Triple Hit) | K41: Before accuracy, the user may sacrifice one active Totem. This attack inflicts the target with that Totem's corresponding effect, where X is the number of successful hits. Lion: 3 Bleed/X. Hawk: 3 Poison/X. Giraffe: 3 Burn/X.
A42: Totem Crest | B42: 5 | C42: Once | D42: - | E42: - | F42: - | G42: Swift | H42: - | I42: Self | J42: - | K42: The user sacrifices one active Totem to permanently increase the effect of any Animal or Colour. Each Animal or Colour may only be crested once. Animals: Lion (+5% damage), Hawk (+2 Crit Range), Giraffe (+1 MP) Colours: One chosen colour has it's effect doubled.
A43: Totemic Focus | B43: 6 | C43: Twice | D43: 4 | E43: 2d8+6 | F43: Magical | G43: Standard | H43: AoE | I43: Foes | J43: Pierce 3 | K43: This attack gains +X dice, where X is the highest number of shared Animals or Colours across the user's active Totems.
A44: Chimeric Totem | B44: 7 | C44: Twice / E2T | D44: 4 | E44: 1d6+1 | F44: Magical | G44: Standard | H44: 1 | I44: Foe | J44: Range 3 (6 hits) | K44: For every active totem, this attack loses 1 hit. Each of the user's active totems inflicts the target with a stacking effect according to it's animal: Lion: -1 EVAS/1 Hawk: -2 DR/1 Giraffe: 2 Cripple/1
A45: Ancestral Wrath | B45: 8 | C45: Once | D45: 5 | E45: 2d10+3 | F45: Magical | G45: Standard | H45: 1 | I45: Foe | J45: Varies | K45: The user chooses one of their active totems to base this move's range and effect on. Lion: Melee. This attack ignores negative outside factors to damage. Hawk: Range 4. This attack gains an extra hit Giraffe: Range 4. This attack gains Push 2. If the target cannot be pushed the full distance, they recieve 1d10+5 damage and 2 Cripple/1.
A46: Manzat's Blessing | B46: 9 | C46: E2T | D46: 4 | E46: 3d6+6 | F46: Magical | G46: Standard | H46: 1 | I46: Foe | J46: Range 4 | K46: The user's Totem Colour effect is doubled for one round.
A47: Cataclysm | B47: 10 | C47: Once | D47: 5 | E47: 4d8+7 | F47: Magical | G47: Standard | H47: 1 | I47: Foe | J47: Range 3 | K47: Before accuracy, the user may choose to sacrifice any number of Totems. For each Totem sacrificed, the user gains +5 damage and +1 ACC for this attack. Carve Totem is disabled for one round.

Sheet Stats
B1: HP | C1: A | D1: M | E1: PD | F1: MD | G1: MP | H1: HP | I1: A | J1: M | K1: PD | L1: MD | M1: MP | N1: HP | O1: A | P1: M | Q1: PD | R1: MD | S1: MP | T1: HP | U1: A | V1: M | W1: PD | X1: MD | Y1: MP | Z1: HP | AA1: A | AB1: M | AC1: PD | AD1: MD | AE1: MP | AF1: HP | AG1: A | AH1: M | AI1: PD | AJ1: MD | AK1: MP
A2: Classes | B2: Bard | H2: Cryokinetic | N2: Guardian | T2: Pyrokinetic | Z2: Rifter | AF2: Skirmisher
A3: Stats | B3: 80 | C3: 6 | D3: 6 | E3: 22 | F3: 22 | G3: 3 | H3: 75 | I3: 7 | J3: 7 | K3: 21 | L3: 21 | M3: 3 | N3: 85 | O3: 5 | P3: 5 | Q3: 30 | R3: 30 | S3: 3 | T3: 65 | U3: 11 | V3: 11 | W3: 16 | X3: 16 | Y3: 3 | Z3: 60 | AA3: 9 | AB3: 9 | AC3: 19 | AD3: 19 | AE3: 3 | AF3: 65 | AG3: 8 | AH3: 8 | AI3: 20 | AJ3: 20 | AK3: 4
A4: Archer Celestial | B4: Crossbow | H4: Longbow | N4: Shortbow | T4: Lunar Rod | Z4: Solar Rod | AF4: Star Rod
A5: Stats | B5: 65 | C5: 11 | D5: 7 | E5: 13 | F5: 14 | G5: 1 | H5: 65 | I5: 12 | J5: 2 | K5: 6 | L5: 6 | M5: 1 | N5: 60 | O5: 10 | P5: 5 | Q5: 9 | R5: 9 | S5: 3 | T5: 70 | U5: 1 | V5: 13 | W5: 6 | X5: 10 | Y5: 2 | Z5: 60 | AA5: 2 | AB5: 14 | AC5: 9 | AD5: 9 | AE5: 1 | AF5: 65 | AG5: 0 | AH5: 11 | AI5: 12 | AJ5: 12 | AK5: 2
A6: Clairvoyant Dark | B6: Orb | H6: Pendulum | N6: Tarot Cards | T6: Athame | Z6: Chalice | AF6: Scythe
A7: Stats | B7: 60 | C7: 7 | D7: 13 | E7: 5 | F7: 16 | G7: 1 | H7: 65 | I7: 5 | J7: 9 | K7: 12 | L7: 9 | M7: 1 | N7: 65 | O7: 5 | P7: 11 | Q7: 9 | R7: 10 | S7: 2 | T7: 65 | U7: 6 | V7: 7 | W7: 15 | X7: 10 | Y7: 3 | Z7: 65 | AA7: 0 | AB7: 13 | AC7: 15 | AD7: 15 | AE7: 1 | AF7: 65 | AG7: 8 | AH7: 13 | AI7: 9 | AJ7: 9 | AK7: 2
A8: Dueler Fighter | B8: Gladius | H8: Katana | N8: Rapier | T8: Bo Staff | Z8: Claws | AF8: Tonfa
A9: Stats | B9: 65 | C9: 14 | D9: 0 | E9: 15 | F9: 10 | G9: 2 | H9: 65 | I9: 10 | J9: 0 | K9: 12 | L9: 12 | M9: 3 | N9: 60 | O9: 10 | P9: 9 | Q9: 13 | R9: 11 | S9: 2 | T9: 65 | U9: 12 | V9: 5 | W9: 14 | X9: 14 | Y9: 2 | Z9: 65 | AA9: 11 | AB9: 4 | AC9: 9 | AD9: 9 | AE9: 3 | AF9: 70 | AG9: 12 | AH9: 9 | AI9: 15 | AJ9: 15 | AK9: 2
A10: Heavy Regal | B10: Axe | H10: Hammer | N10: Tomahawk | T10: Crown | Z10: Runes | AF10: Talisman
A11: Stats | B11: 60 | C11: 19 | D11: 7 | E11: 11 | F11: 11 | G11: 1 | H11: 70 | I11: 15 | J11: 7 | K11: 19 | L11: 8 | M11: 1 | N11: 65 | O11: 13 | P11: 8 | Q11: 17 | R11: 10 | S11: 2 | T11: 70 | U11: 12 | V11: 4 | W11: 14 | X11: 14 | Y11: 2 | Z11: 70 | AA11: 0 | AB11: 5 | AC11: 10 | AD11: 15 | AE11: 2 | AF11: 65 | AG11: 7 | AH11: 11 | AI11: 15 | AJ11: 15 | AK11: 2
A12: Sorcerer | B12: Shillelagh | H12: Spellbook | N12: Totems
A13: Stats | B13: 65 | C13: 13 | D13: 13 | E13: 10 | F13: 10 | G13: 1 | H13: 60 | I13: 4 | J13: 12 | K13: 7 | L13: 27 | M13: 1 | N13: 70 | O13: 3 | P13: 7 | Q13: 5 | R13: 5 | S13: 1

Sheet Stats (old)
B1: HP | C1: A | D1: M | E1: PD | F1: MD | G1: MP | H1: HP | I1: A | J1: M | K1: PD | L1: MD | M1: MP | N1: HP | O1: A | P1: M | Q1: PD | R1: MD | S1: MP | T1: HP | U1: A | V1: M | W1: PD | X1: MD | Y1: MP | Z1: HP | AA1: A | AB1: M | AC1: PD | AD1: MD | AE1: MP | AF1: HP | AG1: A | AH1: M | AI1: PD | AJ1: MD | AK1: MP
A2: Classes | B2: Bard | H2: Cryokinetic | N2: Guardian | T2: Pyrokinetic | Z2: Rifter | AF2: Skirmisher
A3: 1 | B3: =ROUNDUP(((B$12*POWER(0.99,14*(10-$A3))/2)+B$12/2)/5,0)*5 -> 55 | C3: =ROUND((C$12*POWER(0.99,14*(10-$A3))/2)+C$12/2,0) -> 4 | D3: =ROUND((D$12*POWER(0.99,14*(10-$A3))/2)+D$12/2,0) -> 4 | E3: =ROUND((E$12*POWER(0.99,14*(10-$A3))/2)+E$12/2,0) -> 14 | F3: =ROUND((F$12*POWER(0.99,14*(10-$A3))/2)+F$12/2,0) -> 14 | G3: =G$12 -> 3 | H3: =ROUNDUP(((H$12*POWER(0.99,14*(10-$A3))/2)+H$12/2)/5,0)*5 -> 50 | I3: =ROUND((I$12*POWER(0.99,14*(10-$A3))/2)+I$12/2,0) -> 4 | J3: =ROUND((J$12*POWER(0.99,14*(10-$A3))/2)+J$12/2,0) -> 4 | K3: =ROUND((K$12*POWER(0.99,14*(10-$A3))/2)+K$12/2,0) -> 13 | L3: =ROUND((L$12*POWER(0.99,14*(10-$A3))/2)+L$12/2,0) -> 13 | M3: =M$12 -> 3 | N3: =ROUNDUP(((N$12*POWER(0.99,14*(10-$A3))/2)+N$12/2)/5,0)*5 -> 55 | O3: =ROUND((O$12*POWER(0.99,14*(10-$A3))/2)+O$12/2,0) -> 3 | P3: =ROUND((P$12*POWER(0.99,14*(10-$A3))/2)+P$12/2,0) -> 3 | Q3: =ROUND((Q$12*POWER(0.99,14*(10-$A3))/2)+Q$12/2,0) -> 19 | R3: =ROUND((R$12*POWER(0.99,14*(10-$A3))/2)+R$12/2,0) -> 19 | S3: =S$12 -> 3 | T3: =ROUNDUP(((T$12*POWER(0.99,14*(10-$A3))/2)+T$12/2)/5,0)*5 -> 45 | U3: =ROUND((U$12*POWER(0.99,14*(10-$A3))/2)+U$12/2,0) -> 7 | V3: =ROUND((V$12*POWER(0.99,14*(10-$A3))/2)+V$12/2,0) -> 7 | W3: =ROUND((W$12*POWER(0.99,14*(10-$A3))/2)+W$12/2,0) -> 10 | X3: =ROUND((X$12*POWER(0.99,14*(10-$A3))/2)+X$12/2,0) -> 10 | Y3: =Y$12 -> 3 | Z3: =ROUNDUP(((Z$12*POWER(0.99,14*(10-$A3))/2)+Z$12/2)/5,0)*5 -> 40 | AA3: =ROUND((AA$12*POWER(0.99,14*(10-$A3))/2)+AA$12/2,0) -> 6 | AB3: =ROUND((AB$12*POWER(0.99,14*(10-$A3))/2)+AB$12/2,0) -> 6 | AC3: =ROUND((AC$12*POWER(0.99,14*(10-$A3))/2)+AC$12/2,0) -> 12 | AD3: =ROUND((AD$12*POWER(0.99,14*(10-$A3))/2)+AD$12/2,0) -> 12 | AE3: =AE$12 -> 3 | AF3: =ROUNDUP(((AF$12*POWER(0.99,14*(10-$A3))/2)+AF$12/2)/5,0)*5 -> 45 | AG3: =ROUND((AG$12*POWER(0.99,14*(10-$A3))/2)+AG$12/2,0) -> 5 | AH3: =ROUND((AH$12*POWER(0.99,14*(10-$A3))/2)+AH$12/2,0) -> 5 | AI3: =ROUND((AI$12*POWER(0.99,14*(10-$A3))/2)+AI$12/2,0) -> 13 | AJ3: =ROUND((AJ$12*POWER(0.99,14*(10-$A3))/2)+AJ$12/2,0) -> 13 | AK3: =AK$12 -> 4
A4: 2 | B4: =ROUNDUP(((B$12*POWER(0.99,14*(10-$A4))/2)+B$12/2)/5,0)*5 -> 55 | C4: =ROUND((C$12*POWER(0.99,14*(10-$A4))/2)+C$12/2,0) -> 4 | D4: =ROUND((D$12*POWER(0.99,14*(10-$A4))/2)+D$12/2,0) -> 4 | E4: =ROUND((E$12*POWER(0.99,14*(10-$A4))/2)+E$12/2,0) -> 15 | F4: =ROUND((F$12*POWER(0.99,14*(10-$A4))/2)+F$12/2,0) -> 15 | G4: =G$12 -> 3 | H4: =ROUNDUP(((H$12*POWER(0.99,14*(10-$A4))/2)+H$12/2)/5,0)*5 -> 50 | I4: =ROUND((I$12*POWER(0.99,14*(10-$A4))/2)+I$12/2,0) -> 5 | J4: =ROUND((J$12*POWER(0.99,14*(10-$A4))/2)+J$12/2,0) -> 5 | K4: =ROUND((K$12*POWER(0.99,14*(10-$A4))/2)+K$12/2,0) -> 14 | L4: =ROUND((L$12*POWER(0.99,14*(10-$A4))/2)+L$12/2,0) -> 14 | M4: =M$12 -> 3 | N4: =ROUNDUP(((N$12*POWER(0.99,14*(10-$A4))/2)+N$12/2)/5,0)*5 -> 60 | O4: =ROUND((O$12*POWER(0.99,14*(10-$A4))/2)+O$12/2,0) -> 3 | P4: =ROUND((P$12*POWER(0.99,14*(10-$A4))/2)+P$12/2,0) -> 3 | Q4: =ROUND((Q$12*POWER(0.99,14*(10-$A4))/2)+Q$12/2,0) -> 20 | R4: =ROUND((R$12*POWER(0.99,14*(10-$A4))/2)+R$12/2,0) -> 20 | S4: =S$12 -> 3 | T4: =ROUNDUP(((T$12*POWER(0.99,14*(10-$A4))/2)+T$12/2)/5,0)*5 -> 45 | U4: =ROUND((U$12*POWER(0.99,14*(10-$A4))/2)+U$12/2,0) -> 7 | V4: =ROUND((V$12*POWER(0.99,14*(10-$A4))/2)+V$12/2,0) -> 7 | W4: =ROUND((W$12*POWER(0.99,14*(10-$A4))/2)+W$12/2,0) -> 11 | X4: =ROUND((X$12*POWER(0.99,14*(10-$A4))/2)+X$12/2,0) -> 11 | Y4: =Y$12 -> 3 | Z4: =ROUNDUP(((Z$12*POWER(0.99,14*(10-$A4))/2)+Z$12/2)/5,0)*5 -> 40 | AA4: =ROUND((AA$12*POWER(0.99,14*(10-$A4))/2)+AA$12/2,0) -> 6 | AB4: =ROUND((AB$12*POWER(0.99,14*(10-$A4))/2)+AB$12/2,0) -> 6 | AC4: =ROUND((AC$12*POWER(0.99,14*(10-$A4))/2)+AC$12/2,0) -> 13 | AD4: =ROUND((AD$12*POWER(0.99,14*(10-$A4))/2)+AD$12/2,0) -> 13 | AE4: =AE$12 -> 3 | AF4: =ROUNDUP(((AF$12*POWER(0.99,14*(10-$A4))/2)+AF$12/2)/5,0)*5 -> 45 | AG4: =ROUND((AG$12*POWER(0.99,14*(10-$A4))/2)+AG$12/2,0) -> 5 | AH4: =ROUND((AH$12*POWER(0.99,14*(10-$A4))/2)+AH$12/2,0) -> 5 | AI4: =ROUND((AI$12*POWER(0.99,14*(10-$A4))/2)+AI$12/2,0) -> 13 | AJ4: =ROUND((AJ$12*POWER(0.99,14*(10-$A4))/2)+AJ$12/2,0) -> 13 | AK4: =AK$12 -> 4
A5: 3 | B5: =ROUNDUP(((B$12*POWER(0.99,14*(10-$A5))/2)+B$12/2)/5,0)*5 -> 55 | C5: =ROUND((C$12*POWER(0.99,14*(10-$A5))/2)+C$12/2,0) -> 4 | D5: =ROUND((D$12*POWER(0.99,14*(10-$A5))/2)+D$12/2,0) -> 4 | E5: =ROUND((E$12*POWER(0.99,14*(10-$A5))/2)+E$12/2,0) -> 15 | F5: =ROUND((F$12*POWER(0.99,14*(10-$A5))/2)+F$12/2,0) -> 15 | G5: =G$12 -> 3 | H5: =ROUNDUP(((H$12*POWER(0.99,14*(10-$A5))/2)+H$12/2)/5,0)*5 -> 55 | I5: =ROUND((I$12*POWER(0.99,14*(10-$A5))/2)+I$12/2,0) -> 5 | J5: =ROUND((J$12*POWER(0.99,14*(10-$A5))/2)+J$12/2,0) -> 5 | K5: =ROUND((K$12*POWER(0.99,14*(10-$A5))/2)+K$12/2,0) -> 14 | L5: =ROUND((L$12*POWER(0.99,14*(10-$A5))/2)+L$12/2,0) -> 14 | M5: =M$12 -> 3 | N5: =ROUNDUP(((N$12*POWER(0.99,14*(10-$A5))/2)+N$12/2)/5,0)*5 -> 60 | O5: =ROUND((O$12*POWER(0.99,14*(10-$A5))/2)+O$12/2,0) -> 3 | P5: =ROUND((P$12*POWER(0.99,14*(10-$A5))/2)+P$12/2,0) -> 3 | Q5: =ROUND((Q$12*POWER(0.99,14*(10-$A5))/2)+Q$12/2,0) -> 21 | R5: =ROUND((R$12*POWER(0.99,14*(10-$A5))/2)+R$12/2,0) -> 21 | S5: =S$12 -> 3 | T5: =ROUNDUP(((T$12*POWER(0.99,14*(10-$A5))/2)+T$12/2)/5,0)*5 -> 45 | U5: =ROUND((U$12*POWER(0.99,14*(10-$A5))/2)+U$12/2,0) -> 8 | V5: =ROUND((V$12*POWER(0.99,14*(10-$A5))/2)+V$12/2,0) -> 8 | W5: =ROUND((W$12*POWER(0.99,14*(10-$A5))/2)+W$12/2,0) -> 11 | X5: =ROUND((X$12*POWER(0.99,14*(10-$A5))/2)+X$12/2,0) -> 11 | Y5: =Y$12 -> 3 | Z5: =ROUNDUP(((Z$12*POWER(0.99,14*(10-$A5))/2)+Z$12/2)/5,0)*5 -> 45 | AA5: =ROUND((AA$12*POWER(0.99,14*(10-$A5))/2)+AA$12/2,0) -> 6 | AB5: =ROUND((AB$12*POWER(0.99,14*(10-$A5))/2)+AB$12/2,0) -> 6 | AC5: =ROUND((AC$12*POWER(0.99,14*(10-$A5))/2)+AC$12/2,0) -> 13 | AD5: =ROUND((AD$12*POWER(0.99,14*(10-$A5))/2)+AD$12/2,0) -> 13 | AE5: =AE$12 -> 3 | AF5: =ROUNDUP(((AF$12*POWER(0.99,14*(10-$A5))/2)+AF$12/2)/5,0)*5 -> 45 | AG5: =ROUND((AG$12*POWER(0.99,14*(10-$A5))/2)+AG$12/2,0) -> 5 | AH5: =ROUND((AH$12*POWER(0.99,14*(10-$A5))/2)+AH$12/2,0) -> 5 | AI5: =ROUND((AI$12*POWER(0.99,14*(10-$A5))/2)+AI$12/2,0) -> 14 | AJ5: =ROUND((AJ$12*POWER(0.99,14*(10-$A5))/2)+AJ$12/2,0) -> 14 | AK5: =AK$12 -> 4
A6: 4 | B6: =ROUNDUP(((B$12*POWER(0.99,14*(10-$A6))/2)+B$12/2)/5,0)*5 -> 60 | C6: =ROUND((C$12*POWER(0.99,14*(10-$A6))/2)+C$12/2,0) -> 4 | D6: =ROUND((D$12*POWER(0.99,14*(10-$A6))/2)+D$12/2,0) -> 4 | E6: =ROUND((E$12*POWER(0.99,14*(10-$A6))/2)+E$12/2,0) -> 16 | F6: =ROUND((F$12*POWER(0.99,14*(10-$A6))/2)+F$12/2,0) -> 16 | G6: =G$12 -> 3 | H6: =ROUNDUP(((H$12*POWER(0.99,14*(10-$A6))/2)+H$12/2)/5,0)*5 -> 55 | I6: =ROUND((I$12*POWER(0.99,14*(10-$A6))/2)+I$12/2,0) -> 5 | J6: =ROUND((J$12*POWER(0.99,14*(10-$A6))/2)+J$12/2,0) -> 5 | K6: =ROUND((K$12*POWER(0.99,14*(10-$A6))/2)+K$12/2,0) -> 15 | L6: =ROUND((L$12*POWER(0.99,14*(10-$A6))/2)+L$12/2,0) -> 15 | M6: =M$12 -> 3 | N6: =ROUNDUP(((N$12*POWER(0.99,14*(10-$A6))/2)+N$12/2)/5,0)*5 -> 65 | O6: =ROUND((O$12*POWER(0.99,14*(10-$A6))/2)+O$12/2,0) -> 4 | P6: =ROUND((P$12*POWER(0.99,14*(10-$A6))/2)+P$12/2,0) -> 4 | Q6: =ROUND((Q$12*POWER(0.99,14*(10-$A6))/2)+Q$12/2,0) -> 21 | R6: =ROUND((R$12*POWER(0.99,14*(10-$A6))/2)+R$12/2,0) -> 21 | S6: =S$12 -> 3 | T6: =ROUNDUP(((T$12*POWER(0.99,14*(10-$A6))/2)+T$12/2)/5,0)*5 -> 50 | U6: =ROUND((U$12*POWER(0.99,14*(10-$A6))/2)+U$12/2,0) -> 8 | V6: =ROUND((V$12*POWER(0.99,14*(10-$A6))/2)+V$12/2,0) -> 8 | W6: =ROUND((W$12*POWER(0.99,14*(10-$A6))/2)+W$12/2,0) -> 11 | X6: =ROUND((X$12*POWER(0.99,14*(10-$A6))/2)+X$12/2,0) -> 11 | Y6: =Y$12 -> 3 | Z6: =ROUNDUP(((Z$12*POWER(0.99,14*(10-$A6))/2)+Z$12/2)/5,0)*5 -> 45 | AA6: =ROUND((AA$12*POWER(0.99,14*(10-$A6))/2)+AA$12/2,0) -> 6 | AB6: =ROUND((AB$12*POWER(0.99,14*(10-$A6))/2)+AB$12/2,0) -> 6 | AC6: =ROUND((AC$12*POWER(0.99,14*(10-$A6))/2)+AC$12/2,0) -> 14 | AD6: =ROUND((AD$12*POWER(0.99,14*(10-$A6))/2)+AD$12/2,0) -> 14 | AE6: =AE$12 -> 3 | AF6: =ROUNDUP(((AF$12*POWER(0.99,14*(10-$A6))/2)+AF$12/2)/5,0)*5 -> 50 | AG6: =ROUND((AG$12*POWER(0.99,14*(10-$A6))/2)+AG$12/2,0) -> 6 | AH6: =ROUND((AH$12*POWER(0.99,14*(10-$A6))/2)+AH$12/2,0) -> 6 | AI6: =ROUND((AI$12*POWER(0.99,14*(10-$A6))/2)+AI$12/2,0) -> 14 | AJ6: =ROUND((AJ$12*POWER(0.99,14*(10-$A6))/2)+AJ$12/2,0) -> 14 | AK6: =AK$12 -> 4
A7: 5 | B7: =ROUNDUP(((B$12*POWER(0.99,14*(10-$A7))/2)+B$12/2)/5,0)*5 -> 60 | C7: =ROUND((C$12*POWER(0.99,14*(10-$A7))/2)+C$12/2,0) -> 4 | D7: =ROUND((D$12*POWER(0.99,14*(10-$A7))/2)+D$12/2,0) -> 4 | E7: =ROUND((E$12*POWER(0.99,14*(10-$A7))/2)+E$12/2,0) -> 16 | F7: =ROUND((F$12*POWER(0.99,14*(10-$A7))/2)+F$12/2,0) -> 16 | G7: =G$12 -> 3 | H7: =ROUNDUP(((H$12*POWER(0.99,14*(10-$A7))/2)+H$12/2)/5,0)*5 -> 60 | I7: =ROUND((I$12*POWER(0.99,14*(10-$A7))/2)+I$12/2,0) -> 5 | J7: =ROUND((J$12*POWER(0.99,14*(10-$A7))/2)+J$12/2,0) -> 5 | K7: =ROUND((K$12*POWER(0.99,14*(10-$A7))/2)+K$12/2,0) -> 16 | L7: =ROUND((L$12*POWER(0.99,14*(10-$A7))/2)+L$12/2,0) -> 16 | M7: =M$12 -> 3 | N7: =ROUNDUP(((N$12*POWER(0.99,14*(10-$A7))/2)+N$12/2)/5,0)*5 -> 65 | O7: =ROUND((O$12*POWER(0.99,14*(10-$A7))/2)+O$12/2,0) -> 4 | P7: =ROUND((P$12*POWER(0.99,14*(10-$A7))/2)+P$12/2,0) -> 4 | Q7: =ROUND((Q$12*POWER(0.99,14*(10-$A7))/2)+Q$12/2,0) -> 22 | R7: =ROUND((R$12*POWER(0.99,14*(10-$A7))/2)+R$12/2,0) -> 22 | S7: =S$12 -> 3 | T7: =ROUNDUP(((T$12*POWER(0.99,14*(10-$A7))/2)+T$12/2)/5,0)*5 -> 50 | U7: =ROUND((U$12*POWER(0.99,14*(10-$A7))/2)+U$12/2,0) -> 8 | V7: =ROUND((V$12*POWER(0.99,14*(10-$A7))/2)+V$12/2,0) -> 8 | W7: =ROUND((W$12*POWER(0.99,14*(10-$A7))/2)+W$12/2,0) -> 12 | X7: =ROUND((X$12*POWER(0.99,14*(10-$A7))/2)+X$12/2,0) -> 12 | Y7: =Y$12 -> 3 | Z7: =ROUNDUP(((Z$12*POWER(0.99,14*(10-$A7))/2)+Z$12/2)/5,0)*5 -> 45 | AA7: =ROUND((AA$12*POWER(0.99,14*(10-$A7))/2)+AA$12/2,0) -> 7 | AB7: =ROUND((AB$12*POWER(0.99,14*(10-$A7))/2)+AB$12/2,0) -> 7 | AC7: =ROUND((AC$12*POWER(0.99,14*(10-$A7))/2)+AC$12/2,0) -> 14 | AD7: =ROUND((AD$12*POWER(0.99,14*(10-$A7))/2)+AD$12/2,0) -> 14 | AE7: =AE$12 -> 3 | AF7: =ROUNDUP(((AF$12*POWER(0.99,14*(10-$A7))/2)+AF$12/2)/5,0)*5 -> 50 | AG7: =ROUND((AG$12*POWER(0.99,14*(10-$A7))/2)+AG$12/2,0) -> 6 | AH7: =ROUND((AH$12*POWER(0.99,14*(10-$A7))/2)+AH$12/2,0) -> 6 | AI7: =ROUND((AI$12*POWER(0.99,14*(10-$A7))/2)+AI$12/2,0) -> 15 | AJ7: =ROUND((AJ$12*POWER(0.99,14*(10-$A7))/2)+AJ$12/2,0) -> 15 | AK7: =AK$12 -> 4
A8: 6 | B8: =ROUNDUP(((B$12*POWER(0.99,14*(10-$A8))/2)+B$12/2)/5,0)*5 -> 65 | C8: =ROUND((C$12*POWER(0.99,14*(10-$A8))/2)+C$12/2,0) -> 5 | D8: =ROUND((D$12*POWER(0.99,14*(10-$A8))/2)+D$12/2,0) -> 5 | E8: =ROUND((E$12*POWER(0.99,14*(10-$A8))/2)+E$12/2,0) -> 17 | F8: =ROUND((F$12*POWER(0.99,14*(10-$A8))/2)+F$12/2,0) -> 17 | G8: =G$12 -> 3 | H8: =ROUNDUP(((H$12*POWER(0.99,14*(10-$A8))/2)+H$12/2)/5,0)*5 -> 60 | I8: =ROUND((I$12*POWER(0.99,14*(10-$A8))/2)+I$12/2,0) -> 5 | J8: =ROUND((J$12*POWER(0.99,14*(10-$A8))/2)+J$12/2,0) -> 5 | K8: =ROUND((K$12*POWER(0.99,14*(10-$A8))/2)+K$12/2,0) -> 16 | L8: =ROUND((L$12*POWER(0.99,14*(10-$A8))/2)+L$12/2,0) -> 16 | M8: =M$12 -> 3 | N8: =ROUNDUP(((N$12*POWER(0.99,14*(10-$A8))/2)+N$12/2)/5,0)*5 -> 70 | O8: =ROUND((O$12*POWER(0.99,14*(10-$A8))/2)+O$12/2,0) -> 4 | P8: =ROUND((P$12*POWER(0.99,14*(10-$A8))/2)+P$12/2,0) -> 4 | Q8: =ROUND((Q$12*POWER(0.99,14*(10-$A8))/2)+Q$12/2,0) -> 24 | R8: =ROUND((R$12*POWER(0.99,14*(10-$A8))/2)+R$12/2,0) -> 24 | S8: =S$12 -> 3 | T8: =ROUNDUP(((T$12*POWER(0.99,14*(10-$A8))/2)+T$12/2)/5,0)*5 -> 55 | U8: =ROUND((U$12*POWER(0.99,14*(10-$A8))/2)+U$12/2,0) -> 9 | V8: =ROUND((V$12*POWER(0.99,14*(10-$A8))/2)+V$12/2,0) -> 9 | W8: =ROUND((W$12*POWER(0.99,14*(10-$A8))/2)+W$12/2,0) -> 13 | X8: =ROUND((X$12*POWER(0.99,14*(10-$A8))/2)+X$12/2,0) -> 13 | Y8: =Y$12 -> 3 | Z8: =ROUNDUP(((Z$12*POWER(0.99,14*(10-$A8))/2)+Z$12/2)/5,0)*5 -> 50 | AA8: =ROUND((AA$12*POWER(0.99,14*(10-$A8))/2)+AA$12/2,0) -> 7 | AB8: =ROUND((AB$12*POWER(0.99,14*(10-$A8))/2)+AB$12/2,0) -> 7 | AC8: =ROUND((AC$12*POWER(0.99,14*(10-$A8))/2)+AC$12/2,0) -> 15 | AD8: =ROUND((AD$12*POWER(0.99,14*(10-$A8))/2)+AD$12/2,0) -> 15 | AE8: =AE$12 -> 3 | AF8: =ROUNDUP(((AF$12*POWER(0.99,14*(10-$A8))/2)+AF$12/2)/5,0)*5 -> 55 | AG8: =ROUND((AG$12*POWER(0.99,14*(10-$A8))/2)+AG$12/2,0) -> 6 | AH8: =ROUND((AH$12*POWER(0.99,14*(10-$A8))/2)+AH$12/2,0) -> 6 | AI8: =ROUND((AI$12*POWER(0.99,14*(10-$A8))/2)+AI$12/2,0) -> 16 | AJ8: =ROUND((AJ$12*POWER(0.99,14*(10-$A8))/2)+AJ$12/2,0) -> 16 | AK8: =AK$12 -> 4
A9: 7 | B9: =ROUNDUP(((B$12*POWER(0.99,14*(10-$A9))/2)+B$12/2)/5,0)*5 -> 70 | C9: =ROUND((C$12*POWER(0.99,14*(10-$A9))/2)+C$12/2,0) -> 5 | D9: =ROUND((D$12*POWER(0.99,14*(10-$A9))/2)+D$12/2,0) -> 5 | E9: =ROUND((E$12*POWER(0.99,14*(10-$A9))/2)+E$12/2,0) -> 18 | F9: =ROUND((F$12*POWER(0.99,14*(10-$A9))/2)+F$12/2,0) -> 18 | G9: =G$12 -> 3 | H9: =ROUNDUP(((H$12*POWER(0.99,14*(10-$A9))/2)+H$12/2)/5,0)*5 -> 65 | I9: =ROUND((I$12*POWER(0.99,14*(10-$A9))/2)+I$12/2,0) -> 6 | J9: =ROUND((J$12*POWER(0.99,14*(10-$A9))/2)+J$12/2,0) -> 6 | K9: =ROUND((K$12*POWER(0.99,14*(10-$A9))/2)+K$12/2,0) -> 17 | L9: =ROUND((L$12*POWER(0.99,14*(10-$A9))/2)+L$12/2,0) -> 17 | M9: =M$12 -> 3 | N9: =ROUNDUP(((N$12*POWER(0.99,14*(10-$A9))/2)+N$12/2)/5,0)*5 -> 75 | O9: =ROUND((O$12*POWER(0.99,14*(10-$A9))/2)+O$12/2,0) -> 4 | P9: =ROUND((P$12*POWER(0.99,14*(10-$A9))/2)+P$12/2,0) -> 4 | Q9: =ROUND((Q$12*POWER(0.99,14*(10-$A9))/2)+Q$12/2,0) -> 25 | R9: =ROUND((R$12*POWER(0.99,14*(10-$A9))/2)+R$12/2,0) -> 25 | S9: 3 | T9: =ROUNDUP(((T$12*POWER(0.99,14*(10-$A9))/2)+T$12/2)/5,0)*5 -> 55 | U9: =ROUND((U$12*POWER(0.99,14*(10-$A9))/2)+U$12/2,0) -> 9 | V9: =ROUND((V$12*POWER(0.99,14*(10-$A9))/2)+V$12/2,0) -> 9 | W9: =ROUND((W$12*POWER(0.99,14*(10-$A9))/2)+W$12/2,0) -> 13 | X9: =ROUND((X$12*POWER(0.99,14*(10-$A9))/2)+X$12/2,0) -> 13 | Y9: =Y$12 -> 3 | Z9: =ROUNDUP(((Z$12*POWER(0.99,14*(10-$A9))/2)+Z$12/2)/5,0)*5 -> 50 | AA9: =ROUND((AA$12*POWER(0.99,14*(10-$A9))/2)+AA$12/2,0) -> 7 | AB9: =ROUND((AB$12*POWER(0.99,14*(10-$A9))/2)+AB$12/2,0) -> 7 | AC9: =ROUND((AC$12*POWER(0.99,14*(10-$A9))/2)+AC$12/2,0) -> 16 | AD9: =ROUND((AD$12*POWER(0.99,14*(10-$A9))/2)+AD$12/2,0) -> 16 | AE9: =AE$12 -> 3 | AF9: =ROUNDUP(((AF$12*POWER(0.99,14*(10-$A9))/2)+AF$12/2)/5,0)*5 -> 55 | AG9: =ROUND((AG$12*POWER(0.99,14*(10-$A9))/2)+AG$12/2,0) -> 7 | AH9: =ROUND((AH$12*POWER(0.99,14*(10-$A9))/2)+AH$12/2,0) -> 7 | AI9: =ROUND((AI$12*POWER(0.99,14*(10-$A9))/2)+AI$12/2,0) -> 17 | AJ9: =ROUND((AJ$12*POWER(0.99,14*(10-$A9))/2)+AJ$12/2,0) -> 17 | AK9: =AK$12 -> 4
A10: 8 | B10: =ROUNDUP(((B$12*POWER(0.99,14*(10-$A10))/2)+B$12/2)/5,0)*5 -> 75 | C10: =ROUND((C$12*POWER(0.99,14*(10-$A10))/2)+C$12/2,0) -> 5 | D10: =ROUND((D$12*POWER(0.99,14*(10-$A10))/2)+D$12/2,0) -> 5 | E10: =ROUND((E$12*POWER(0.99,14*(10-$A10))/2)+E$12/2,0) -> 19 | F10: =ROUND((F$12*POWER(0.99,14*(10-$A10))/2)+F$12/2,0) -> 19 | G10: =G$12 -> 3 | H10: =ROUNDUP(((H$12*POWER(0.99,14*(10-$A10))/2)+H$12/2)/5,0)*5 -> 70 | I10: =ROUND((I$12*POWER(0.99,14*(10-$A10))/2)+I$12/2,0) -> 6 | J10: =ROUND((J$12*POWER(0.99,14*(10-$A10))/2)+J$12/2,0) -> 6 | K10: =ROUND((K$12*POWER(0.99,14*(10-$A10))/2)+K$12/2,0) -> 18 | L10: =ROUND((L$12*POWER(0.99,14*(10-$A10))/2)+L$12/2,0) -> 18 | M10: =M$12 -> 3 | N10: =ROUNDUP(((N$12*POWER(0.99,14*(10-$A10))/2)+N$12/2)/5,0)*5 -> 75 | O10: =ROUND((O$12*POWER(0.99,14*(10-$A10))/2)+O$12/2,0) -> 4 | P10: =ROUND((P$12*POWER(0.99,14*(10-$A10))/2)+P$12/2,0) -> 4 | Q10: =ROUND((Q$12*POWER(0.99,14*(10-$A10))/2)+Q$12/2,0) -> 26 | R10: =ROUND((R$12*POWER(0.99,14*(10-$A10))/2)+R$12/2,0) -> 26 | S10: 3 | T10: =ROUNDUP(((T$12*POWER(0.99,14*(10-$A10))/2)+T$12/2)/5,0)*5 -> 60 | U10: =ROUND((U$12*POWER(0.99,14*(10-$A10))/2)+U$12/2,0) -> 10 | V10: =ROUND((V$12*POWER(0.99,14*(10-$A10))/2)+V$12/2,0) -> 10 | W10: =ROUND((W$12*POWER(0.99,14*(10-$A10))/2)+W$12/2,0) -> 14 | X10: =ROUND((X$12*POWER(0.99,14*(10-$A10))/2)+X$12/2,0) -> 14 | Y10: =Y$12 -> 3 | Z10: =ROUNDUP(((Z$12*POWER(0.99,14*(10-$A10))/2)+Z$12/2)/5,0)*5 -> 55 | AA10: =ROUND((AA$12*POWER(0.99,14*(10-$A10))/2)+AA$12/2,0) -> 8 | AB10: =ROUND((AB$12*POWER(0.99,14*(10-$A10))/2)+AB$12/2,0) -> 8 | AC10: =ROUND((AC$12*POWER(0.99,14*(10-$A10))/2)+AC$12/2,0) -> 17 | AD10: =ROUND((AD$12*POWER(0.99,14*(10-$A10))/2)+AD$12/2,0) -> 17 | AE10: =AE$12 -> 3 | AF10: =ROUNDUP(((AF$12*POWER(0.99,14*(10-$A10))/2)+AF$12/2)/5,0)*5 -> 60 | AG10: =ROUND((AG$12*POWER(0.99,14*(10-$A10))/2)+AG$12/2,0) -> 7 | AH10: =ROUND((AH$12*POWER(0.99,14*(10-$A10))/2)+AH$12/2,0) -> 7 | AI10: =ROUND((AI$12*POWER(0.99,14*(10-$A10))/2)+AI$12/2,0) -> 18 | AJ10: =ROUND((AJ$12*POWER(0.99,14*(10-$A10))/2)+AJ$12/2,0) -> 18 | AK10: =AK$12 -> 4
A11: 9 | B11: =ROUNDUP(((B$12*POWER(0.99,14*(10-$A11))/2)+B$12/2)/5,0)*5 -> 75 | C11: =ROUND((C$12*POWER(0.99,14*(10-$A11))/2)+C$12/2,0) -> 6 | D11: =ROUND((D$12*POWER(0.99,14*(10-$A11))/2)+D$12/2,0) -> 6 | E11: =ROUND((E$12*POWER(0.99,14*(10-$A11))/2)+E$12/2,0) -> 21 | F11: =ROUND((F$12*POWER(0.99,14*(10-$A11))/2)+F$12/2,0) -> 21 | G11: =G$12 -> 3 | H11: =ROUNDUP(((H$12*POWER(0.99,14*(10-$A11))/2)+H$12/2)/5,0)*5 -> 75 | I11: =ROUND((I$12*POWER(0.99,14*(10-$A11))/2)+I$12/2,0) -> 7 | J11: =ROUND((J$12*POWER(0.99,14*(10-$A11))/2)+J$12/2,0) -> 7 | K11: =ROUND((K$12*POWER(0.99,14*(10-$A11))/2)+K$12/2,0) -> 20 | L11: =ROUND((L$12*POWER(0.99,14*(10-$A11))/2)+L$12/2,0) -> 20 | M11: =M$12 -> 3 | N11: =ROUNDUP(((N$12*POWER(0.99,14*(10-$A11))/2)+N$12/2)/5,0)*5 -> 80 | O11: =ROUND((O$12*POWER(0.99,14*(10-$A11))/2)+O$12/2,0) -> 5 | P11: =ROUND((P$12*POWER(0.99,14*(10-$A11))/2)+P$12/2,0) -> 5 | Q11: =ROUND((Q$12*POWER(0.99,14*(10-$A11))/2)+Q$12/2,0) -> 28 | R11: =ROUND((R$12*POWER(0.99,14*(10-$A11))/2)+R$12/2,0) -> 28 | S11: 3 | T11: =ROUNDUP(((T$12*POWER(0.99,14*(10-$A11))/2)+T$12/2)/5,0)*5 -> 65 | U11: =ROUND((U$12*POWER(0.99,14*(10-$A11))/2)+U$12/2,0) -> 10 | V11: =ROUND((V$12*POWER(0.99,14*(10-$A11))/2)+V$12/2,0) -> 10 | W11: =ROUND((W$12*POWER(0.99,14*(10-$A11))/2)+W$12/2,0) -> 15 | X11: =ROUND((X$12*POWER(0.99,14*(10-$A11))/2)+X$12/2,0) -> 15 | Y11: =Y$12 -> 3 | Z11: =ROUNDUP(((Z$12*POWER(0.99,14*(10-$A11))/2)+Z$12/2)/5,0)*5 -> 60 | AA11: =ROUND((AA$12*POWER(0.99,14*(10-$A11))/2)+AA$12/2,0) -> 8 | AB11: =ROUND((AB$12*POWER(0.99,14*(10-$A11))/2)+AB$12/2,0) -> 8 | AC11: =ROUND((AC$12*POWER(0.99,14*(10-$A11))/2)+AC$12/2,0) -> 18 | AD11: =ROUND((AD$12*POWER(0.99,14*(10-$A11))/2)+AD$12/2,0) -> 18 | AE11: =AE$12 -> 3 | AF11: =ROUNDUP(((AF$12*POWER(0.99,14*(10-$A11))/2)+AF$12/2)/5,0)*5 -> 65 | AG11: =ROUND((AG$12*POWER(0.99,14*(10-$A11))/2)+AG$12/2,0) -> 7 | AH11: =ROUND((AH$12*POWER(0.99,14*(10-$A11))/2)+AH$12/2,0) -> 7 | AI11: =ROUND((AI$12*POWER(0.99,14*(10-$A11))/2)+AI$12/2,0) -> 19 | AJ11: =ROUND((AJ$12*POWER(0.99,14*(10-$A11))/2)+AJ$12/2,0) -> 19 | AK11: =AK$12 -> 4
A12: 10 | B12: 80 | C12: 6 | D12: 6 | E12: 22 | F12: 22 | G12: 3 | H12: 75 | I12: 7 | J12: 7 | K12: 21 | L12: 21 | M12: 3 | N12: 85 | O12: 5 | P12: 5 | Q12: 30 | R12: 30 | S12: 3 | T12: 65 | U12: 11 | V12: 11 | W12: 16 | X12: 16 | Y12: 3 | Z12: 60 | AA12: 9 | AB12: 9 | AC12: 19 | AD12: 19 | AE12: 3 | AF12: 65 | AG12: 8 | AH12: 8 | AI12: 20 | AJ12: 20 | AK12: 4
A13: Archer / Celestial | B13: Crossbow | H13: Longbow | N13: Shortbow | T13: Lunar Rod | Z13: Solar Rod | AF13: Star Rod
A14: 1 | B14: =ROUNDUP(((B$23*POWER(0.99,14*(10-$A25))/2)+B$23/2)/5,0)*5 -> 45 | C14: =ROUND((C$23*POWER(0.99,14*(10-$A25))/2)+C$23/2,0) -> 7 | D14: =ROUND((D$23*POWER(0.99,14*(10-$A25))/2)+D$23/2,0) -> 4 | E14: =ROUND((E$23*POWER(0.99,14*(10-$A25))/2)+E$23/2,0) -> 8 | F14: =ROUND((F$23*POWER(0.99,14*(10-$A25))/2)+F$23/2,0) -> 9 | G14: =G$23 -> 1 | H14: =ROUNDUP(((H$23*POWER(0.99,14*(10-$A25))/2)+H$23/2)/5,0)*5 -> 45 | I14: =ROUND((I$23*POWER(0.99,14*(10-$A25))/2)+I$23/2,0) -> 8 | J14: =ROUND((J$23*POWER(0.99,14*(10-$A25))/2)+J$23/2,0) -> 1 | K14: =ROUND((K$23*POWER(0.99,14*(10-$A25))/2)+K$23/2,0) -> 4 | L14: =ROUND((L$23*POWER(0.99,14*(10-$A25))/2)+L$23/2,0) -> 4 | M14: =M$23 -> 1 | N14: =ROUNDUP(((N$23*POWER(0.99,14*(10-$A25))/2)+N$23/2)/5,0)*5 -> 40 | O14: =ROUND((O$23*POWER(0.99,14*(10-$A25))/2)+O$23/2,0) -> 6 | P14: =ROUND((P$23*POWER(0.99,14*(10-$A25))/2)+P$23/2,0) -> 3 | Q14: =ROUND((Q$23*POWER(0.99,14*(10-$A25))/2)+Q$23/2,0) -> 6 | R14: =ROUND((R$23*POWER(0.99,14*(10-$A25))/2)+R$23/2,0) -> 6 | S14: =S$23 -> 3 | T14: =ROUNDUP(((T$23*POWER(0.99,14*(10-$A58))/2)+T$23/2)/5,0)*5 -> 45 | U14: =ROUND((U$23*POWER(0.99,14*(10-$A58))/2)+U$23/2,0) -> 1 | V14: =ROUND((V$23*POWER(0.99,14*(10-$A58))/2)+V$23/2,0) -> 8 | W14: =ROUND((W$23*POWER(0.99,14*(10-$A58))/2)+W$23/2,0) -> 4 | X14: =ROUND((X$23*POWER(0.99,14*(10-$A58))/2)+X$23/2,0) -> 6 | Y14: =Y$23 -> 2 | Z14: =ROUNDUP(((Z$23*POWER(0.99,14*(10-$A58))/2)+Z$23/2)/5,0)*5 -> 40 | AA14: =ROUND((AA$23*POWER(0.99,14*(10-$A58))/2)+AA$23/2,0) -> 1 | AB14: =ROUND((AB$23*POWER(0.99,14*(10-$A58))/2)+AB$23/2,0) -> 9 | AC14: =ROUND((AC$23*POWER(0.99,14*(10-$A58))/2)+AC$23/2,0) -> 6 | AD14: =ROUND((AD$23*POWER(0.99,14*(10-$A58))/2)+AD$23/2,0) -> 6 | AE14: =AE$23 -> 1 | AF14: =ROUNDUP(((AF$23*POWER(0.99,14*(10-$A58))/2)+AF$23/2)/5,0)*5 -> 45 | AG14: =ROUND((AG$23*POWER(0.99,14*(10-$A58))/2)+AG$23/2,0) -> 0 | AH14: =ROUND((AH$23*POWER(0.99,14*(10-$A58))/2)+AH$23/2,0) -> 7 | AI14: =ROUND((AI$23*POWER(0.99,14*(10-$A58))/2)+AI$23/2,0) -> 8 | AJ14: =ROUND((AJ$23*POWER(0.99,14*(10-$A58))/2)+AJ$23/2,0) -> 8 | AK14: =AK$23 -> 2
A15: 2 | B15: =ROUNDUP(((B$23*POWER(0.99,14*(10-$A26))/2)+B$23/2)/5,0)*5 -> 45 | C15: =ROUND((C$23*POWER(0.99,14*(10-$A26))/2)+C$23/2,0) -> 7 | D15: =ROUND((D$23*POWER(0.99,14*(10-$A26))/2)+D$23/2,0) -> 5 | E15: =ROUND((E$23*POWER(0.99,14*(10-$A26))/2)+E$23/2,0) -> 9 | F15: =ROUND((F$23*POWER(0.99,14*(10-$A26))/2)+F$23/2,0) -> 9 | G15: =G$23 -> 1 | H15: =ROUNDUP(((H$23*POWER(0.99,14*(10-$A26))/2)+H$23/2)/5,0)*5 -> 45 | I15: =ROUND((I$23*POWER(0.99,14*(10-$A26))/2)+I$23/2,0) -> 8 | J15: =ROUND((J$23*POWER(0.99,14*(10-$A26))/2)+J$23/2,0) -> 1 | K15: =ROUND((K$23*POWER(0.99,14*(10-$A26))/2)+K$23/2,0) -> 4 | L15: =ROUND((L$23*POWER(0.99,14*(10-$A26))/2)+L$23/2,0) -> 4 | M15: =M$23 -> 1 | N15: =ROUNDUP(((N$23*POWER(0.99,14*(10-$A26))/2)+N$23/2)/5,0)*5 -> 40 | O15: =ROUND((O$23*POWER(0.99,14*(10-$A26))/2)+O$23/2,0) -> 7 | P15: =ROUND((P$23*POWER(0.99,14*(10-$A26))/2)+P$23/2,0) -> 3 | Q15: =ROUND((Q$23*POWER(0.99,14*(10-$A26))/2)+Q$23/2,0) -> 6 | R15: =ROUND((R$23*POWER(0.99,14*(10-$A26))/2)+R$23/2,0) -> 6 | S15: =S$23 -> 3 | T15: =ROUNDUP(((T$23*POWER(0.99,14*(10-$A59))/2)+T$23/2)/5,0)*5 -> 50 | U15: =ROUND((U$23*POWER(0.99,14*(10-$A59))/2)+U$23/2,0) -> 1 | V15: =ROUND((V$23*POWER(0.99,14*(10-$A59))/2)+V$23/2,0) -> 9 | W15: =ROUND((W$23*POWER(0.99,14*(10-$A59))/2)+W$23/2,0) -> 4 | X15: =ROUND((X$23*POWER(0.99,14*(10-$A59))/2)+X$23/2,0) -> 7 | Y15: =Y$23 -> 2 | Z15: =ROUNDUP(((Z$23*POWER(0.99,14*(10-$A59))/2)+Z$23/2)/5,0)*5 -> 40 | AA15: =ROUND((AA$23*POWER(0.99,14*(10-$A59))/2)+AA$23/2,0) -> 1 | AB15: =ROUND((AB$23*POWER(0.99,14*(10-$A59))/2)+AB$23/2,0) -> 9 | AC15: =ROUND((AC$23*POWER(0.99,14*(10-$A59))/2)+AC$23/2,0) -> 6 | AD15: =ROUND((AD$23*POWER(0.99,14*(10-$A59))/2)+AD$23/2,0) -> 6 | AE15: =AE$23 -> 1 | AF15: =ROUNDUP(((AF$23*POWER(0.99,14*(10-$A59))/2)+AF$23/2)/5,0)*5 -> 45 | AG15: =ROUND((AG$23*POWER(0.99,14*(10-$A59))/2)+AG$23/2,0) -> 0 | AH15: =ROUND((AH$23*POWER(0.99,14*(10-$A59))/2)+AH$23/2,0) -> 7 | AI15: =ROUND((AI$23*POWER(0.99,14*(10-$A59))/2)+AI$23/2,0) -> 8 | AJ15: =ROUND((AJ$23*POWER(0.99,14*(10-$A59))/2)+AJ$23/2,0) -> 8 | AK15: =AK$23 -> 2
A16: 3 | B16: =ROUNDUP(((B$23*POWER(0.99,14*(10-$A27))/2)+B$23/2)/5,0)*5 -> 45 | C16: =ROUND((C$23*POWER(0.99,14*(10-$A27))/2)+C$23/2,0) -> 8 | D16: =ROUND((D$23*POWER(0.99,14*(10-$A27))/2)+D$23/2,0) -> 5 | E16: =ROUND((E$23*POWER(0.99,14*(10-$A27))/2)+E$23/2,0) -> 9 | F16: =ROUND((F$23*POWER(0.99,14*(10-$A27))/2)+F$23/2,0) -> 10 | G16: =G$23 -> 1 | H16: =ROUNDUP(((H$23*POWER(0.99,14*(10-$A27))/2)+H$23/2)/5,0)*5 -> 45 | I16: =ROUND((I$23*POWER(0.99,14*(10-$A27))/2)+I$23/2,0) -> 8 | J16: =ROUND((J$23*POWER(0.99,14*(10-$A27))/2)+J$23/2,0) -> 1 | K16: =ROUND((K$23*POWER(0.99,14*(10-$A27))/2)+K$23/2,0) -> 4 | L16: =ROUND((L$23*POWER(0.99,14*(10-$A27))/2)+L$23/2,0) -> 4 | M16: =M$23 -> 1 | N16: =ROUNDUP(((N$23*POWER(0.99,14*(10-$A27))/2)+N$23/2)/5,0)*5 -> 45 | O16: =ROUND((O$23*POWER(0.99,14*(10-$A27))/2)+O$23/2,0) -> 7 | P16: =ROUND((P$23*POWER(0.99,14*(10-$A27))/2)+P$23/2,0) -> 3 | Q16: =ROUND((Q$23*POWER(0.99,14*(10-$A27))/2)+Q$23/2,0) -> 6 | R16: =ROUND((R$23*POWER(0.99,14*(10-$A27))/2)+R$23/2,0) -> 6 | S16: =S$23 -> 3 | T16: =ROUNDUP(((T$23*POWER(0.99,14*(10-$A60))/2)+T$23/2)/5,0)*5 -> 50 | U16: =ROUND((U$23*POWER(0.99,14*(10-$A60))/2)+U$23/2,0) -> 1 | V16: =ROUND((V$23*POWER(0.99,14*(10-$A60))/2)+V$23/2,0) -> 9 | W16: =ROUND((W$23*POWER(0.99,14*(10-$A60))/2)+W$23/2,0) -> 4 | X16: =ROUND((X$23*POWER(0.99,14*(10-$A60))/2)+X$23/2,0) -> 7 | Y16: =Y$23 -> 2 | Z16: =ROUNDUP(((Z$23*POWER(0.99,14*(10-$A60))/2)+Z$23/2)/5,0)*5 -> 45 | AA16: =ROUND((AA$23*POWER(0.99,14*(10-$A60))/2)+AA$23/2,0) -> 1 | AB16: =ROUND((AB$23*POWER(0.99,14*(10-$A60))/2)+AB$23/2,0) -> 10 | AC16: =ROUND((AC$23*POWER(0.99,14*(10-$A60))/2)+AC$23/2,0) -> 6 | AD16: =ROUND((AD$23*POWER(0.99,14*(10-$A60))/2)+AD$23/2,0) -> 6 | AE16: =AE$23 -> 1 | AF16: =ROUNDUP(((AF$23*POWER(0.99,14*(10-$A60))/2)+AF$23/2)/5,0)*5 -> 45 | AG16: =ROUND((AG$23*POWER(0.99,14*(10-$A60))/2)+AG$23/2,0) -> 0 | AH16: =ROUND((AH$23*POWER(0.99,14*(10-$A60))/2)+AH$23/2,0) -> 8 | AI16: =ROUND((AI$23*POWER(0.99,14*(10-$A60))/2)+AI$23/2,0) -> 8 | AJ16: =ROUND((AJ$23*POWER(0.99,14*(10-$A60))/2)+AJ$23/2,0) -> 8 | AK16: =AK$23 -> 2
A17: 4 | B17: =ROUNDUP(((B$23*POWER(0.99,14*(10-$A28))/2)+B$23/2)/5,0)*5 -> 50 | C17: =ROUND((C$23*POWER(0.99,14*(10-$A28))/2)+C$23/2,0) -> 8 | D17: =ROUND((D$23*POWER(0.99,14*(10-$A28))/2)+D$23/2,0) -> 5 | E17: =ROUND((E$23*POWER(0.99,14*(10-$A28))/2)+E$23/2,0) -> 9 | F17: =ROUND((F$23*POWER(0.99,14*(10-$A28))/2)+F$23/2,0) -> 10 | G17: =G$23 -> 1 | H17: =ROUNDUP(((H$23*POWER(0.99,14*(10-$A28))/2)+H$23/2)/5,0)*5 -> 50 | I17: =ROUND((I$23*POWER(0.99,14*(10-$A28))/2)+I$23/2,0) -> 9 | J17: =ROUND((J$23*POWER(0.99,14*(10-$A28))/2)+J$23/2,0) -> 1 | K17: =ROUND((K$23*POWER(0.99,14*(10-$A28))/2)+K$23/2,0) -> 4 | L17: =ROUND((L$23*POWER(0.99,14*(10-$A28))/2)+L$23/2,0) -> 4 | M17: =M$23 -> 1 | N17: =ROUNDUP(((N$23*POWER(0.99,14*(10-$A28))/2)+N$23/2)/5,0)*5 -> 45 | O17: =ROUND((O$23*POWER(0.99,14*(10-$A28))/2)+O$23/2,0) -> 7 | P17: =ROUND((P$23*POWER(0.99,14*(10-$A28))/2)+P$23/2,0) -> 4 | Q17: =ROUND((Q$23*POWER(0.99,14*(10-$A28))/2)+Q$23/2,0) -> 6 | R17: =ROUND((R$23*POWER(0.99,14*(10-$A28))/2)+R$23/2,0) -> 6 | S17: =S$23 -> 3 | T17: =ROUNDUP(((T$23*POWER(0.99,14*(10-$A61))/2)+T$23/2)/5,0)*5 -> 55 | U17: =ROUND((U$23*POWER(0.99,14*(10-$A61))/2)+U$23/2,0) -> 1 | V17: =ROUND((V$23*POWER(0.99,14*(10-$A61))/2)+V$23/2,0) -> 9 | W17: =ROUND((W$23*POWER(0.99,14*(10-$A61))/2)+W$23/2,0) -> 4 | X17: =ROUND((X$23*POWER(0.99,14*(10-$A61))/2)+X$23/2,0) -> 7 | Y17: =Y$23 -> 2 | Z17: =ROUNDUP(((Z$23*POWER(0.99,14*(10-$A61))/2)+Z$23/2)/5,0)*5 -> 45 | AA17: =ROUND((AA$23*POWER(0.99,14*(10-$A61))/2)+AA$23/2,0) -> 1 | AB17: =ROUND((AB$23*POWER(0.99,14*(10-$A61))/2)+AB$23/2,0) -> 10 | AC17: =ROUND((AC$23*POWER(0.99,14*(10-$A61))/2)+AC$23/2,0) -> 6 | AD17: =ROUND((AD$23*POWER(0.99,14*(10-$A61))/2)+AD$23/2,0) -> 6 | AE17: =AE$23 -> 1 | AF17: =ROUNDUP(((AF$23*POWER(0.99,14*(10-$A61))/2)+AF$23/2)/5,0)*5 -> 50 | AG17: =ROUND((AG$23*POWER(0.99,14*(10-$A61))/2)+AG$23/2,0) -> 0 | AH17: =ROUND((AH$23*POWER(0.99,14*(10-$A61))/2)+AH$23/2,0) -> 8 | AI17: =ROUND((AI$23*POWER(0.99,14*(10-$A61))/2)+AI$23/2,0) -> 9 | AJ17: =ROUND((AJ$23*POWER(0.99,14*(10-$A61))/2)+AJ$23/2,0) -> 9 | AK17: =AK$23 -> 2
A18: 5 | B18: =ROUNDUP(((B$23*POWER(0.99,14*(10-$A29))/2)+B$23/2)/5,0)*5 -> 50 | C18: =ROUND((C$23*POWER(0.99,14*(10-$A29))/2)+C$23/2,0) -> 8 | D18: =ROUND((D$23*POWER(0.99,14*(10-$A29))/2)+D$23/2,0) -> 5 | E18: =ROUND((E$23*POWER(0.99,14*(10-$A29))/2)+E$23/2,0) -> 10 | F18: =ROUND((F$23*POWER(0.99,14*(10-$A29))/2)+F$23/2,0) -> 10 | G18: =G$23 -> 1 | H18: =ROUNDUP(((H$23*POWER(0.99,14*(10-$A29))/2)+H$23/2)/5,0)*5 -> 50 | I18: =ROUND((I$23*POWER(0.99,14*(10-$A29))/2)+I$23/2,0) -> 9 | J18: =ROUND((J$23*POWER(0.99,14*(10-$A29))/2)+J$23/2,0) -> 1 | K18: =ROUND((K$23*POWER(0.99,14*(10-$A29))/2)+K$23/2,0) -> 4 | L18: =ROUND((L$23*POWER(0.99,14*(10-$A29))/2)+L$23/2,0) -> 4 | M18: =M$23 -> 1 | N18: =ROUNDUP(((N$23*POWER(0.99,14*(10-$A29))/2)+N$23/2)/5,0)*5 -> 45 | O18: =ROUND((O$23*POWER(0.99,14*(10-$A29))/2)+O$23/2,0) -> 7 | P18: =ROUND((P$23*POWER(0.99,14*(10-$A29))/2)+P$23/2,0) -> 4 | Q18: =ROUND((Q$23*POWER(0.99,14*(10-$A29))/2)+Q$23/2,0) -> 7 | R18: =ROUND((R$23*POWER(0.99,14*(10-$A29))/2)+R$23/2,0) -> 7 | S18: =S$23 -> 3 | T18: =ROUNDUP(((T$23*POWER(0.99,14*(10-$A62))/2)+T$23/2)/5,0)*5 -> 55 | U18: =ROUND((U$23*POWER(0.99,14*(10-$A62))/2)+U$23/2,0) -> 1 | V18: =ROUND((V$23*POWER(0.99,14*(10-$A62))/2)+V$23/2,0) -> 10 | W18: =ROUND((W$23*POWER(0.99,14*(10-$A62))/2)+W$23/2,0) -> 4 | X18: =ROUND((X$23*POWER(0.99,14*(10-$A62))/2)+X$23/2,0) -> 7 | Y18: =Y$23 -> 2 | Z18: =ROUNDUP(((Z$23*POWER(0.99,14*(10-$A62))/2)+Z$23/2)/5,0)*5 -> 45 | AA18: =ROUND((AA$23*POWER(0.99,14*(10-$A62))/2)+AA$23/2,0) -> 1 | AB18: =ROUND((AB$23*POWER(0.99,14*(10-$A62))/2)+AB$23/2,0) -> 10 | AC18: =ROUND((AC$23*POWER(0.99,14*(10-$A62))/2)+AC$23/2,0) -> 7 | AD18: =ROUND((AD$23*POWER(0.99,14*(10-$A62))/2)+AD$23/2,0) -> 7 | AE18: =AE$23 -> 1 | AF18: =ROUNDUP(((AF$23*POWER(0.99,14*(10-$A62))/2)+AF$23/2)/5,0)*5 -> 50 | AG18: =ROUND((AG$23*POWER(0.99,14*(10-$A62))/2)+AG$23/2,0) -> 0 | AH18: =ROUND((AH$23*POWER(0.99,14*(10-$A62))/2)+AH$23/2,0) -> 8 | AI18: =ROUND((AI$23*POWER(0.99,14*(10-$A62))/2)+AI$23/2,0) -> 9 | AJ18: =ROUND((AJ$23*POWER(0.99,14*(10-$A62))/2)+AJ$23/2,0) -> 9 | AK18: =AK$23 -> 2
A19: 6 | B19: =ROUNDUP(((B$23*POWER(0.99,14*(10-$A30))/2)+B$23/2)/5,0)*5 -> 55 | C19: =ROUND((C$23*POWER(0.99,14*(10-$A30))/2)+C$23/2,0) -> 9 | D19: =ROUND((D$23*POWER(0.99,14*(10-$A30))/2)+D$23/2,0) -> 5 | E19: =ROUND((E$23*POWER(0.99,14*(10-$A30))/2)+E$23/2,0) -> 10 | F19: =ROUND((F$23*POWER(0.99,14*(10-$A30))/2)+F$23/2,0) -> 11 | G19: =G$23 -> 1 | H19: =ROUNDUP(((H$23*POWER(0.99,14*(10-$A30))/2)+H$23/2)/5,0)*5 -> 55 | I19: =ROUND((I$23*POWER(0.99,14*(10-$A30))/2)+I$23/2,0) -> 9 | J19: =ROUND((J$23*POWER(0.99,14*(10-$A30))/2)+J$23/2,0) -> 2 | K19: =ROUND((K$23*POWER(0.99,14*(10-$A30))/2)+K$23/2,0) -> 5 | L19: =ROUND((L$23*POWER(0.99,14*(10-$A30))/2)+L$23/2,0) -> 5 | M19: =M$23 -> 1 | N19: =ROUNDUP(((N$23*POWER(0.99,14*(10-$A30))/2)+N$23/2)/5,0)*5 -> 50 | O19: =ROUND((O$23*POWER(0.99,14*(10-$A30))/2)+O$23/2,0) -> 8 | P19: =ROUND((P$23*POWER(0.99,14*(10-$A30))/2)+P$23/2,0) -> 4 | Q19: =ROUND((Q$23*POWER(0.99,14*(10-$A30))/2)+Q$23/2,0) -> 7 | R19: =ROUND((R$23*POWER(0.99,14*(10-$A30))/2)+R$23/2,0) -> 7 | S19: =S$23 -> 3 | T19: =ROUNDUP(((T$23*POWER(0.99,14*(10-$A63))/2)+T$23/2)/5,0)*5 -> 55 | U19: =ROUND((U$23*POWER(0.99,14*(10-$A63))/2)+U$23/2,0) -> 1 | V19: =ROUND((V$23*POWER(0.99,14*(10-$A63))/2)+V$23/2,0) -> 10 | W19: =ROUND((W$23*POWER(0.99,14*(10-$A63))/2)+W$23/2,0) -> 5 | X19: =ROUND((X$23*POWER(0.99,14*(10-$A63))/2)+X$23/2,0) -> 8 | Y19: =Y$23 -> 2 | Z19: =ROUNDUP(((Z$23*POWER(0.99,14*(10-$A63))/2)+Z$23/2)/5,0)*5 -> 50 | AA19: =ROUND((AA$23*POWER(0.99,14*(10-$A63))/2)+AA$23/2,0) -> 2 | AB19: =ROUND((AB$23*POWER(0.99,14*(10-$A63))/2)+AB$23/2,0) -> 11 | AC19: =ROUND((AC$23*POWER(0.99,14*(10-$A63))/2)+AC$23/2,0) -> 7 | AD19: =ROUND((AD$23*POWER(0.99,14*(10-$A63))/2)+AD$23/2,0) -> 7 | AE19: =AE$23 -> 1 | AF19: =ROUNDUP(((AF$23*POWER(0.99,14*(10-$A63))/2)+AF$23/2)/5,0)*5 -> 55 | AG19: =ROUND((AG$23*POWER(0.99,14*(10-$A63))/2)+AG$23/2,0) -> 0 | AH19: =ROUND((AH$23*POWER(0.99,14*(10-$A63))/2)+AH$23/2,0) -> 9 | AI19: =ROUND((AI$23*POWER(0.99,14*(10-$A63))/2)+AI$23/2,0) -> 9 | AJ19: =ROUND((AJ$23*POWER(0.99,14*(10-$A63))/2)+AJ$23/2,0) -> 9 | AK19: =AK$23 -> 2
A20: 7 | B20: =ROUNDUP(((B$23*POWER(0.99,14*(10-$A31))/2)+B$23/2)/5,0)*5 -> 55 | C20: =ROUND((C$23*POWER(0.99,14*(10-$A31))/2)+C$23/2,0) -> 9 | D20: =ROUND((D$23*POWER(0.99,14*(10-$A31))/2)+D$23/2,0) -> 6 | E20: =ROUND((E$23*POWER(0.99,14*(10-$A31))/2)+E$23/2,0) -> 11 | F20: =ROUND((F$23*POWER(0.99,14*(10-$A31))/2)+F$23/2,0) -> 12 | G20: =G$23 -> 1 | H20: =ROUNDUP(((H$23*POWER(0.99,14*(10-$A31))/2)+H$23/2)/5,0)*5 -> 55 | I20: =ROUND((I$23*POWER(0.99,14*(10-$A31))/2)+I$23/2,0) -> 10 | J20: =ROUND((J$23*POWER(0.99,14*(10-$A31))/2)+J$23/2,0) -> 2 | K20: =ROUND((K$23*POWER(0.99,14*(10-$A31))/2)+K$23/2,0) -> 5 | L20: =ROUND((L$23*POWER(0.99,14*(10-$A31))/2)+L$23/2,0) -> 5 | M20: =M$23 -> 1 | N20: =ROUNDUP(((N$23*POWER(0.99,14*(10-$A31))/2)+N$23/2)/5,0)*5 -> 50 | O20: =ROUND((O$23*POWER(0.99,14*(10-$A31))/2)+O$23/2,0) -> 8 | P20: =ROUND((P$23*POWER(0.99,14*(10-$A31))/2)+P$23/2,0) -> 4 | Q20: =ROUND((Q$23*POWER(0.99,14*(10-$A31))/2)+Q$23/2,0) -> 7 | R20: =ROUND((R$23*POWER(0.99,14*(10-$A31))/2)+R$23/2,0) -> 7 | S20: =S$23 -> 3 | T20: =ROUNDUP(((T$23*POWER(0.99,14*(10-$A64))/2)+T$23/2)/5,0)*5 -> 60 | U20: =ROUND((U$23*POWER(0.99,14*(10-$A64))/2)+U$23/2,0) -> 1 | V20: =ROUND((V$23*POWER(0.99,14*(10-$A64))/2)+V$23/2,0) -> 11 | W20: =ROUND((W$23*POWER(0.99,14*(10-$A64))/2)+W$23/2,0) -> 5 | X20: =ROUND((X$23*POWER(0.99,14*(10-$A64))/2)+X$23/2,0) -> 8 | Y20: =Y$23 -> 2 | Z20: =ROUNDUP(((Z$23*POWER(0.99,14*(10-$A64))/2)+Z$23/2)/5,0)*5 -> 50 | AA20: =ROUND((AA$23*POWER(0.99,14*(10-$A64))/2)+AA$23/2,0) -> 2 | AB20: =ROUND((AB$23*POWER(0.99,14*(10-$A64))/2)+AB$23/2,0) -> 12 | AC20: =ROUND((AC$23*POWER(0.99,14*(10-$A64))/2)+AC$23/2,0) -> 7 | AD20: =ROUND((AD$23*POWER(0.99,14*(10-$A64))/2)+AD$23/2,0) -> 7 | AE20: =AE$23 -> 1 | AF20: =ROUNDUP(((AF$23*POWER(0.99,14*(10-$A64))/2)+AF$23/2)/5,0)*5 -> 55 | AG20: =ROUND((AG$23*POWER(0.99,14*(10-$A64))/2)+AG$23/2,0) -> 0 | AH20: =ROUND((AH$23*POWER(0.99,14*(10-$A64))/2)+AH$23/2,0) -> 9 | AI20: =ROUND((AI$23*POWER(0.99,14*(10-$A64))/2)+AI$23/2,0) -> 10 | AJ20: =ROUND((AJ$23*POWER(0.99,14*(10-$A64))/2)+AJ$23/2,0) -> 10 | AK20: =AK$23 -> 2
A21: 8 | B21: =ROUNDUP(((B$23*POWER(0.99,14*(10-$A32))/2)+B$23/2)/5,0)*5 -> 60 | C21: =ROUND((C$23*POWER(0.99,14*(10-$A32))/2)+C$23/2,0) -> 10 | D21: =ROUND((D$23*POWER(0.99,14*(10-$A32))/2)+D$23/2,0) -> 6 | E21: =ROUND((E$23*POWER(0.99,14*(10-$A32))/2)+E$23/2,0) -> 11 | F21: =ROUND((F$23*POWER(0.99,14*(10-$A32))/2)+F$23/2,0) -> 12 | G21: =G$23 -> 1 | H21: =ROUNDUP(((H$23*POWER(0.99,14*(10-$A32))/2)+H$23/2)/5,0)*5 -> 60 | I21: =ROUND((I$23*POWER(0.99,14*(10-$A32))/2)+I$23/2,0) -> 11 | J21: =ROUND((J$23*POWER(0.99,14*(10-$A32))/2)+J$23/2,0) -> 2 | K21: =ROUND((K$23*POWER(0.99,14*(10-$A32))/2)+K$23/2,0) -> 5 | L21: =ROUND((L$23*POWER(0.99,14*(10-$A32))/2)+L$23/2,0) -> 5 | M21: =M$23 -> 1 | N21: =ROUNDUP(((N$23*POWER(0.99,14*(10-$A32))/2)+N$23/2)/5,0)*5 -> 55 | O21: =ROUND((O$23*POWER(0.99,14*(10-$A32))/2)+O$23/2,0) -> 9 | P21: =ROUND((P$23*POWER(0.99,14*(10-$A32))/2)+P$23/2,0) -> 4 | Q21: =ROUND((Q$23*POWER(0.99,14*(10-$A32))/2)+Q$23/2,0) -> 8 | R21: =ROUND((R$23*POWER(0.99,14*(10-$A32))/2)+R$23/2,0) -> 8 | S21: =S$23 -> 3 | T21: =ROUNDUP(((T$23*POWER(0.99,14*(10-$A65))/2)+T$23/2)/5,0)*5 -> 65 | U21: =ROUND((U$23*POWER(0.99,14*(10-$A65))/2)+U$23/2,0) -> 1 | V21: =ROUND((V$23*POWER(0.99,14*(10-$A65))/2)+V$23/2,0) -> 11 | W21: =ROUND((W$23*POWER(0.99,14*(10-$A65))/2)+W$23/2,0) -> 5 | X21: =ROUND((X$23*POWER(0.99,14*(10-$A65))/2)+X$23/2,0) -> 9 | Y21: =Y$23 -> 2 | Z21: =ROUNDUP(((Z$23*POWER(0.99,14*(10-$A65))/2)+Z$23/2)/5,0)*5 -> 55 | AA21: =ROUND((AA$23*POWER(0.99,14*(10-$A65))/2)+AA$23/2,0) -> 2 | AB21: =ROUND((AB$23*POWER(0.99,14*(10-$A65))/2)+AB$23/2,0) -> 12 | AC21: =ROUND((AC$23*POWER(0.99,14*(10-$A65))/2)+AC$23/2,0) -> 8 | AD21: =ROUND((AD$23*POWER(0.99,14*(10-$A65))/2)+AD$23/2,0) -> 8 | AE21: =AE$23 -> 1 | AF21: =ROUNDUP(((AF$23*POWER(0.99,14*(10-$A65))/2)+AF$23/2)/5,0)*5 -> 60 | AG21: =ROUND((AG$23*POWER(0.99,14*(10-$A65))/2)+AG$23/2,0) -> 0 | AH21: =ROUND((AH$23*POWER(0.99,14*(10-$A65))/2)+AH$23/2,0) -> 10 | AI21: =ROUND((AI$23*POWER(0.99,14*(10-$A65))/2)+AI$23/2,0) -> 11 | AJ21: =ROUND((AJ$23*POWER(0.99,14*(10-$A65))/2)+AJ$23/2,0) -> 11 | AK21: =AK$23 -> 2
A22: 9 | B22: =ROUNDUP(((B$23*POWER(0.99,14*(10-$A33))/2)+B$23/2)/5,0)*5 -> 65 | C22: =ROUND((C$23*POWER(0.99,14*(10-$A33))/2)+C$23/2,0) -> 10 | D22: =ROUND((D$23*POWER(0.99,14*(10-$A33))/2)+D$23/2,0) -> 7 | E22: =ROUND((E$23*POWER(0.99,14*(10-$A33))/2)+E$23/2,0) -> 12 | F22: =ROUND((F$23*POWER(0.99,14*(10-$A33))/2)+F$23/2,0) -> 13 | G22: =G$23 -> 1 | H22: =ROUNDUP(((H$23*POWER(0.99,14*(10-$A33))/2)+H$23/2)/5,0)*5 -> 65 | I22: =ROUND((I$23*POWER(0.99,14*(10-$A33))/2)+I$23/2,0) -> 11 | J22: =ROUND((J$23*POWER(0.99,14*(10-$A33))/2)+J$23/2,0) -> 2 | K22: =ROUND((K$23*POWER(0.99,14*(10-$A33))/2)+K$23/2,0) -> 6 | L22: =ROUND((L$23*POWER(0.99,14*(10-$A33))/2)+L$23/2,0) -> 6 | M22: =M$23 -> 1 | N22: =ROUNDUP(((N$23*POWER(0.99,14*(10-$A33))/2)+N$23/2)/5,0)*5 -> 60 | O22: =ROUND((O$23*POWER(0.99,14*(10-$A33))/2)+O$23/2,0) -> 9 | P22: =ROUND((P$23*POWER(0.99,14*(10-$A33))/2)+P$23/2,0) -> 5 | Q22: =ROUND((Q$23*POWER(0.99,14*(10-$A33))/2)+Q$23/2,0) -> 8 | R22: =ROUND((R$23*POWER(0.99,14*(10-$A33))/2)+R$23/2,0) -> 8 | S22: =S$23 -> 3 | T22: =ROUNDUP(((T$23*POWER(0.99,14*(10-$A66))/2)+T$23/2)/5,0)*5 -> 70 | U22: =ROUND((U$23*POWER(0.99,14*(10-$A66))/2)+U$23/2,0) -> 1 | V22: =ROUND((V$23*POWER(0.99,14*(10-$A66))/2)+V$23/2,0) -> 12 | W22: =ROUND((W$23*POWER(0.99,14*(10-$A66))/2)+W$23/2,0) -> 6 | X22: =ROUND((X$23*POWER(0.99,14*(10-$A66))/2)+X$23/2,0) -> 9 | Y22: =Y$23 -> 2 | Z22: =ROUNDUP(((Z$23*POWER(0.99,14*(10-$A66))/2)+Z$23/2)/5,0)*5 -> 60 | AA22: =ROUND((AA$23*POWER(0.99,14*(10-$A66))/2)+AA$23/2,0) -> 2 | AB22: =ROUND((AB$23*POWER(0.99,14*(10-$A66))/2)+AB$23/2,0) -> 13 | AC22: =ROUND((AC$23*POWER(0.99,14*(10-$A66))/2)+AC$23/2,0) -> 8 | AD22: =ROUND((AD$23*POWER(0.99,14*(10-$A66))/2)+AD$23/2,0) -> 8 | AE22: =AE$23 -> 1 | AF22: =ROUNDUP(((AF$23*POWER(0.99,14*(10-$A66))/2)+AF$23/2)/5,0)*5 -> 65 | AG22: =ROUND((AG$23*POWER(0.99,14*(10-$A66))/2)+AG$23/2,0) -> 0 | AH22: =ROUND((AH$23*POWER(0.99,14*(10-$A66))/2)+AH$23/2,0) -> 10 | AI22: =ROUND((AI$23*POWER(0.99,14*(10-$A66))/2)+AI$23/2,0) -> 11 | AJ22: =ROUND((AJ$23*POWER(0.99,14*(10-$A66))/2)+AJ$23/2,0) -> 11 | AK22: =AK$23 -> 2
A23: 10 | B23: 65 | C23: 11 | D23: 7 | E23: 13 | F23: 14 | G23: 1 | H23: 65 | I23: 12 | J23: 2 | K23: 6 | L23: 6 | M23: 1 | N23: 60 | O23: 10 | P23: 5 | Q23: 9 | R23: 9 | S23: 3 | T23: 70 | U23: 1 | V23: 13 | W23: 6 | X23: 10 | Y23: 2 | Z23: 60 | AA23: 2 | AB23: 14 | AC23: 9 | AD23: 9 | AE23: 1 | AF23: 65 | AG23: 0 | AH23: 11 | AI23: 12 | AJ23: 12 | AK23: 2
A24: Clairvoyant / Dark | B24: Orb | H24: Tarot Cards | N24: Pendulum | T24: Athame | Z24: Chalice | AF24: Scythe
A25: 1 | B25: =ROUNDUP(((B$34*POWER(0.99,14*(10-$A47))/2)+B$34/2)/5,0)*5 -> 40 | C25: =ROUND((C$34*POWER(0.99,14*(10-$A47))/2)+C$34/2,0) -> 4 | D25: =ROUND((D$34*POWER(0.99,14*(10-$A47))/2)+D$34/2,0) -> 8 | E25: =ROUND((E$34*POWER(0.99,14*(10-$A47))/2)+E$34/2,0) -> 3 | F25: =ROUND((F$34*POWER(0.99,14*(10-$A47))/2)+F$34/2,0) -> 10 | G25: =G$34 -> 1 | H25: =ROUNDUP(((H$34*POWER(0.99,14*(10-$A47))/2)+H$34/2)/5,0)*5 -> 45 | I25: =ROUND((I$34*POWER(0.99,14*(10-$A47))/2)+I$34/2,0) -> 3 | J25: =ROUND((J$34*POWER(0.99,14*(10-$A47))/2)+J$34/2,0) -> 7 | K25: =ROUND((K$34*POWER(0.99,14*(10-$A47))/2)+K$34/2,0) -> 6 | L25: =ROUND((L$34*POWER(0.99,14*(10-$A47))/2)+L$34/2,0) -> 6 | M25: =M$34 -> 2 | N25: =ROUNDUP(((N$34*POWER(0.99,14*(10-$A47))/2)+N$34/2)/5,0)*5 -> 45 | O25: =ROUND((O$34*POWER(0.99,14*(10-$A47))/2)+O$34/2,0) -> 3 | P25: =ROUND((P$34*POWER(0.99,14*(10-$A47))/2)+P$34/2,0) -> 6 | Q25: =ROUND((Q$34*POWER(0.99,14*(10-$A47))/2)+Q$34/2,0) -> 8 | R25: =ROUND((R$34*POWER(0.99,14*(10-$A47))/2)+R$34/2,0) -> 6 | S25: =S$34 -> 1 | T25: =ROUNDUP(((T$34*POWER(0.99,14*(10-$A36))/2)+T$34/2)/5,0)*5 -> 45 | U25: =ROUND((U$34*POWER(0.99,14*(10-$A36))/2)+U$34/2,0) -> 4 | V25: =ROUND((V$34*POWER(0.99,14*(10-$A36))/2)+V$34/2,0) -> 4 | W25: =ROUND((W$34*POWER(0.99,14*(10-$A36))/2)+W$34/2,0) -> 10 | X25: =ROUND((X$34*POWER(0.99,14*(10-$A36))/2)+X$34/2,0) -> 6 | Y25: =Y$34 -> 2 | Z25: =ROUNDUP(((Z$34*POWER(0.99,14*(10-$A36))/2)+Z$34/2)/5,0)*5 -> 45 | AA25: =ROUND((AA$34*POWER(0.99,14*(10-$A36))/2)+AA$34/2,0) -> 0 | AB25: =ROUND((AB$34*POWER(0.99,14*(10-$A36))/2)+AB$34/2,0) -> 8 | AC25: =ROUND((AC$34*POWER(0.99,14*(10-$A36))/2)+AC$34/2,0) -> 10 | AD25: =ROUND((AD$34*POWER(0.99,14*(10-$A36))/2)+AD$34/2,0) -> 10 | AE25: =AE$34 -> 1 | AF25: =ROUNDUP(((AF$34*POWER(0.99,14*(10-$A36))/2)+AF$34/2)/5,0)*5 -> 45 | AG25: =ROUND((AG$34*POWER(0.99,14*(10-$A36))/2)+AG$34/2,0) -> 5 | AH25: =ROUND((AH$34*POWER(0.99,14*(10-$A36))/2)+AH$34/2,0) -> 8 | AI25: =ROUND((AI$34*POWER(0.99,14*(10-$A36))/2)+AI$34/2,0) -> 6 | AJ25: =ROUND((AJ$34*POWER(0.99,14*(10-$A36))/2)+AJ$34/2,0) -> 6 | AK25: =AK$34 -> 2
A26: 2 | B26: =ROUNDUP(((B$34*POWER(0.99,14*(10-$A48))/2)+B$34/2)/5,0)*5 -> 40 | C26: =ROUND((C$34*POWER(0.99,14*(10-$A48))/2)+C$34/2,0) -> 5 | D26: =ROUND((D$34*POWER(0.99,14*(10-$A48))/2)+D$34/2,0) -> 9 | E26: =ROUND((E$34*POWER(0.99,14*(10-$A48))/2)+E$34/2,0) -> 3 | F26: =ROUND((F$34*POWER(0.99,14*(10-$A48))/2)+F$34/2,0) -> 11 | G26: =G$34 -> 1 | H26: =ROUNDUP(((H$34*POWER(0.99,14*(10-$A48))/2)+H$34/2)/5,0)*5 -> 45 | I26: =ROUND((I$34*POWER(0.99,14*(10-$A48))/2)+I$34/2,0) -> 3 | J26: =ROUND((J$34*POWER(0.99,14*(10-$A48))/2)+J$34/2,0) -> 7 | K26: =ROUND((K$34*POWER(0.99,14*(10-$A48))/2)+K$34/2,0) -> 6 | L26: =ROUND((L$34*POWER(0.99,14*(10-$A48))/2)+L$34/2,0) -> 7 | M26: =M$34 -> 2 | N26: =ROUNDUP(((N$34*POWER(0.99,14*(10-$A48))/2)+N$34/2)/5,0)*5 -> 45 | O26: =ROUND((O$34*POWER(0.99,14*(10-$A48))/2)+O$34/2,0) -> 3 | P26: =ROUND((P$34*POWER(0.99,14*(10-$A48))/2)+P$34/2,0) -> 6 | Q26: =ROUND((Q$34*POWER(0.99,14*(10-$A48))/2)+Q$34/2,0) -> 8 | R26: =ROUND((R$34*POWER(0.99,14*(10-$A48))/2)+R$34/2,0) -> 6 | S26: =S$34 -> 1 | T26: =ROUNDUP(((T$34*POWER(0.99,14*(10-$A37))/2)+T$34/2)/5,0)*5 -> 45 | U26: =ROUND((U$34*POWER(0.99,14*(10-$A37))/2)+U$34/2,0) -> 4 | V26: =ROUND((V$34*POWER(0.99,14*(10-$A37))/2)+V$34/2,0) -> 5 | W26: =ROUND((W$34*POWER(0.99,14*(10-$A37))/2)+W$34/2,0) -> 10 | X26: =ROUND((X$34*POWER(0.99,14*(10-$A37))/2)+X$34/2,0) -> 7 | Y26: =Y$34 -> 2 | Z26: =ROUNDUP(((Z$34*POWER(0.99,14*(10-$A37))/2)+Z$34/2)/5,0)*5 -> 45 | AA26: =ROUND((AA$34*POWER(0.99,14*(10-$A37))/2)+AA$34/2,0) -> 0 | AB26: =ROUND((AB$34*POWER(0.99,14*(10-$A37))/2)+AB$34/2,0) -> 9 | AC26: =ROUND((AC$34*POWER(0.99,14*(10-$A37))/2)+AC$34/2,0) -> 10 | AD26: =ROUND((AD$34*POWER(0.99,14*(10-$A37))/2)+AD$34/2,0) -> 10 | AE26: =AE$34 -> 1 | AF26: =ROUNDUP(((AF$34*POWER(0.99,14*(10-$A37))/2)+AF$34/2)/5,0)*5 -> 50 | AG26: =ROUND((AG$34*POWER(0.99,14*(10-$A37))/2)+AG$34/2,0) -> 5 | AH26: =ROUND((AH$34*POWER(0.99,14*(10-$A37))/2)+AH$34/2,0) -> 9 | AI26: =ROUND((AI$34*POWER(0.99,14*(10-$A37))/2)+AI$34/2,0) -> 6 | AJ26: =ROUND((AJ$34*POWER(0.99,14*(10-$A37))/2)+AJ$34/2,0) -> 6 | AK26: =AK$34 -> 2
A27: 3 | B27: =ROUNDUP(((B$34*POWER(0.99,14*(10-$A49))/2)+B$34/2)/5,0)*5 -> 45 | C27: =ROUND((C$34*POWER(0.99,14*(10-$A49))/2)+C$34/2,0) -> 5 | D27: =ROUND((D$34*POWER(0.99,14*(10-$A49))/2)+D$34/2,0) -> 9 | E27: =ROUND((E$34*POWER(0.99,14*(10-$A49))/2)+E$34/2,0) -> 3 | F27: =ROUND((F$34*POWER(0.99,14*(10-$A49))/2)+F$34/2,0) -> 11 | G27: =G$34 -> 1 | H27: =ROUNDUP(((H$34*POWER(0.99,14*(10-$A49))/2)+H$34/2)/5,0)*5 -> 45 | I27: =ROUND((I$34*POWER(0.99,14*(10-$A49))/2)+I$34/2,0) -> 3 | J27: =ROUND((J$34*POWER(0.99,14*(10-$A49))/2)+J$34/2,0) -> 8 | K27: =ROUND((K$34*POWER(0.99,14*(10-$A49))/2)+K$34/2,0) -> 6 | L27: =ROUND((L$34*POWER(0.99,14*(10-$A49))/2)+L$34/2,0) -> 7 | M27: =M$34 -> 2 | N27: =ROUNDUP(((N$34*POWER(0.99,14*(10-$A49))/2)+N$34/2)/5,0)*5 -> 45 | O27: =ROUND((O$34*POWER(0.99,14*(10-$A49))/2)+O$34/2,0) -> 3 | P27: =ROUND((P$34*POWER(0.99,14*(10-$A49))/2)+P$34/2,0) -> 6 | Q27: =ROUND((Q$34*POWER(0.99,14*(10-$A49))/2)+Q$34/2,0) -> 8 | R27: =ROUND((R$34*POWER(0.99,14*(10-$A49))/2)+R$34/2,0) -> 6 | S27: =S$34 -> 1 | T27: =ROUNDUP(((T$34*POWER(0.99,14*(10-$A38))/2)+T$34/2)/5,0)*5 -> 45 | U27: =ROUND((U$34*POWER(0.99,14*(10-$A38))/2)+U$34/2,0) -> 4 | V27: =ROUND((V$34*POWER(0.99,14*(10-$A38))/2)+V$34/2,0) -> 5 | W27: =ROUND((W$34*POWER(0.99,14*(10-$A38))/2)+W$34/2,0) -> 10 | X27: =ROUND((X$34*POWER(0.99,14*(10-$A38))/2)+X$34/2,0) -> 7 | Y27: =Y$34 -> 2 | Z27: =ROUNDUP(((Z$34*POWER(0.99,14*(10-$A38))/2)+Z$34/2)/5,0)*5 -> 45 | AA27: =ROUND((AA$34*POWER(0.99,14*(10-$A38))/2)+AA$34/2,0) -> 0 | AB27: =ROUND((AB$34*POWER(0.99,14*(10-$A38))/2)+AB$34/2,0) -> 9 | AC27: =ROUND((AC$34*POWER(0.99,14*(10-$A38))/2)+AC$34/2,0) -> 10 | AD27: =ROUND((AD$34*POWER(0.99,14*(10-$A38))/2)+AD$34/2,0) -> 10 | AE27: =AE$34 -> 1 | AF27: =ROUNDUP(((AF$34*POWER(0.99,14*(10-$A38))/2)+AF$34/2)/5,0)*5 -> 50 | AG27: =ROUND((AG$34*POWER(0.99,14*(10-$A38))/2)+AG$34/2,0) -> 5 | AH27: =ROUND((AH$34*POWER(0.99,14*(10-$A38))/2)+AH$34/2,0) -> 9 | AI27: =ROUND((AI$34*POWER(0.99,14*(10-$A38))/2)+AI$34/2,0) -> 6 | AJ27: =ROUND((AJ$34*POWER(0.99,14*(10-$A38))/2)+AJ$34/2,0) -> 6 | AK27: =AK$34 -> 2
A28: 4 | B28: =ROUNDUP(((B$34*POWER(0.99,14*(10-$A50))/2)+B$34/2)/5,0)*5 -> 45 | C28: =ROUND((C$34*POWER(0.99,14*(10-$A50))/2)+C$34/2,0) -> 5 | D28: =ROUND((D$34*POWER(0.99,14*(10-$A50))/2)+D$34/2,0) -> 9 | E28: =ROUND((E$34*POWER(0.99,14*(10-$A50))/2)+E$34/2,0) -> 4 | F28: =ROUND((F$34*POWER(0.99,14*(10-$A50))/2)+F$34/2,0) -> 11 | G28: =G$34 -> 1 | H28: =ROUNDUP(((H$34*POWER(0.99,14*(10-$A50))/2)+H$34/2)/5,0)*5 -> 50 | I28: =ROUND((I$34*POWER(0.99,14*(10-$A50))/2)+I$34/2,0) -> 4 | J28: =ROUND((J$34*POWER(0.99,14*(10-$A50))/2)+J$34/2,0) -> 8 | K28: =ROUND((K$34*POWER(0.99,14*(10-$A50))/2)+K$34/2,0) -> 6 | L28: =ROUND((L$34*POWER(0.99,14*(10-$A50))/2)+L$34/2,0) -> 7 | M28: =M$34 -> 2 | N28: =ROUNDUP(((N$34*POWER(0.99,14*(10-$A50))/2)+N$34/2)/5,0)*5 -> 50 | O28: =ROUND((O$34*POWER(0.99,14*(10-$A50))/2)+O$34/2,0) -> 4 | P28: =ROUND((P$34*POWER(0.99,14*(10-$A50))/2)+P$34/2,0) -> 6 | Q28: =ROUND((Q$34*POWER(0.99,14*(10-$A50))/2)+Q$34/2,0) -> 9 | R28: =ROUND((R$34*POWER(0.99,14*(10-$A50))/2)+R$34/2,0) -> 6 | S28: =S$34 -> 1 | T28: =ROUNDUP(((T$34*POWER(0.99,14*(10-$A39))/2)+T$34/2)/5,0)*5 -> 50 | U28: =ROUND((U$34*POWER(0.99,14*(10-$A39))/2)+U$34/2,0) -> 4 | V28: =ROUND((V$34*POWER(0.99,14*(10-$A39))/2)+V$34/2,0) -> 5 | W28: =ROUND((W$34*POWER(0.99,14*(10-$A39))/2)+W$34/2,0) -> 11 | X28: =ROUND((X$34*POWER(0.99,14*(10-$A39))/2)+X$34/2,0) -> 7 | Y28: =Y$34 -> 2 | Z28: =ROUNDUP(((Z$34*POWER(0.99,14*(10-$A39))/2)+Z$34/2)/5,0)*5 -> 50 | AA28: =ROUND((AA$34*POWER(0.99,14*(10-$A39))/2)+AA$34/2,0) -> 0 | AB28: =ROUND((AB$34*POWER(0.99,14*(10-$A39))/2)+AB$34/2,0) -> 9 | AC28: =ROUND((AC$34*POWER(0.99,14*(10-$A39))/2)+AC$34/2,0) -> 11 | AD28: =ROUND((AD$34*POWER(0.99,14*(10-$A39))/2)+AD$34/2,0) -> 11 | AE28: =AE$34 -> 1 | AF28: =ROUNDUP(((AF$34*POWER(0.99,14*(10-$A39))/2)+AF$34/2)/5,0)*5 -> 55 | AG28: =ROUND((AG$34*POWER(0.99,14*(10-$A39))/2)+AG$34/2,0) -> 6 | AH28: =ROUND((AH$34*POWER(0.99,14*(10-$A39))/2)+AH$34/2,0) -> 9 | AI28: =ROUND((AI$34*POWER(0.99,14*(10-$A39))/2)+AI$34/2,0) -> 6 | AJ28: =ROUND((AJ$34*POWER(0.99,14*(10-$A39))/2)+AJ$34/2,0) -> 6 | AK28: =AK$34 -> 2
A29: 5 | B29: =ROUNDUP(((B$34*POWER(0.99,14*(10-$A51))/2)+B$34/2)/5,0)*5 -> 45 | C29: =ROUND((C$34*POWER(0.99,14*(10-$A51))/2)+C$34/2,0) -> 5 | D29: =ROUND((D$34*POWER(0.99,14*(10-$A51))/2)+D$34/2,0) -> 10 | E29: =ROUND((E$34*POWER(0.99,14*(10-$A51))/2)+E$34/2,0) -> 4 | F29: =ROUND((F$34*POWER(0.99,14*(10-$A51))/2)+F$34/2,0) -> 12 | G29: =G$34 -> 1 | H29: =ROUNDUP(((H$34*POWER(0.99,14*(10-$A51))/2)+H$34/2)/5,0)*5 -> 50 | I29: =ROUND((I$34*POWER(0.99,14*(10-$A51))/2)+I$34/2,0) -> 4 | J29: =ROUND((J$34*POWER(0.99,14*(10-$A51))/2)+J$34/2,0) -> 8 | K29: =ROUND((K$34*POWER(0.99,14*(10-$A51))/2)+K$34/2,0) -> 7 | L29: =ROUND((L$34*POWER(0.99,14*(10-$A51))/2)+L$34/2,0) -> 7 | M29: =M$34 -> 2 | N29: =ROUNDUP(((N$34*POWER(0.99,14*(10-$A51))/2)+N$34/2)/5,0)*5 -> 50 | O29: =ROUND((O$34*POWER(0.99,14*(10-$A51))/2)+O$34/2,0) -> 4 | P29: =ROUND((P$34*POWER(0.99,14*(10-$A51))/2)+P$34/2,0) -> 7 | Q29: =ROUND((Q$34*POWER(0.99,14*(10-$A51))/2)+Q$34/2,0) -> 9 | R29: =ROUND((R$34*POWER(0.99,14*(10-$A51))/2)+R$34/2,0) -> 7 | S29: =S$34 -> 1 | T29: =ROUNDUP(((T$34*POWER(0.99,14*(10-$A40))/2)+T$34/2)/5,0)*5 -> 50 | U29: =ROUND((U$34*POWER(0.99,14*(10-$A40))/2)+U$34/2,0) -> 4 | V29: =ROUND((V$34*POWER(0.99,14*(10-$A40))/2)+V$34/2,0) -> 5 | W29: =ROUND((W$34*POWER(0.99,14*(10-$A40))/2)+W$34/2,0) -> 11 | X29: =ROUND((X$34*POWER(0.99,14*(10-$A40))/2)+X$34/2,0) -> 7 | Y29: =Y$34 -> 2 | Z29: =ROUNDUP(((Z$34*POWER(0.99,14*(10-$A40))/2)+Z$34/2)/5,0)*5 -> 50 | AA29: =ROUND((AA$34*POWER(0.99,14*(10-$A40))/2)+AA$34/2,0) -> 0 | AB29: =ROUND((AB$34*POWER(0.99,14*(10-$A40))/2)+AB$34/2,0) -> 10 | AC29: =ROUND((AC$34*POWER(0.99,14*(10-$A40))/2)+AC$34/2,0) -> 11 | AD29: =ROUND((AD$34*POWER(0.99,14*(10-$A40))/2)+AD$34/2,0) -> 11 | AE29: =AE$34 -> 1 | AF29: =ROUNDUP(((AF$34*POWER(0.99,14*(10-$A40))/2)+AF$34/2)/5,0)*5 -> 55 | AG29: =ROUND((AG$34*POWER(0.99,14*(10-$A40))/2)+AG$34/2,0) -> 6 | AH29: =ROUND((AH$34*POWER(0.99,14*(10-$A40))/2)+AH$34/2,0) -> 10 | AI29: =ROUND((AI$34*POWER(0.99,14*(10-$A40))/2)+AI$34/2,0) -> 7 | AJ29: =ROUND((AJ$34*POWER(0.99,14*(10-$A40))/2)+AJ$34/2,0) -> 7 | AK29: =AK$34 -> 2
A30: 6 | B30: =ROUNDUP(((B$34*POWER(0.99,14*(10-$A52))/2)+B$34/2)/5,0)*5 -> 50 | C30: =ROUND((C$34*POWER(0.99,14*(10-$A52))/2)+C$34/2,0) -> 5 | D30: =ROUND((D$34*POWER(0.99,14*(10-$A52))/2)+D$34/2,0) -> 10 | E30: =ROUND((E$34*POWER(0.99,14*(10-$A52))/2)+E$34/2,0) -> 4 | F30: =ROUND((F$34*POWER(0.99,14*(10-$A52))/2)+F$34/2,0) -> 13 | G30: =G$34 -> 1 | H30: =ROUNDUP(((H$34*POWER(0.99,14*(10-$A52))/2)+H$34/2)/5,0)*5 -> 55 | I30: =ROUND((I$34*POWER(0.99,14*(10-$A52))/2)+I$34/2,0) -> 4 | J30: =ROUND((J$34*POWER(0.99,14*(10-$A52))/2)+J$34/2,0) -> 9 | K30: =ROUND((K$34*POWER(0.99,14*(10-$A52))/2)+K$34/2,0) -> 7 | L30: =ROUND((L$34*POWER(0.99,14*(10-$A52))/2)+L$34/2,0) -> 8 | M30: =M$34 -> 2 | N30: =ROUNDUP(((N$34*POWER(0.99,14*(10-$A52))/2)+N$34/2)/5,0)*5 -> 55 | O30: =ROUND((O$34*POWER(0.99,14*(10-$A52))/2)+O$34/2,0) -> 4 | P30: =ROUND((P$34*POWER(0.99,14*(10-$A52))/2)+P$34/2,0) -> 7 | Q30: =ROUND((Q$34*POWER(0.99,14*(10-$A52))/2)+Q$34/2,0) -> 9 | R30: =ROUND((R$34*POWER(0.99,14*(10-$A52))/2)+R$34/2,0) -> 7 | S30: =S$34 -> 1 | T30: =ROUNDUP(((T$34*POWER(0.99,14*(10-$A41))/2)+T$34/2)/5,0)*5 -> 55 | U30: =ROUND((U$34*POWER(0.99,14*(10-$A41))/2)+U$34/2,0) -> 5 | V30: =ROUND((V$34*POWER(0.99,14*(10-$A41))/2)+V$34/2,0) -> 5 | W30: =ROUND((W$34*POWER(0.99,14*(10-$A41))/2)+W$34/2,0) -> 12 | X30: =ROUND((X$34*POWER(0.99,14*(10-$A41))/2)+X$34/2,0) -> 8 | Y30: =Y$34 -> 2 | Z30: =ROUNDUP(((Z$34*POWER(0.99,14*(10-$A41))/2)+Z$34/2)/5,0)*5 -> 55 | AA30: =ROUND((AA$34*POWER(0.99,14*(10-$A41))/2)+AA$34/2,0) -> 0 | AB30: =ROUND((AB$34*POWER(0.99,14*(10-$A41))/2)+AB$34/2,0) -> 10 | AC30: =ROUND((AC$34*POWER(0.99,14*(10-$A41))/2)+AC$34/2,0) -> 12 | AD30: =ROUND((AD$34*POWER(0.99,14*(10-$A41))/2)+AD$34/2,0) -> 12 | AE30: =AE$34 -> 1 | AF30: =ROUNDUP(((AF$34*POWER(0.99,14*(10-$A41))/2)+AF$34/2)/5,0)*5 -> 55 | AG30: =ROUND((AG$34*POWER(0.99,14*(10-$A41))/2)+AG$34/2,0) -> 6 | AH30: =ROUND((AH$34*POWER(0.99,14*(10-$A41))/2)+AH$34/2,0) -> 10 | AI30: =ROUND((AI$34*POWER(0.99,14*(10-$A41))/2)+AI$34/2,0) -> 7 | AJ30: =ROUND((AJ$34*POWER(0.99,14*(10-$A41))/2)+AJ$34/2,0) -> 7 | AK30: =AK$34 -> 2
A31: 7 | B31: =ROUNDUP(((B$34*POWER(0.99,14*(10-$A53))/2)+B$34/2)/5,0)*5 -> 50 | C31: =ROUND((C$34*POWER(0.99,14*(10-$A53))/2)+C$34/2,0) -> 6 | D31: =ROUND((D$34*POWER(0.99,14*(10-$A53))/2)+D$34/2,0) -> 11 | E31: =ROUND((E$34*POWER(0.99,14*(10-$A53))/2)+E$34/2,0) -> 4 | F31: =ROUND((F$34*POWER(0.99,14*(10-$A53))/2)+F$34/2,0) -> 13 | G31: =G$34 -> 1 | H31: =ROUNDUP(((H$34*POWER(0.99,14*(10-$A53))/2)+H$34/2)/5,0)*5 -> 55 | I31: =ROUND((I$34*POWER(0.99,14*(10-$A53))/2)+I$34/2,0) -> 4 | J31: =ROUND((J$34*POWER(0.99,14*(10-$A53))/2)+J$34/2,0) -> 9 | K31: =ROUND((K$34*POWER(0.99,14*(10-$A53))/2)+K$34/2,0) -> 7 | L31: =ROUND((L$34*POWER(0.99,14*(10-$A53))/2)+L$34/2,0) -> 8 | M31: =M$34 -> 2 | N31: =ROUNDUP(((N$34*POWER(0.99,14*(10-$A53))/2)+N$34/2)/5,0)*5 -> 55 | O31: =ROUND((O$34*POWER(0.99,14*(10-$A53))/2)+O$34/2,0) -> 4 | P31: =ROUND((P$34*POWER(0.99,14*(10-$A53))/2)+P$34/2,0) -> 7 | Q31: =ROUND((Q$34*POWER(0.99,14*(10-$A53))/2)+Q$34/2,0) -> 10 | R31: =ROUND((R$34*POWER(0.99,14*(10-$A53))/2)+R$34/2,0) -> 7 | S31: =S$34 -> 1 | T31: =ROUNDUP(((T$34*POWER(0.99,14*(10-$A42))/2)+T$34/2)/5,0)*5 -> 55 | U31: =ROUND((U$34*POWER(0.99,14*(10-$A42))/2)+U$34/2,0) -> 5 | V31: =ROUND((V$34*POWER(0.99,14*(10-$A42))/2)+V$34/2,0) -> 6 | W31: =ROUND((W$34*POWER(0.99,14*(10-$A42))/2)+W$34/2,0) -> 12 | X31: =ROUND((X$34*POWER(0.99,14*(10-$A42))/2)+X$34/2,0) -> 8 | Y31: =Y$34 -> 2 | Z31: =ROUNDUP(((Z$34*POWER(0.99,14*(10-$A42))/2)+Z$34/2)/5,0)*5 -> 55 | AA31: =ROUND((AA$34*POWER(0.99,14*(10-$A42))/2)+AA$34/2,0) -> 0 | AB31: =ROUND((AB$34*POWER(0.99,14*(10-$A42))/2)+AB$34/2,0) -> 11 | AC31: =ROUND((AC$34*POWER(0.99,14*(10-$A42))/2)+AC$34/2,0) -> 12 | AD31: =ROUND((AD$34*POWER(0.99,14*(10-$A42))/2)+AD$34/2,0) -> 12 | AE31: =AE$34 -> 1 | AF31: =ROUNDUP(((AF$34*POWER(0.99,14*(10-$A42))/2)+AF$34/2)/5,0)*5 -> 60 | AG31: =ROUND((AG$34*POWER(0.99,14*(10-$A42))/2)+AG$34/2,0) -> 7 | AH31: =ROUND((AH$34*POWER(0.99,14*(10-$A42))/2)+AH$34/2,0) -> 11 | AI31: =ROUND((AI$34*POWER(0.99,14*(10-$A42))/2)+AI$34/2,0) -> 7 | AJ31: =ROUND((AJ$34*POWER(0.99,14*(10-$A42))/2)+AJ$34/2,0) -> 7 | AK31: =AK$34 -> 2
